Workbook

Sheet SETTINGS
A1: ⚡ FOREX TRADING JOURNAL — SETTINGS
A2: Configure all global parameters. Blue cells = user input. Do NOT edit black formula cells.
A4: ACCOUNT SETTINGS
A5: Account Currency | B5: USD
A6: Starting Balance | B6: 50000
A7: Current Balance | B7: =B6 -> 50000
A8: Default Risk % | B8: 0.01
A9: Max Daily Loss % | B9: 0.03
A10: Max Drawdown % | B10: 0.1
A12: PIP / POINT VALUE REFERENCE (Standard Lot = 100,000 units)
A13: Market Type | B13: Instrument Example | C13: Pip Size | D13: Pip Value / Std Lot (USD) | E13: Notes
A14: Forex Non-JPY | B14: EUR/USD, GBP/USD | C14: 0.0001 | D14: 10 | E14: 1 pip = 0.0001; $10/pip on std lot
A15: Forex JPY | B15: USD/JPY, GBP/JPY | C15: 0.01 | D15: ≈$9.09 | E15: 1 pip = 0.01; value varies w/ USD/JPY rate
A16: Gold XAUUSD | B16: XAU/USD | C16: 0.01 | D16: 1 | E16: $1/pip on std lot; 1 lot = 100 oz
A17: Indices – US | B17: US30, SPX500 | C17: 1 | D17: 1 | E17: 1 pt = $1 per mini-lot typically
A18: Indices – UK | B18: UK100 | C18: 1 | D18: £1 | E18: Currency-adjusted by broker
A19: Crypto | B19: BTC/USD | C19: 1 | D19: 1 | E19: Varies by broker contract size
A22: DROPDOWN SOURCE LISTS (Named Ranges — used by TRADE_LOG validation)
A23: Strategies | B23: Timeframes | C23: Markets | D23: Sessions | E23: Results | F23: Directions | G23: Confluences
A24: Breakout | B24: M1 | C24: EUR/USD | D24: London | E24: Win | F24: Buy | G24: Trend
A25: Trend Follow | B25: M5 | C25: GBP/USD | D25: New York | E25: Loss | F25: Sell | G25: S/R Level
A26: Mean Reversion | B26: M15 | C26: USD/JPY | D26: Asian | E26: Breakeven | G26: Fibonacci
A27: Scalp | B27: M30 | C27: GBP/JPY | D27: London/NY Overlap | E27: Partial Win | G27: Volume
A28: News Trade | B28: H1 | C28: AUD/USD | D28: Asian/London Overlap | E28: Open | G28: News
A29: Support/Resistance | B29: H4 | C29: USD/CAD | G29: Divergence
A30: ICT/SMC | B30: D1 | C30: EUR/JPY | G30: MA Cross
A31: Price Action | B31: W1 | C31: XAU/USD | G31: Order Block
A32: Harmonic | B32: MN | C32: US30 | G32: Fair Value Gap
A33: Other | C33: SPX500 | G33: BOS/CHoCH
C34: NAS100
C35: UK100
C36: Other

Sheet TRADE_LOG
A1: 📊 TRADE LOG — Complete Trade Record
A2: IDENTIFICATION | E2: INSTRUMENT | H2: SETUP | K2: ENTRY & RISK | S2: PARTIAL EXITS | AC2: RESULTS | AJ2: ANALYTICS & NOTES
A3: Trade ID | B3: Date Opened | C3: Time Opened | D3: Date Closed | E3: Market/Pair | F3: Direction | G3: Session | H3: Strategy | I3: Timeframe | J3: Confluences | K3: Entry Price | L3: Stop Loss | M3: Take Profit 1 | N3: Take Profit 2 | O3: Risk % | P3: SL Pips | Q3: Risk $ | R3: Lot Size | S3: Exit 1 Price | T3: Exit 1 % | U3: Exit 1 P/L $ | V3: Exit 2 Price | W3: Exit 2 % | X3: Exit 2 P/L $ | Y3: Exit 3 Price | Z3: Exit 3 % | AA3: Exit 3 P/L $ | AB3: Final Exit Price | AC3: Final Exit % | AD3: Wt Avg Exit | AE3: Total P/L $ | AF3: RR Ratio | AG3: R-Multiple | AH3: Result | AI3: Trade Duration | AJ3: Pips P/L | AK3: Notes | AL3: Screenshot URL | AM3: Mistakes | AN3: Emotion Score | AO3: Running Balance
A4: =IF(B4="","",ROW()-3) -> 1 | B4: 45306 | C4: 08:30 | D4: 45306 | E4: EUR/USD | F4: Buy | G4: London | H4: Trend Follow | I4: H1 | J4: Trend,S/R Level | K4: 1.0852 | L4: 1.0832 | M4: 1.09 | N4: 1.095 | O4: 0.01 | P4: =IF(K4="","",IFERROR(ABS(K4-L4)/IF(ISNUMBER(SEARCH("JPY",E4)),0.01,IF(ISNUMBER(SEARCH("XAU",E4)),0.01,IF(OR(ISNUMBER(SEARCH("30",E4)),ISNUMBER(SEARCH("500",E4)),ISNUMBER(SEARCH("100",E4))),1,0.0001))),0)) -> 20 | Q4: =IF(K4="","",SETTINGS!$B$6*O4) -> 500 | R4: =IF(K4="","",IFERROR(Q4/(P4*IF(ISNUMBER(SEARCH("JPY",E4)),9.09,IF(ISNUMBER(SEARCH("XAU",E4)),1,IF(OR(ISNUMBER(SEARCH("30",E4)),ISNUMBER(SEARCH("500",E4)),ISNUMBER(SEARCH("100",E4))),1,10)))),0)) -> 2.5 | S4: 1.0885 | T4: 0.5 | U4: =IF(OR(S4="",T4=0),"",IFERROR((S4-K4)*IF(F4="Sell",-1,1)*R4*T4*IF(ISNUMBER(SEARCH("JPY",E4)),1000,IF(ISNUMBER(SEARCH("XAU",E4)),100,IF(OR(ISNUMBER(SEARCH("30",E4)),ISNUMBER(SEARCH("500",E4)),ISNUMBER(SEARCH("100",E4))),100,100000))),0)) -> 412.5 | X4: =IF(OR(V4="",W4=0),"",IFERROR((V4-K4)*IF(F4="Sell",-1,1)*R4*W4*IF(ISNUMBER(SEARCH("JPY",E4)),1000,IF(ISNUMBER(SEARCH("XAU",E4)),100,IF(OR(ISNUMBER(SEARCH("30",E4)),ISNUMBER(SEARCH("500",E4)),ISNUMBER(SEARCH("100",E4))),100,100000))),0)) | AA4: =IF(OR(Y4="",Z4=0),"",IFERROR((Y4-K4)*IF(F4="Sell",-1,1)*R4*Z4*IF(ISNUMBER(SEARCH("JPY",E4)),1000,IF(ISNUMBER(SEARCH("XAU",E4)),100,IF(OR(ISNUMBER(SEARCH("30",E4)),ISNUMBER(SEARCH("500",E4)),ISNUMBER(SEARCH("100",E4))),100,100000))),0)) | AB4: 1.091 | AC4: =IF(K4="","",1-IFERROR(T4,0)-IFERROR(W4,0)-IFERROR(Z4,0)) -> 0.5 | AD4: =IF(AB4="","",IFERROR((IFERROR(S4*T4,0)+IFERROR(V4*W4,0)+IFERROR(Y4*Z4,0)+AB4*AC4)/(IFERROR(T4,0)+IFERROR(W4,0)+IFERROR(Z4,0)+AC4),AB4)) -> 1.08975 | AE4: =IF(AB4="","",IF(U4="",0,U4)+IF(X4="",0,X4)+IF(AA4="",0,AA4)+IFERROR((AB4-K4)*IF(F4="Sell",-1,1)*R4*AC4*IF(ISNUMBER(SEARCH("JPY",E4)),1000,IF(ISNUMBER(SEARCH("XAU",E4)),100,IF(OR(ISNUMBER(SEARCH("30",E4)),ISNUMBER(SEARCH("500",E4)),ISNUMBER(SEARCH("100",E4))),100,100000))),0)) -> 1137.5 | AF4: =IF(OR(K4="",M4="",L4=""),"",IFERROR(ABS(M4-K4)/ABS(K4-L4),0)) -> 2.4 | AG4: =IF(OR(AE4="",AE4=0,Q4=0,Q4=""),"",IFERROR(AE4/Q4,0)) -> 2.275 | AH4: =IF(AB4="","Open",IF(AG4="","Open",IF(AG4>0.1,"Win",IF(AG4<-0.1,"Loss","Breakeven")))) -> Win | AI4: =IF(OR(B4="",D4=""),"",D4-B4) -> 0 | AJ4: =IF(AD4="","",IFERROR((AD4-K4)*IF(F4="Sell",-1,1)/IF(ISNUMBER(SEARCH("JPY",E4)),0.01,IF(ISNUMBER(SEARCH("XAU",E4)),0.01,IF(OR(ISNUMBER(SEARCH("30",E4)),ISNUMBER(SEARCH("500",E4)),ISNUMBER(SEARCH("100",E4))),1,0.0001))),0)) -> 45.5 | AK4: Clean breakout setup | AN4: 7 | AO4: =IF(AE4="","",SETTINGS!$B$6+IF(AE4="",0,AE4)) -> 51137.5
A5: =IF(B5="","",ROW()-3) -> 2 | B5: 45307 | C5: 10:15 | D5: 45307 | E5: GBP/USD | F5: Sell | G5: London/NY Overlap | H5: Price Action | I5: H4 | J5: S/R Level,BOS/CHoCH | K5: 1.2765 | L5: 1.2795 | M5: 1.271 | N5: 1.268 | O5: 0.01 | P5: =IF(K5="","",IFERROR(ABS(K5-L5)/IF(ISNUMBER(SEARCH("JPY",E5)),0.01,IF(ISNUMBER(SEARCH("XAU",E5)),0.01,IF(OR(ISNUMBER(SEARCH("30",E5)),ISNUMBER(SEARCH("500",E5)),ISNUMBER(SEARCH("100",E5))),1,0.0001))),0)) -> 30 | Q5: =IF(K5="","",SETTINGS!$B$6*O5) -> 500 | R5: =IF(K5="","",IFERROR(Q5/(P5*IF(ISNUMBER(SEARCH("JPY",E5)),9.09,IF(ISNUMBER(SEARCH("XAU",E5)),1,IF(OR(ISNUMBER(SEARCH("30",E5)),ISNUMBER(SEARCH("500",E5)),ISNUMBER(SEARCH("100",E5))),1,10)))),0)) -> 1.6666667 | T5: 0 | U5: =IF(OR(S5="",T5=0),"",IFERROR((S5-K5)*IF(F5="Sell",-1,1)*R5*T5*IF(ISNUMBER(SEARCH("JPY",E5)),1000,IF(ISNUMBER(SEARCH("XAU",E5)),100,IF(OR(ISNUMBER(SEARCH("30",E5)),ISNUMBER(SEARCH("500",E5)),ISNUMBER(SEARCH("100",E5))),100,100000))),0)) | X5: =IF(OR(V5="",W5=0),"",IFERROR((V5-K5)*IF(F5="Sell",-1,1)*R5*W5*IF(ISNUMBER(SEARCH("JPY",E5)),1000,IF(ISNUMBER(SEARCH("XAU",E5)),100,IF(OR(ISNUMBER(SEARCH("30",E5)),ISNUMBER(SEARCH("500",E5)),ISNUMBER(SEARCH("100",E5))),100,100000))),0)) | AA5: =IF(OR(Y5="",Z5=0),"",IFERROR((Y5-K5)*IF(F5="Sell",-1,1)*R5*Z5*IF(ISNUMBER(SEARCH("JPY",E5)),1000,IF(ISNUMBER(SEARCH("XAU",E5)),100,IF(OR(ISNUMBER(SEARCH("30",E5)),ISNUMBER(SEARCH("500",E5)),ISNUMBER(SEARCH("100",E5))),100,100000))),0)) | AB5: 1.271 | AC5: =IF(K5="","",1-IFERROR(T5,0)-IFERROR(W5,0)-IFERROR(Z5,0)) -> 1 | AD5: =IF(AB5="","",IFERROR((IFERROR(S5*T5,0)+IFERROR(V5*W5,0)+IFERROR(Y5*Z5,0)+AB5*AC5)/(IFERROR(T5,0)+IFERROR(W5,0)+IFERROR(Z5,0)+AC5),AB5)) -> 1.271 | AE5: =IF(AB5="","",IF(U5="",0,U5)+IF(X5="",0,X5)+IF(AA5="",0,AA5)+IFERROR((AB5-K5)*IF(F5="Sell",-1,1)*R5*AC5*IF(ISNUMBER(SEARCH("JPY",E5)),1000,IF(ISNUMBER(SEARCH("XAU",E5)),100,IF(OR(ISNUMBER(SEARCH("30",E5)),ISNUMBER(SEARCH("500",E5)),ISNUMBER(SEARCH("100",E5))),100,100000))),0)) -> 916.66667 | AF5: =IF(OR(K5="",M5="",L5=""),"",IFERROR(ABS(M5-K5)/ABS(K5-L5),0)) -> 1.8333333 | AG5: =IF(OR(AE5="",AE5=0,Q5=0,Q5=""),"",IFERROR(AE5/Q5,0)) -> 1.8333333 | AH5: =IF(AB5="","Open",IF(AG5="","Open",IF(AG5>0.1,"Win",IF(AG5<-0.1,"Loss","Breakeven")))) -> Win | AI5: =IF(OR(B5="",D5=""),"",D5-B5) -> 0 | AJ5: =IF(AD5="","",IFERROR((AD5-K5)*IF(F5="Sell",-1,1)/IF(ISNUMBER(SEARCH("JPY",E5)),0.01,IF(ISNUMBER(SEARCH("XAU",E5)),0.01,IF(OR(ISNUMBER(SEARCH("30",E5)),ISNUMBER(SEARCH("500",E5)),ISNUMBER(SEARCH("100",E5))),1,0.0001))),0)) -> 55 | AK5: Double top rejection | AN5: 6 | AO5: =IF(AE5="","",IFERROR(IF(AO4="",SETTINGS!$B$6,AO4),SETTINGS!$B$6)+IF(AE5="",0,AE5)) -> 52054.167
A6: =IF(B6="","",ROW()-3) -> 3 | B6: 45308 | C6: 14:00 | D6: 45309 | E6: XAU/USD | F6: Buy | G6: New York | H6: Breakout | I6: H1 | J6: Trend,Volume | K6: 2025.5 | L6: 2018 | M6: 2040 | N6: 2055 | O6: 0.015 | P6: =IF(K6="","",IFERROR(ABS(K6-L6)/IF(ISNUMBER(SEARCH("JPY",E6)),0.01,IF(ISNUMBER(SEARCH("XAU",E6)),0.01,IF(OR(ISNUMBER(SEARCH("30",E6)),ISNUMBER(SEARCH("500",E6)),ISNUMBER(SEARCH("100",E6))),1,0.0001))),0)) -> 750 | Q6: =IF(K6="","",SETTINGS!$B$6*O6) -> 750 | R6: =IF(K6="","",IFERROR(Q6/(P6*IF(ISNUMBER(SEARCH("JPY",E6)),9.09,IF(ISNUMBER(SEARCH("XAU",E6)),1,IF(OR(ISNUMBER(SEARCH("30",E6)),ISNUMBER(SEARCH("500",E6)),ISNUMBER(SEARCH("100",E6))),1,10)))),0)) -> 1 | S6: 2038 | T6: 0.4 | U6: =IF(OR(S6="",T6=0),"",IFERROR((S6-K6)*IF(F6="Sell",-1,1)*R6*T6*IF(ISNUMBER(SEARCH("JPY",E6)),1000,IF(ISNUMBER(SEARCH("XAU",E6)),100,IF(OR(ISNUMBER(SEARCH("30",E6)),ISNUMBER(SEARCH("500",E6)),ISNUMBER(SEARCH("100",E6))),100,100000))),0)) -> 500 | V6: 2045 | W6: 0.35 | X6: =IF(OR(V6="",W6=0),"",IFERROR((V6-K6)*IF(F6="Sell",-1,1)*R6*W6*IF(ISNUMBER(SEARCH("JPY",E6)),1000,IF(ISNUMBER(SEARCH("XAU",E6)),100,IF(OR(ISNUMBER(SEARCH("30",E6)),ISNUMBER(SEARCH("500",E6)),ISNUMBER(SEARCH("100",E6))),100,100000))),0)) -> 682.5 | AA6: =IF(OR(Y6="",Z6=0),"",IFERROR((Y6-K6)*IF(F6="Sell",-1,1)*R6*Z6*IF(ISNUMBER(SEARCH("JPY",E6)),1000,IF(ISNUMBER(SEARCH("XAU",E6)),100,IF(OR(ISNUMBER(SEARCH("30",E6)),ISNUMBER(SEARCH("500",E6)),ISNUMBER(SEARCH("100",E6))),100,100000))),0)) | AB6: 2050 | AC6: =IF(K6="","",1-IFERROR(T6,0)-IFERROR(W6,0)-IFERROR(Z6,0)) -> 0.25 | AD6: =IF(AB6="","",IFERROR((IFERROR(S6*T6,0)+IFERROR(V6*W6,0)+IFERROR(Y6*Z6,0)+AB6*AC6)/(IFERROR(T6,0)+IFERROR(W6,0)+IFERROR(Z6,0)+AC6),AB6)) -> 2043.45 | AE6: =IF(AB6="","",IF(U6="",0,U6)+IF(X6="",0,X6)+IF(AA6="",0,AA6)+IFERROR((AB6-K6)*IF(F6="Sell",-1,1)*R6*AC6*IF(ISNUMBER(SEARCH("JPY",E6)),1000,IF(ISNUMBER(SEARCH("XAU",E6)),100,IF(OR(ISNUMBER(SEARCH("30",E6)),ISNUMBER(SEARCH("500",E6)),ISNUMBER(SEARCH("100",E6))),100,100000))),0)) -> 1795 | AF6: =IF(OR(K6="",M6="",L6=""),"",IFERROR(ABS(M6-K6)/ABS(K6-L6),0)) -> 1.9333333 | AG6: =IF(OR(AE6="",AE6=0,Q6=0,Q6=""),"",IFERROR(AE6/Q6,0)) -> 2.3933333 | AH6: =IF(AB6="","Open",IF(AG6="","Open",IF(AG6>0.1,"Win",IF(AG6<-0.1,"Loss","Breakeven")))) -> Win | AI6: =IF(OR(B6="",D6=""),"",D6-B6) -> 1 | AJ6: =IF(AD6="","",IFERROR((AD6-K6)*IF(F6="Sell",-1,1)/IF(ISNUMBER(SEARCH("JPY",E6)),0.01,IF(ISNUMBER(SEARCH("XAU",E6)),0.01,IF(OR(ISNUMBER(SEARCH("30",E6)),ISNUMBER(SEARCH("500",E6)),ISNUMBER(SEARCH("100",E6))),1,0.0001))),0)) -> 1795 | AK6: Gold trending strongly | AN6: 8 | AO6: =IF(AE6="","",IFERROR(IF(AO5="",SETTINGS!$B$6,AO5),SETTINGS!$B$6)+IF(AE6="",0,AE6)) -> 53849.167
A7: =IF(B7="","",ROW()-3) -> 4 | B7: 45309 | C7: 09:00 | D7: 45309 | E7: USD/JPY | F7: Sell | G7: Asian | H7: Mean Reversion | I7: M15 | J7: S/R Level,Divergence | K7: 148.25 | L7: 148.65 | M7: 147.5 | O7: 0.01 | P7: =IF(K7="","",IFERROR(ABS(K7-L7)/IF(ISNUMBER(SEARCH("JPY",E7)),0.01,IF(ISNUMBER(SEARCH("XAU",E7)),0.01,IF(OR(ISNUMBER(SEARCH("30",E7)),ISNUMBER(SEARCH("500",E7)),ISNUMBER(SEARCH("100",E7))),1,0.0001))),0)) -> 40 | Q7: =IF(K7="","",SETTINGS!$B$6*O7) -> 500 | R7: =IF(K7="","",IFERROR(Q7/(P7*IF(ISNUMBER(SEARCH("JPY",E7)),9.09,IF(ISNUMBER(SEARCH("XAU",E7)),1,IF(OR(ISNUMBER(SEARCH("30",E7)),ISNUMBER(SEARCH("500",E7)),ISNUMBER(SEARCH("100",E7))),1,10)))),0)) -> 1.3751375 | T7: 0 | U7: =IF(OR(S7="",T7=0),"",IFERROR((S7-K7)*IF(F7="Sell",-1,1)*R7*T7*IF(ISNUMBER(SEARCH("JPY",E7)),1000,IF(ISNUMBER(SEARCH("XAU",E7)),100,IF(OR(ISNUMBER(SEARCH("30",E7)),ISNUMBER(SEARCH("500",E7)),ISNUMBER(SEARCH("100",E7))),100,100000))),0)) | X7: =IF(OR(V7="",W7=0),"",IFERROR((V7-K7)*IF(F7="Sell",-1,1)*R7*W7*IF(ISNUMBER(SEARCH("JPY",E7)),1000,IF(ISNUMBER(SEARCH("XAU",E7)),100,IF(OR(ISNUMBER(SEARCH("30",E7)),ISNUMBER(SEARCH("500",E7)),ISNUMBER(SEARCH("100",E7))),100,100000))),0)) | AA7: =IF(OR(Y7="",Z7=0),"",IFERROR((Y7-K7)*IF(F7="Sell",-1,1)*R7*Z7*IF(ISNUMBER(SEARCH("JPY",E7)),1000,IF(ISNUMBER(SEARCH("XAU",E7)),100,IF(OR(ISNUMBER(SEARCH("30",E7)),ISNUMBER(SEARCH("500",E7)),ISNUMBER(SEARCH("100",E7))),100,100000))),0)) | AB7: 147.8 | AC7: =IF(K7="","",1-IFERROR(T7,0)-IFERROR(W7,0)-IFERROR(Z7,0)) -> 1 | AD7: =IF(AB7="","",IFERROR((IFERROR(S7*T7,0)+IFERROR(V7*W7,0)+IFERROR(Y7*Z7,0)+AB7*AC7)/(IFERROR(T7,0)+IFERROR(W7,0)+IFERROR(Z7,0)+AC7),AB7)) -> 147.8 | AE7: =IF(AB7="","",IF(U7="",0,U7)+IF(X7="",0,X7)+IF(AA7="",0,AA7)+IFERROR((AB7-K7)*IF(F7="Sell",-1,1)*R7*AC7*IF(ISNUMBER(SEARCH("JPY",E7)),1000,IF(ISNUMBER(SEARCH("XAU",E7)),100,IF(OR(ISNUMBER(SEARCH("30",E7)),ISNUMBER(SEARCH("500",E7)),ISNUMBER(SEARCH("100",E7))),100,100000))),0)) -> 618.81188 | AF7: =IF(OR(K7="",M7="",L7=""),"",IFERROR(ABS(M7-K7)/ABS(K7-L7),0)) -> 1.875 | AG7: =IF(OR(AE7="",AE7=0,Q7=0,Q7=""),"",IFERROR(AE7/Q7,0)) -> 1.2376238 | AH7: =IF(AB7="","Open",IF(AG7="","Open",IF(AG7>0.1,"Win",IF(AG7<-0.1,"Loss","Breakeven")))) -> Win | AI7: =IF(OR(B7="",D7=""),"",D7-B7) -> 0 | AJ7: =IF(AD7="","",IFERROR((AD7-K7)*IF(F7="Sell",-1,1)/IF(ISNUMBER(SEARCH("JPY",E7)),0.01,IF(ISNUMBER(SEARCH("XAU",E7)),0.01,IF(OR(ISNUMBER(SEARCH("30",E7)),ISNUMBER(SEARCH("500",E7)),ISNUMBER(SEARCH("100",E7))),1,0.0001))),0)) -> 45 | AK7: Quick scalp at resistance | AN7: 5 | AO7: =IF(AE7="","",IFERROR(IF(AO6="",SETTINGS!$B$6,AO6),SETTINGS!$B$6)+IF(AE7="",0,AE7)) -> 54467.979
A8: =IF(B8="","",ROW()-3) -> 5 | B8: 45313 | C8: 08:45 | D8: 45313 | E8: EUR/USD | F8: Buy | G8: London | H8: ICT/SMC | I8: H1 | J8: Order Block,Fair Value Gap | K8: 1.0879 | L8: 1.0859 | M8: 1.092 | O8: 0.01 | P8: =IF(K8="","",IFERROR(ABS(K8-L8)/IF(ISNUMBER(SEARCH("JPY",E8)),0.01,IF(ISNUMBER(SEARCH("XAU",E8)),0.01,IF(OR(ISNUMBER(SEARCH("30",E8)),ISNUMBER(SEARCH("500",E8)),ISNUMBER(SEARCH("100",E8))),1,0.0001))),0)) -> 20 | Q8: =IF(K8="","",SETTINGS!$B$6*O8) -> 500 | R8: =IF(K8="","",IFERROR(Q8/(P8*IF(ISNUMBER(SEARCH("JPY",E8)),9.09,IF(ISNUMBER(SEARCH("XAU",E8)),1,IF(OR(ISNUMBER(SEARCH("30",E8)),ISNUMBER(SEARCH("500",E8)),ISNUMBER(SEARCH("100",E8))),1,10)))),0)) -> 2.5 | S8: 1.0905 | T8: 0.6 | U8: =IF(OR(S8="",T8=0),"",IFERROR((S8-K8)*IF(F8="Sell",-1,1)*R8*T8*IF(ISNUMBER(SEARCH("JPY",E8)),1000,IF(ISNUMBER(SEARCH("XAU",E8)),100,IF(OR(ISNUMBER(SEARCH("30",E8)),ISNUMBER(SEARCH("500",E8)),ISNUMBER(SEARCH("100",E8))),100,100000))),0)) -> 390 | X8: =IF(OR(V8="",W8=0),"",IFERROR((V8-K8)*IF(F8="Sell",-1,1)*R8*W8*IF(ISNUMBER(SEARCH("JPY",E8)),1000,IF(ISNUMBER(SEARCH("XAU",E8)),100,IF(OR(ISNUMBER(SEARCH("30",E8)),ISNUMBER(SEARCH("500",E8)),ISNUMBER(SEARCH("100",E8))),100,100000))),0)) | AA8: =IF(OR(Y8="",Z8=0),"",IFERROR((Y8-K8)*IF(F8="Sell",-1,1)*R8*Z8*IF(ISNUMBER(SEARCH("JPY",E8)),1000,IF(ISNUMBER(SEARCH("XAU",E8)),100,IF(OR(ISNUMBER(SEARCH("30",E8)),ISNUMBER(SEARCH("500",E8)),ISNUMBER(SEARCH("100",E8))),100,100000))),0)) | AB8: 1.0915 | AC8: =IF(K8="","",1-IFERROR(T8,0)-IFERROR(W8,0)-IFERROR(Z8,0)) -> 0.4 | AD8: =IF(AB8="","",IFERROR((IFERROR(S8*T8,0)+IFERROR(V8*W8,0)+IFERROR(Y8*Z8,0)+AB8*AC8)/(IFERROR(T8,0)+IFERROR(W8,0)+IFERROR(Z8,0)+AC8),AB8)) -> 1.0909 | AE8: =IF(AB8="","",IF(U8="",0,U8)+IF(X8="",0,X8)+IF(AA8="",0,AA8)+IFERROR((AB8-K8)*IF(F8="Sell",-1,1)*R8*AC8*IF(ISNUMBER(SEARCH("JPY",E8)),1000,IF(ISNUMBER(SEARCH("XAU",E8)),100,IF(OR(ISNUMBER(SEARCH("30",E8)),ISNUMBER(SEARCH("500",E8)),ISNUMBER(SEARCH("100",E8))),100,100000))),0)) -> 750 | AF8: =IF(OR(K8="",M8="",L8=""),"",IFERROR(ABS(M8-K8)/ABS(K8-L8),0)) -> 2.05 | AG8: =IF(OR(AE8="",AE8=0,Q8=0,Q8=""),"",IFERROR(AE8/Q8,0)) -> 1.5 | AH8: =IF(AB8="","Open",IF(AG8="","Open",IF(AG8>0.1,"Win",IF(AG8<-0.1,"Loss","Breakeven")))) -> Win | AI8: =IF(OR(B8="",D8=""),"",D8-B8) -> 0 | AJ8: =IF(AD8="","",IFERROR((AD8-K8)*IF(F8="Sell",-1,1)/IF(ISNUMBER(SEARCH("JPY",E8)),0.01,IF(ISNUMBER(SEARCH("XAU",E8)),0.01,IF(OR(ISNUMBER(SEARCH("30",E8)),ISNUMBER(SEARCH("500",E8)),ISNUMBER(SEARCH("100",E8))),1,0.0001))),0)) -> 30 | AK8: FVG entry off London open | AN8: 9 | AO8: =IF(AE8="","",IFERROR(IF(AO7="",SETTINGS!$B$6,AO7),SETTINGS!$B$6)+IF(AE8="",0,AE8)) -> 55217.979
A9: =IF(B9="","",ROW()-3) | P9: =IF(K9="","",IFERROR(ABS(K9-L9)/IF(ISNUMBER(SEARCH("JPY",E9)),0.01,IF(ISNUMBER(SEARCH("XAU",E9)),0.01,IF(OR(ISNUMBER(SEARCH("30",E9)),ISNUMBER(SEARCH("500",E9)),ISNUMBER(SEARCH("100",E9))),1,0.0001))),0)) | Q9: =IF(K9="","",SETTINGS!$B$6*O9) | R9: =IF(K9="","",IFERROR(Q9/(P9*IF(ISNUMBER(SEARCH("JPY",E9)),9.09,IF(ISNUMBER(SEARCH("XAU",E9)),1,IF(OR(ISNUMBER(SEARCH("30",E9)),ISNUMBER(SEARCH("500",E9)),ISNUMBER(SEARCH("100",E9))),1,10)))),0)) | U9: =IF(OR(S9="",T9=0),"",IFERROR((S9-K9)*IF(F9="Sell",-1,1)*R9*T9*IF(ISNUMBER(SEARCH("JPY",E9)),1000,IF(ISNUMBER(SEARCH("XAU",E9)),100,IF(OR(ISNUMBER(SEARCH("30",E9)),ISNUMBER(SEARCH("500",E9)),ISNUMBER(SEARCH("100",E9))),100,100000))),0)) | X9: =IF(OR(V9="",W9=0),"",IFERROR((V9-K9)*IF(F9="Sell",-1,1)*R9*W9*IF(ISNUMBER(SEARCH("JPY",E9)),1000,IF(ISNUMBER(SEARCH("XAU",E9)),100,IF(OR(ISNUMBER(SEARCH("30",E9)),ISNUMBER(SEARCH("500",E9)),ISNUMBER(SEARCH("100",E9))),100,100000))),0)) | AA9: =IF(OR(Y9="",Z9=0),"",IFERROR((Y9-K9)*IF(F9="Sell",-1,1)*R9*Z9*IF(ISNUMBER(SEARCH("JPY",E9)),1000,IF(ISNUMBER(SEARCH("XAU",E9)),100,IF(OR(ISNUMBER(SEARCH("30",E9)),ISNUMBER(SEARCH("500",E9)),ISNUMBER(SEARCH("100",E9))),100,100000))),0)) | AC9: =IF(K9="","",1-IFERROR(T9,0)-IFERROR(W9,0)-IFERROR(Z9,0)) | AD9: =IF(AB9="","",IFERROR((IFERROR(S9*T9,0)+IFERROR(V9*W9,0)+IFERROR(Y9*Z9,0)+AB9*AC9)/(IFERROR(T9,0)+IFERROR(W9,0)+IFERROR(Z9,0)+AC9),AB9)) | AE9: =IF(AB9="","",IF(U9="",0,U9)+IF(X9="",0,X9)+IF(AA9="",0,AA9)+IFERROR((AB9-K9)*IF(F9="Sell",-1,1)*R9*AC9*IF(ISNUMBER(SEARCH("JPY",E9)),1000,IF(ISNUMBER(SEARCH("XAU",E9)),100,IF(OR(ISNUMBER(SEARCH("30",E9)),ISNUMBER(SEARCH("500",E9)),ISNUMBER(SEARCH("100",E9))),100,100000))),0)) | AF9: =IF(OR(K9="",M9="",L9=""),"",IFERROR(ABS(M9-K9)/ABS(K9-L9),0)) | AG9: =IF(OR(AE9="",AE9=0,Q9=0,Q9=""),"",IFERROR(AE9/Q9,0)) | AH9: =IF(AB9="","Open",IF(AG9="","Open",IF(AG9>0.1,"Win",IF(AG9<-0.1,"Loss","Breakeven")))) -> Open | AI9: =IF(OR(B9="",D9=""),"",D9-B9) | AJ9: =IF(AD9="","",IFERROR((AD9-K9)*IF(F9="Sell",-1,1)/IF(ISNUMBER(SEARCH("JPY",E9)),0.01,IF(ISNUMBER(SEARCH("XAU",E9)),0.01,IF(OR(ISNUMBER(SEARCH("30",E9)),ISNUMBER(SEARCH("500",E9)),ISNUMBER(SEARCH("100",E9))),1,0.0001))),0)) | AO9: =IF(AE9="","",IFERROR(IF(AO8="",SETTINGS!$B$6,AO8),SETTINGS!$B$6)+IF(AE9="",0,AE9))
A10: =IF(B10="","",ROW()-3) | P10: =IF(K10="","",IFERROR(ABS(K10-L10)/IF(ISNUMBER(SEARCH("JPY",E10)),0.01,IF(ISNUMBER(SEARCH("XAU",E10)),0.01,IF(OR(ISNUMBER(SEARCH("30",E10)),ISNUMBER(SEARCH("500",E10)),ISNUMBER(SEARCH("100",E10))),1,0.0001))),0)) | Q10: =IF(K10="","",SETTINGS!$B$6*O10) | R10: =IF(K10="","",IFERROR(Q10/(P10*IF(ISNUMBER(SEARCH("JPY",E10)),9.09,IF(ISNUMBER(SEARCH("XAU",E10)),1,IF(OR(ISNUMBER(SEARCH("30",E10)),ISNUMBER(SEARCH("500",E10)),ISNUMBER(SEARCH("100",E10))),1,10)))),0)) | U10: =IF(OR(S10="",T10=0),"",IFERROR((S10-K10)*IF(F10="Sell",-1,1)*R10*T10*IF(ISNUMBER(SEARCH("JPY",E10)),1000,IF(ISNUMBER(SEARCH("XAU",E10)),100,IF(OR(ISNUMBER(SEARCH("30",E10)),ISNUMBER(SEARCH("500",E10)),ISNUMBER(SEARCH("100",E10))),100,100000))),0)) | X10: =IF(OR(V10="",W10=0),"",IFERROR((V10-K10)*IF(F10="Sell",-1,1)*R10*W10*IF(ISNUMBER(SEARCH("JPY",E10)),1000,IF(ISNUMBER(SEARCH("XAU",E10)),100,IF(OR(ISNUMBER(SEARCH("30",E10)),ISNUMBER(SEARCH("500",E10)),ISNUMBER(SEARCH("100",E10))),100,100000))),0)) | AA10: =IF(OR(Y10="",Z10=0),"",IFERROR((Y10-K10)*IF(F10="Sell",-1,1)*R10*Z10*IF(ISNUMBER(SEARCH("JPY",E10)),1000,IF(ISNUMBER(SEARCH("XAU",E10)),100,IF(OR(ISNUMBER(SEARCH("30",E10)),ISNUMBER(SEARCH("500",E10)),ISNUMBER(SEARCH("100",E10))),100,100000))),0)) | AC10: =IF(K10="","",1-IFERROR(T10,0)-IFERROR(W10,0)-IFERROR(Z10,0)) | AD10: =IF(AB10="","",IFERROR((IFERROR(S10*T10,0)+IFERROR(V10*W10,0)+IFERROR(Y10*Z10,0)+AB10*AC10)/(IFERROR(T10,0)+IFERROR(W10,0)+IFERROR(Z10,0)+AC10),AB10)) | AE10: =IF(AB10="","",IF(U10="",0,U10)+IF(X10="",0,X10)+IF(AA10="",0,AA10)+IFERROR((AB10-K10)*IF(F10="Sell",-1,1)*R10*AC10*IF(ISNUMBER(SEARCH("JPY",E10)),1000,IF(ISNUMBER(SEARCH("XAU",E10)),100,IF(OR(ISNUMBER(SEARCH("30",E10)),ISNUMBER(SEARCH("500",E10)),ISNUMBER(SEARCH("100",E10))),100,100000))),0)) | AF10: =IF(OR(K10="",M10="",L10=""),"",IFERROR(ABS(M10-K10)/ABS(K10-L10),0)) | AG10: =IF(OR(AE10="",AE10=0,Q10=0,Q10=""),"",IFERROR(AE10/Q10,0)) | AH10: =IF(AB10="","Open",IF(AG10="","Open",IF(AG10>0.1,"Win",IF(AG10<-0.1,"Loss","Breakeven")))) -> Open | AI10: =IF(OR(B10="",D10=""),"",D10-B10) | AJ10: =IF(AD10="","",IFERROR((AD10-K10)*IF(F10="Sell",-1,1)/IF(ISNUMBER(SEARCH("JPY",E10)),0.01,IF(ISNUMBER(SEARCH("XAU",E10)),0.01,IF(OR(ISNUMBER(SEARCH("30",E10)),ISNUMBER(SEARCH("500",E10)),ISNUMBER(SEARCH("100",E10))),1,0.0001))),0)) | AO10: =IF(AE10="","",IFERROR(IF(AO9="",SETTINGS!$B$6,AO9),SETTINGS!$B$6)+IF(AE10="",0,AE10))
A11: =IF(B11="","",ROW()-3) | P11: =IF(K11="","",IFERROR(ABS(K11-L11)/IF(ISNUMBER(SEARCH("JPY",E11)),0.01,IF(ISNUMBER(SEARCH("XAU",E11)),0.01,IF(OR(ISNUMBER(SEARCH("30",E11)),ISNUMBER(SEARCH("500",E11)),ISNUMBER(SEARCH("100",E11))),1,0.0001))),0)) | Q11: =IF(K11="","",SETTINGS!$B$6*O11) | R11: =IF(K11="","",IFERROR(Q11/(P11*IF(ISNUMBER(SEARCH("JPY",E11)),9.09,IF(ISNUMBER(SEARCH("XAU",E11)),1,IF(OR(ISNUMBER(SEARCH("30",E11)),ISNUMBER(SEARCH("500",E11)),ISNUMBER(SEARCH("100",E11))),1,10)))),0)) | U11: =IF(OR(S11="",T11=0),"",IFERROR((S11-K11)*IF(F11="Sell",-1,1)*R11*T11*IF(ISNUMBER(SEARCH("JPY",E11)),1000,IF(ISNUMBER(SEARCH("XAU",E11)),100,IF(OR(ISNUMBER(SEARCH("30",E11)),ISNUMBER(SEARCH("500",E11)),ISNUMBER(SEARCH("100",E11))),100,100000))),0)) | X11: =IF(OR(V11="",W11=0),"",IFERROR((V11-K11)*IF(F11="Sell",-1,1)*R11*W11*IF(ISNUMBER(SEARCH("JPY",E11)),1000,IF(ISNUMBER(SEARCH("XAU",E11)),100,IF(OR(ISNUMBER(SEARCH("30",E11)),ISNUMBER(SEARCH("500",E11)),ISNUMBER(SEARCH("100",E11))),100,100000))),0)) | AA11: =IF(OR(Y11="",Z11=0),"",IFERROR((Y11-K11)*IF(F11="Sell",-1,1)*R11*Z11*IF(ISNUMBER(SEARCH("JPY",E11)),1000,IF(ISNUMBER(SEARCH("XAU",E11)),100,IF(OR(ISNUMBER(SEARCH("30",E11)),ISNUMBER(SEARCH("500",E11)),ISNUMBER(SEARCH("100",E11))),100,100000))),0)) | AC11: =IF(K11="","",1-IFERROR(T11,0)-IFERROR(W11,0)-IFERROR(Z11,0)) | AD11: =IF(AB11="","",IFERROR((IFERROR(S11*T11,0)+IFERROR(V11*W11,0)+IFERROR(Y11*Z11,0)+AB11*AC11)/(IFERROR(T11,0)+IFERROR(W11,0)+IFERROR(Z11,0)+AC11),AB11)) | AE11: =IF(AB11="","",IF(U11="",0,U11)+IF(X11="",0,X11)+IF(AA11="",0,AA11)+IFERROR((AB11-K11)*IF(F11="Sell",-1,1)*R11*AC11*IF(ISNUMBER(SEARCH("JPY",E11)),1000,IF(ISNUMBER(SEARCH("XAU",E11)),100,IF(OR(ISNUMBER(SEARCH("30",E11)),ISNUMBER(SEARCH("500",E11)),ISNUMBER(SEARCH("100",E11))),100,100000))),0)) | AF11: =IF(OR(K11="",M11="",L11=""),"",IFERROR(ABS(M11-K11)/ABS(K11-L11),0)) | AG11: =IF(OR(AE11="",AE11=0,Q11=0,Q11=""),"",IFERROR(AE11/Q11,0)) | AH11: =IF(AB11="","Open",IF(AG11="","Open",IF(AG11>0.1,"Win",IF(AG11<-0.1,"Loss","Breakeven")))) -> Open | AI11: =IF(OR(B11="",D11=""),"",D11-B11) | AJ11: =IF(AD11="","",IFERROR((AD11-K11)*IF(F11="Sell",-1,1)/IF(ISNUMBER(SEARCH("JPY",E11)),0.01,IF(ISNUMBER(SEARCH("XAU",E11)),0.01,IF(OR(ISNUMBER(SEARCH("30",E11)),ISNUMBER(SEARCH("500",E11)),ISNUMBER(SEARCH("100",E11))),1,0.0001))),0)) | AO11: =IF(AE11="","",IFERROR(IF(AO10="",SETTINGS!$B$6,AO10),SETTINGS!$B$6)+IF(AE11="",0,AE11))
A12: =IF(B12="","",ROW()-3) | P12: =IF(K12="","",IFERROR(ABS(K12-L12)/IF(ISNUMBER(SEARCH("JPY",E12)),0.01,IF(ISNUMBER(SEARCH("XAU",E12)),0.01,IF(OR(ISNUMBER(SEARCH("30",E12)),ISNUMBER(SEARCH("500",E12)),ISNUMBER(SEARCH("100",E12))),1,0.0001))),0)) | Q12: =IF(K12="","",SETTINGS!$B$6*O12) | R12: =IF(K12="","",IFERROR(Q12/(P12*IF(ISNUMBER(SEARCH("JPY",E12)),9.09,IF(ISNUMBER(SEARCH("XAU",E12)),1,IF(OR(ISNUMBER(SEARCH("30",E12)),ISNUMBER(SEARCH("500",E12)),ISNUMBER(SEARCH("100",E12))),1,10)))),0)) | U12: =IF(OR(S12="",T12=0),"",IFERROR((S12-K12)*IF(F12="Sell",-1,1)*R12*T12*IF(ISNUMBER(SEARCH("JPY",E12)),1000,IF(ISNUMBER(SEARCH("XAU",E12)),100,IF(OR(ISNUMBER(SEARCH("30",E12)),ISNUMBER(SEARCH("500",E12)),ISNUMBER(SEARCH("100",E12))),100,100000))),0)) | X12: =IF(OR(V12="",W12=0),"",IFERROR((V12-K12)*IF(F12="Sell",-1,1)*R12*W12*IF(ISNUMBER(SEARCH("JPY",E12)),1000,IF(ISNUMBER(SEARCH("XAU",E12)),100,IF(OR(ISNUMBER(SEARCH("30",E12)),ISNUMBER(SEARCH("500",E12)),ISNUMBER(SEARCH("100",E12))),100,100000))),0)) | AA12: =IF(OR(Y12="",Z12=0),"",IFERROR((Y12-K12)*IF(F12="Sell",-1,1)*R12*Z12*IF(ISNUMBER(SEARCH("JPY",E12)),1000,IF(ISNUMBER(SEARCH("XAU",E12)),100,IF(OR(ISNUMBER(SEARCH("30",E12)),ISNUMBER(SEARCH("500",E12)),ISNUMBER(SEARCH("100",E12))),100,100000))),0)) | AC12: =IF(K12="","",1-IFERROR(T12,0)-IFERROR(W12,0)-IFERROR(Z12,0)) | AD12: =IF(AB12="","",IFERROR((IFERROR(S12*T12,0)+IFERROR(V12*W12,0)+IFERROR(Y12*Z12,0)+AB12*AC12)/(IFERROR(T12,0)+IFERROR(W12,0)+IFERROR(Z12,0)+AC12),AB12)) | AE12: =IF(AB12="","",IF(U12="",0,U12)+IF(X12="",0,X12)+IF(AA12="",0,AA12)+IFERROR((AB12-K12)*IF(F12="Sell",-1,1)*R12*AC12*IF(ISNUMBER(SEARCH("JPY",E12)),1000,IF(ISNUMBER(SEARCH("XAU",E12)),100,IF(OR(ISNUMBER(SEARCH("30",E12)),ISNUMBER(SEARCH("500",E12)),ISNUMBER(SEARCH("100",E12))),100,100000))),0)) | AF12: =IF(OR(K12="",M12="",L12=""),"",IFERROR(ABS(M12-K12)/ABS(K12-L12),0)) | AG12: =IF(OR(AE12="",AE12=0,Q12=0,Q12=""),"",IFERROR(AE12/Q12,0)) | AH12: =IF(AB12="","Open",IF(AG12="","Open",IF(AG12>0.1,"Win",IF(AG12<-0.1,"Loss","Breakeven")))) -> Open | AI12: =IF(OR(B12="",D12=""),"",D12-B12) | AJ12: =IF(AD12="","",IFERROR((AD12-K12)*IF(F12="Sell",-1,1)/IF(ISNUMBER(SEARCH("JPY",E12)),0.01,IF(ISNUMBER(SEARCH("XAU",E12)),0.01,IF(OR(ISNUMBER(SEARCH("30",E12)),ISNUMBER(SEARCH("500",E12)),ISNUMBER(SEARCH("100",E12))),1,0.0001))),0)) | AO12: =IF(AE12="","",IFERROR(IF(AO11="",SETTINGS!$B$6,AO11),SETTINGS!$B$6)+IF(AE12="",0,AE12))
A13: =IF(B13="","",ROW()-3) | P13: =IF(K13="","",IFERROR(ABS(K13-L13)/IF(ISNUMBER(SEARCH("JPY",E13)),0.01,IF(ISNUMBER(SEARCH("XAU",E13)),0.01,IF(OR(ISNUMBER(SEARCH("30",E13)),ISNUMBER(SEARCH("500",E13)),ISNUMBER(SEARCH("100",E13))),1,0.0001))),0)) | Q13: =IF(K13="","",SETTINGS!$B$6*O13) | R13: =IF(K13="","",IFERROR(Q13/(P13*IF(ISNUMBER(SEARCH("JPY",E13)),9.09,IF(ISNUMBER(SEARCH("XAU",E13)),1,IF(OR(ISNUMBER(SEARCH("30",E13)),ISNUMBER(SEARCH("500",E13)),ISNUMBER(SEARCH("100",E13))),1,10)))),0)) | U13: =IF(OR(S13="",T13=0),"",IFERROR((S13-K13)*IF(F13="Sell",-1,1)*R13*T13*IF(ISNUMBER(SEARCH("JPY",E13)),1000,IF(ISNUMBER(SEARCH("XAU",E13)),100,IF(OR(ISNUMBER(SEARCH("30",E13)),ISNUMBER(SEARCH("500",E13)),ISNUMBER(SEARCH("100",E13))),100,100000))),0)) | X13: =IF(OR(V13="",W13=0),"",IFERROR((V13-K13)*IF(F13="Sell",-1,1)*R13*W13*IF(ISNUMBER(SEARCH("JPY",E13)),1000,IF(ISNUMBER(SEARCH("XAU",E13)),100,IF(OR(ISNUMBER(SEARCH("30",E13)),ISNUMBER(SEARCH("500",E13)),ISNUMBER(SEARCH("100",E13))),100,100000))),0)) | AA13: =IF(OR(Y13="",Z13=0),"",IFERROR((Y13-K13)*IF(F13="Sell",-1,1)*R13*Z13*IF(ISNUMBER(SEARCH("JPY",E13)),1000,IF(ISNUMBER(SEARCH("XAU",E13)),100,IF(OR(ISNUMBER(SEARCH("30",E13)),ISNUMBER(SEARCH("500",E13)),ISNUMBER(SEARCH("100",E13))),100,100000))),0)) | AC13: =IF(K13="","",1-IFERROR(T13,0)-IFERROR(W13,0)-IFERROR(Z13,0)) | AD13: =IF(AB13="","",IFERROR((IFERROR(S13*T13,0)+IFERROR(V13*W13,0)+IFERROR(Y13*Z13,0)+AB13*AC13)/(IFERROR(T13,0)+IFERROR(W13,0)+IFERROR(Z13,0)+AC13),AB13)) | AE13: =IF(AB13="","",IF(U13="",0,U13)+IF(X13="",0,X13)+IF(AA13="",0,AA13)+IFERROR((AB13-K13)*IF(F13="Sell",-1,1)*R13*AC13*IF(ISNUMBER(SEARCH("JPY",E13)),1000,IF(ISNUMBER(SEARCH("XAU",E13)),100,IF(OR(ISNUMBER(SEARCH("30",E13)),ISNUMBER(SEARCH("500",E13)),ISNUMBER(SEARCH("100",E13))),100,100000))),0)) | AF13: =IF(OR(K13="",M13="",L13=""),"",IFERROR(ABS(M13-K13)/ABS(K13-L13),0)) | AG13: =IF(OR(AE13="",AE13=0,Q13=0,Q13=""),"",IFERROR(AE13/Q13,0)) | AH13: =IF(AB13="","Open",IF(AG13="","Open",IF(AG13>0.1,"Win",IF(AG13<-0.1,"Loss","Breakeven")))) -> Open | AI13: =IF(OR(B13="",D13=""),"",D13-B13) | AJ13: =IF(AD13="","",IFERROR((AD13-K13)*IF(F13="Sell",-1,1)/IF(ISNUMBER(SEARCH("JPY",E13)),0.01,IF(ISNUMBER(SEARCH("XAU",E13)),0.01,IF(OR(ISNUMBER(SEARCH("30",E13)),ISNUMBER(SEARCH("500",E13)),ISNUMBER(SEARCH("100",E13))),1,0.0001))),0)) | AO13: =IF(AE13="","",IFERROR(IF(AO12="",SETTINGS!$B$6,AO12),SETTINGS!$B$6)+IF(AE13="",0,AE13))
A14: =IF(B14="","",ROW()-3) | P14: =IF(K14="","",IFERROR(ABS(K14-L14)/IF(ISNUMBER(SEARCH("JPY",E14)),0.01,IF(ISNUMBER(SEARCH("XAU",E14)),0.01,IF(OR(ISNUMBER(SEARCH("30",E14)),ISNUMBER(SEARCH("500",E14)),ISNUMBER(SEARCH("100",E14))),1,0.0001))),0)) | Q14: =IF(K14="","",SETTINGS!$B$6*O14) | R14: =IF(K14="","",IFERROR(Q14/(P14*IF(ISNUMBER(SEARCH("JPY",E14)),9.09,IF(ISNUMBER(SEARCH("XAU",E14)),1,IF(OR(ISNUMBER(SEARCH("30",E14)),ISNUMBER(SEARCH("500",E14)),ISNUMBER(SEARCH("100",E14))),1,10)))),0)) | U14: =IF(OR(S14="",T14=0),"",IFERROR((S14-K14)*IF(F14="Sell",-1,1)*R14*T14*IF(ISNUMBER(SEARCH("JPY",E14)),1000,IF(ISNUMBER(SEARCH("XAU",E14)),100,IF(OR(ISNUMBER(SEARCH("30",E14)),ISNUMBER(SEARCH("500",E14)),ISNUMBER(SEARCH("100",E14))),100,100000))),0)) | X14: =IF(OR(V14="",W14=0),"",IFERROR((V14-K14)*IF(F14="Sell",-1,1)*R14*W14*IF(ISNUMBER(SEARCH("JPY",E14)),1000,IF(ISNUMBER(SEARCH("XAU",E14)),100,IF(OR(ISNUMBER(SEARCH("30",E14)),ISNUMBER(SEARCH("500",E14)),ISNUMBER(SEARCH("100",E14))),100,100000))),0)) | AA14: =IF(OR(Y14="",Z14=0),"",IFERROR((Y14-K14)*IF(F14="Sell",-1,1)*R14*Z14*IF(ISNUMBER(SEARCH("JPY",E14)),1000,IF(ISNUMBER(SEARCH("XAU",E14)),100,IF(OR(ISNUMBER(SEARCH("30",E14)),ISNUMBER(SEARCH("500",E14)),ISNUMBER(SEARCH("100",E14))),100,100000))),0)) | AC14: =IF(K14="","",1-IFERROR(T14,0)-IFERROR(W14,0)-IFERROR(Z14,0)) | AD14: =IF(AB14="","",IFERROR((IFERROR(S14*T14,0)+IFERROR(V14*W14,0)+IFERROR(Y14*Z14,0)+AB14*AC14)/(IFERROR(T14,0)+IFERROR(W14,0)+IFERROR(Z14,0)+AC14),AB14)) | AE14: =IF(AB14="","",IF(U14="",0,U14)+IF(X14="",0,X14)+IF(AA14="",0,AA14)+IFERROR((AB14-K14)*IF(F14="Sell",-1,1)*R14*AC14*IF(ISNUMBER(SEARCH("JPY",E14)),1000,IF(ISNUMBER(SEARCH("XAU",E14)),100,IF(OR(ISNUMBER(SEARCH("30",E14)),ISNUMBER(SEARCH("500",E14)),ISNUMBER(SEARCH("100",E14))),100,100000))),0)) | AF14: =IF(OR(K14="",M14="",L14=""),"",IFERROR(ABS(M14-K14)/ABS(K14-L14),0)) | AG14: =IF(OR(AE14="",AE14=0,Q14=0,Q14=""),"",IFERROR(AE14/Q14,0)) | AH14: =IF(AB14="","Open",IF(AG14="","Open",IF(AG14>0.1,"Win",IF(AG14<-0.1,"Loss","Breakeven")))) -> Open | AI14: =IF(OR(B14="",D14=""),"",D14-B14) | AJ14: =IF(AD14="","",IFERROR((AD14-K14)*IF(F14="Sell",-1,1)/IF(ISNUMBER(SEARCH("JPY",E14)),0.01,IF(ISNUMBER(SEARCH("XAU",E14)),0.01,IF(OR(ISNUMBER(SEARCH("30",E14)),ISNUMBER(SEARCH("500",E14)),ISNUMBER(SEARCH("100",E14))),1,0.0001))),0)) | AO14: =IF(AE14="","",IFERROR(IF(AO13="",SETTINGS!$B$6,AO13),SETTINGS!$B$6)+IF(AE14="",0,AE14))
A15: =IF(B15="","",ROW()-3) | P15: =IF(K15="","",IFERROR(ABS(K15-L15)/IF(ISNUMBER(SEARCH("JPY",E15)),0.01,IF(ISNUMBER(SEARCH("XAU",E15)),0.01,IF(OR(ISNUMBER(SEARCH("30",E15)),ISNUMBER(SEARCH("500",E15)),ISNUMBER(SEARCH("100",E15))),1,0.0001))),0)) | Q15: =IF(K15="","",SETTINGS!$B$6*O15) | R15: =IF(K15="","",IFERROR(Q15/(P15*IF(ISNUMBER(SEARCH("JPY",E15)),9.09,IF(ISNUMBER(SEARCH("XAU",E15)),1,IF(OR(ISNUMBER(SEARCH("30",E15)),ISNUMBER(SEARCH("500",E15)),ISNUMBER(SEARCH("100",E15))),1,10)))),0)) | U15: =IF(OR(S15="",T15=0),"",IFERROR((S15-K15)*IF(F15="Sell",-1,1)*R15*T15*IF(ISNUMBER(SEARCH("JPY",E15)),1000,IF(ISNUMBER(SEARCH("XAU",E15)),100,IF(OR(ISNUMBER(SEARCH("30",E15)),ISNUMBER(SEARCH("500",E15)),ISNUMBER(SEARCH("100",E15))),100,100000))),0)) | X15: =IF(OR(V15="",W15=0),"",IFERROR((V15-K15)*IF(F15="Sell",-1,1)*R15*W15*IF(ISNUMBER(SEARCH("JPY",E15)),1000,IF(ISNUMBER(SEARCH("XAU",E15)),100,IF(OR(ISNUMBER(SEARCH("30",E15)),ISNUMBER(SEARCH("500",E15)),ISNUMBER(SEARCH("100",E15))),100,100000))),0)) | AA15: =IF(OR(Y15="",Z15=0),"",IFERROR((Y15-K15)*IF(F15="Sell",-1,1)*R15*Z15*IF(ISNUMBER(SEARCH("JPY",E15)),1000,IF(ISNUMBER(SEARCH("XAU",E15)),100,IF(OR(ISNUMBER(SEARCH("30",E15)),ISNUMBER(SEARCH("500",E15)),ISNUMBER(SEARCH("100",E15))),100,100000))),0)) | AC15: =IF(K15="","",1-IFERROR(T15,0)-IFERROR(W15,0)-IFERROR(Z15,0)) | AD15: =IF(AB15="","",IFERROR((IFERROR(S15*T15,0)+IFERROR(V15*W15,0)+IFERROR(Y15*Z15,0)+AB15*AC15)/(IFERROR(T15,0)+IFERROR(W15,0)+IFERROR(Z15,0)+AC15),AB15)) | AE15: =IF(AB15="","",IF(U15="",0,U15)+IF(X15="",0,X15)+IF(AA15="",0,AA15)+IFERROR((AB15-K15)*IF(F15="Sell",-1,1)*R15*AC15*IF(ISNUMBER(SEARCH("JPY",E15)),1000,IF(ISNUMBER(SEARCH("XAU",E15)),100,IF(OR(ISNUMBER(SEARCH("30",E15)),ISNUMBER(SEARCH("500",E15)),ISNUMBER(SEARCH("100",E15))),100,100000))),0)) | AF15: =IF(OR(K15="",M15="",L15=""),"",IFERROR(ABS(M15-K15)/ABS(K15-L15),0)) | AG15: =IF(OR(AE15="",AE15=0,Q15=0,Q15=""),"",IFERROR(AE15/Q15,0)) | AH15: =IF(AB15="","Open",IF(AG15="","Open",IF(AG15>0.1,"Win",IF(AG15<-0.1,"Loss","Breakeven")))) -> Open | AI15: =IF(OR(B15="",D15=""),"",D15-B15) | AJ15: =IF(AD15="","",IFERROR((AD15-K15)*IF(F15="Sell",-1,1)/IF(ISNUMBER(SEARCH("JPY",E15)),0.01,IF(ISNUMBER(SEARCH("XAU",E15)),0.01,IF(OR(ISNUMBER(SEARCH("30",E15)),ISNUMBER(SEARCH("500",E15)),ISNUMBER(SEARCH("100",E15))),1,0.0001))),0)) | AO15: =IF(AE15="","",IFERROR(IF(AO14="",SETTINGS!$B$6,AO14),SETTINGS!$B$6)+IF(AE15="",0,AE15))
A16: =IF(B16="","",ROW()-3) | P16: =IF(K16="","",IFERROR(ABS(K16-L16)/IF(ISNUMBER(SEARCH("JPY",E16)),0.01,IF(ISNUMBER(SEARCH("XAU",E16)),0.01,IF(OR(ISNUMBER(SEARCH("30",E16)),ISNUMBER(SEARCH("500",E16)),ISNUMBER(SEARCH("100",E16))),1,0.0001))),0)) | Q16: =IF(K16="","",SETTINGS!$B$6*O16) | R16: =IF(K16="","",IFERROR(Q16/(P16*IF(ISNUMBER(SEARCH("JPY",E16)),9.09,IF(ISNUMBER(SEARCH("XAU",E16)),1,IF(OR(ISNUMBER(SEARCH("30",E16)),ISNUMBER(SEARCH("500",E16)),ISNUMBER(SEARCH("100",E16))),1,10)))),0)) | U16: =IF(OR(S16="",T16=0),"",IFERROR((S16-K16)*IF(F16="Sell",-1,1)*R16*T16*IF(ISNUMBER(SEARCH("JPY",E16)),1000,IF(ISNUMBER(SEARCH("XAU",E16)),100,IF(OR(ISNUMBER(SEARCH("30",E16)),ISNUMBER(SEARCH("500",E16)),ISNUMBER(SEARCH("100",E16))),100,100000))),0)) | X16: =IF(OR(V16="",W16=0),"",IFERROR((V16-K16)*IF(F16="Sell",-1,1)*R16*W16*IF(ISNUMBER(SEARCH("JPY",E16)),1000,IF(ISNUMBER(SEARCH("XAU",E16)),100,IF(OR(ISNUMBER(SEARCH("30",E16)),ISNUMBER(SEARCH("500",E16)),ISNUMBER(SEARCH("100",E16))),100,100000))),0)) | AA16: =IF(OR(Y16="",Z16=0),"",IFERROR((Y16-K16)*IF(F16="Sell",-1,1)*R16*Z16*IF(ISNUMBER(SEARCH("JPY",E16)),1000,IF(ISNUMBER(SEARCH("XAU",E16)),100,IF(OR(ISNUMBER(SEARCH("30",E16)),ISNUMBER(SEARCH("500",E16)),ISNUMBER(SEARCH("100",E16))),100,100000))),0)) | AC16: =IF(K16="","",1-IFERROR(T16,0)-IFERROR(W16,0)-IFERROR(Z16,0)) | AD16: =IF(AB16="","",IFERROR((IFERROR(S16*T16,0)+IFERROR(V16*W16,0)+IFERROR(Y16*Z16,0)+AB16*AC16)/(IFERROR(T16,0)+IFERROR(W16,0)+IFERROR(Z16,0)+AC16),AB16)) | AE16: =IF(AB16="","",IF(U16="",0,U16)+IF(X16="",0,X16)+IF(AA16="",0,AA16)+IFERROR((AB16-K16)*IF(F16="Sell",-1,1)*R16*AC16*IF(ISNUMBER(SEARCH("JPY",E16)),1000,IF(ISNUMBER(SEARCH("XAU",E16)),100,IF(OR(ISNUMBER(SEARCH("30",E16)),ISNUMBER(SEARCH("500",E16)),ISNUMBER(SEARCH("100",E16))),100,100000))),0)) | AF16: =IF(OR(K16="",M16="",L16=""),"",IFERROR(ABS(M16-K16)/ABS(K16-L16),0)) | AG16: =IF(OR(AE16="",AE16=0,Q16=0,Q16=""),"",IFERROR(AE16/Q16,0)) | AH16: =IF(AB16="","Open",IF(AG16="","Open",IF(AG16>0.1,"Win",IF(AG16<-0.1,"Loss","Breakeven")))) -> Open | AI16: =IF(OR(B16="",D16=""),"",D16-B16) | AJ16: =IF(AD16="","",IFERROR((AD16-K16)*IF(F16="Sell",-1,1)/IF(ISNUMBER(SEARCH("JPY",E16)),0.01,IF(ISNUMBER(SEARCH("XAU",E16)),0.01,IF(OR(ISNUMBER(SEARCH("30",E16)),ISNUMBER(SEARCH("500",E16)),ISNUMBER(SEARCH("100",E16))),1,0.0001))),0)) | AO16: =IF(AE16="","",IFERROR(IF(AO15="",SETTINGS!$B$6,AO15),SETTINGS!$B$6)+IF(AE16="",0,AE16))
A17: =IF(B17="","",ROW()-3) | P17: =IF(K17="","",IFERROR(ABS(K17-L17)/IF(ISNUMBER(SEARCH("JPY",E17)),0.01,IF(ISNUMBER(SEARCH("XAU",E17)),0.01,IF(OR(ISNUMBER(SEARCH("30",E17)),ISNUMBER(SEARCH("500",E17)),ISNUMBER(SEARCH("100",E17))),1,0.0001))),0)) | Q17: =IF(K17="","",SETTINGS!$B$6*O17) | R17: =IF(K17="","",IFERROR(Q17/(P17*IF(ISNUMBER(SEARCH("JPY",E17)),9.09,IF(ISNUMBER(SEARCH("XAU",E17)),1,IF(OR(ISNUMBER(SEARCH("30",E17)),ISNUMBER(SEARCH("500",E17)),ISNUMBER(SEARCH("100",E17))),1,10)))),0)) | U17: =IF(OR(S17="",T17=0),"",IFERROR((S17-K17)*IF(F17="Sell",-1,1)*R17*T17*IF(ISNUMBER(SEARCH("JPY",E17)),1000,IF(ISNUMBER(SEARCH("XAU",E17)),100,IF(OR(ISNUMBER(SEARCH("30",E17)),ISNUMBER(SEARCH("500",E17)),ISNUMBER(SEARCH("100",E17))),100,100000))),0)) | X17: =IF(OR(V17="",W17=0),"",IFERROR((V17-K17)*IF(F17="Sell",-1,1)*R17*W17*IF(ISNUMBER(SEARCH("JPY",E17)),1000,IF(ISNUMBER(SEARCH("XAU",E17)),100,IF(OR(ISNUMBER(SEARCH("30",E17)),ISNUMBER(SEARCH("500",E17)),ISNUMBER(SEARCH("100",E17))),100,100000))),0)) | AA17: =IF(OR(Y17="",Z17=0),"",IFERROR((Y17-K17)*IF(F17="Sell",-1,1)*R17*Z17*IF(ISNUMBER(SEARCH("JPY",E17)),1000,IF(ISNUMBER(SEARCH("XAU",E17)),100,IF(OR(ISNUMBER(SEARCH("30",E17)),ISNUMBER(SEARCH("500",E17)),ISNUMBER(SEARCH("100",E17))),100,100000))),0)) | AC17: =IF(K17="","",1-IFERROR(T17,0)-IFERROR(W17,0)-IFERROR(Z17,0)) | AD17: =IF(AB17="","",IFERROR((IFERROR(S17*T17,0)+IFERROR(V17*W17,0)+IFERROR(Y17*Z17,0)+AB17*AC17)/(IFERROR(T17,0)+IFERROR(W17,0)+IFERROR(Z17,0)+AC17),AB17)) | AE17: =IF(AB17="","",IF(U17="",0,U17)+IF(X17="",0,X17)+IF(AA17="",0,AA17)+IFERROR((AB17-K17)*IF(F17="Sell",-1,1)*R17*AC17*IF(ISNUMBER(SEARCH("JPY",E17)),1000,IF(ISNUMBER(SEARCH("XAU",E17)),100,IF(OR(ISNUMBER(SEARCH("30",E17)),ISNUMBER(SEARCH("500",E17)),ISNUMBER(SEARCH("100",E17))),100,100000))),0)) | AF17: =IF(OR(K17="",M17="",L17=""),"",IFERROR(ABS(M17-K17)/ABS(K17-L17),0)) | AG17: =IF(OR(AE17="",AE17=0,Q17=0,Q17=""),"",IFERROR(AE17/Q17,0)) | AH17: =IF(AB17="","Open",IF(AG17="","Open",IF(AG17>0.1,"Win",IF(AG17<-0.1,"Loss","Breakeven")))) -> Open | AI17: =IF(OR(B17="",D17=""),"",D17-B17) | AJ17: =IF(AD17="","",IFERROR((AD17-K17)*IF(F17="Sell",-1,1)/IF(ISNUMBER(SEARCH("JPY",E17)),0.01,IF(ISNUMBER(SEARCH("XAU",E17)),0.01,IF(OR(ISNUMBER(SEARCH("30",E17)),ISNUMBER(SEARCH("500",E17)),ISNUMBER(SEARCH("100",E17))),1,0.0001))),0)) | AO17: =IF(AE17="","",IFERROR(IF(AO16="",SETTINGS!$B$6,AO16),SETTINGS!$B$6)+IF(AE17="",0,AE17))
A18: =IF(B18="","",ROW()-3) | P18: =IF(K18="","",IFERROR(ABS(K18-L18)/IF(ISNUMBER(SEARCH("JPY",E18)),0.01,IF(ISNUMBER(SEARCH("XAU",E18)),0.01,IF(OR(ISNUMBER(SEARCH("30",E18)),ISNUMBER(SEARCH("500",E18)),ISNUMBER(SEARCH("100",E18))),1,0.0001))),0)) | Q18: =IF(K18="","",SETTINGS!$B$6*O18) | R18: =IF(K18="","",IFERROR(Q18/(P18*IF(ISNUMBER(SEARCH("JPY",E18)),9.09,IF(ISNUMBER(SEARCH("XAU",E18)),1,IF(OR(ISNUMBER(SEARCH("30",E18)),ISNUMBER(SEARCH("500",E18)),ISNUMBER(SEARCH("100",E18))),1,10)))),0)) | U18: =IF(OR(S18="",T18=0),"",IFERROR((S18-K18)*IF(F18="Sell",-1,1)*R18*T18*IF(ISNUMBER(SEARCH("JPY",E18)),1000,IF(ISNUMBER(SEARCH("XAU",E18)),100,IF(OR(ISNUMBER(SEARCH("30",E18)),ISNUMBER(SEARCH("500",E18)),ISNUMBER(SEARCH("100",E18))),100,100000))),0)) | X18: =IF(OR(V18="",W18=0),"",IFERROR((V18-K18)*IF(F18="Sell",-1,1)*R18*W18*IF(ISNUMBER(SEARCH("JPY",E18)),1000,IF(ISNUMBER(SEARCH("XAU",E18)),100,IF(OR(ISNUMBER(SEARCH("30",E18)),ISNUMBER(SEARCH("500",E18)),ISNUMBER(SEARCH("100",E18))),100,100000))),0)) | AA18: =IF(OR(Y18="",Z18=0),"",IFERROR((Y18-K18)*IF(F18="Sell",-1,1)*R18*Z18*IF(ISNUMBER(SEARCH("JPY",E18)),1000,IF(ISNUMBER(SEARCH("XAU",E18)),100,IF(OR(ISNUMBER(SEARCH("30",E18)),ISNUMBER(SEARCH("500",E18)),ISNUMBER(SEARCH("100",E18))),100,100000))),0)) | AC18: =IF(K18="","",1-IFERROR(T18,0)-IFERROR(W18,0)-IFERROR(Z18,0)) | AD18: =IF(AB18="","",IFERROR((IFERROR(S18*T18,0)+IFERROR(V18*W18,0)+IFERROR(Y18*Z18,0)+AB18*AC18)/(IFERROR(T18,0)+IFERROR(W18,0)+IFERROR(Z18,0)+AC18),AB18)) | AE18: =IF(AB18="","",IF(U18="",0,U18)+IF(X18="",0,X18)+IF(AA18="",0,AA18)+IFERROR((AB18-K18)*IF(F18="Sell",-1,1)*R18*AC18*IF(ISNUMBER(SEARCH("JPY",E18)),1000,IF(ISNUMBER(SEARCH("XAU",E18)),100,IF(OR(ISNUMBER(SEARCH("30",E18)),ISNUMBER(SEARCH("500",E18)),ISNUMBER(SEARCH("100",E18))),100,100000))),0)) | AF18: =IF(OR(K18="",M18="",L18=""),"",IFERROR(ABS(M18-K18)/ABS(K18-L18),0)) | AG18: =IF(OR(AE18="",AE18=0,Q18=0,Q18=""),"",IFERROR(AE18/Q18,0)) | AH18: =IF(AB18="","Open",IF(AG18="","Open",IF(AG18>0.1,"Win",IF(AG18<-0.1,"Loss","Breakeven")))) -> Open | AI18: =IF(OR(B18="",D18=""),"",D18-B18) | AJ18: =IF(AD18="","",IFERROR((AD18-K18)*IF(F18="Sell",-1,1)/IF(ISNUMBER(SEARCH("JPY",E18)),0.01,IF(ISNUMBER(SEARCH("XAU",E18)),0.01,IF(OR(ISNUMBER(SEARCH("30",E18)),ISNUMBER(SEARCH("500",E18)),ISNUMBER(SEARCH("100",E18))),1,0.0001))),0)) | AO18: =IF(AE18="","",IFERROR(IF(AO17="",SETTINGS!$B$6,AO17),SETTINGS!$B$6)+IF(AE18="",0,AE18))
A19: =IF(B19="","",ROW()-3) | P19: =IF(K19="","",IFERROR(ABS(K19-L19)/IF(ISNUMBER(SEARCH("JPY",E19)),0.01,IF(ISNUMBER(SEARCH("XAU",E19)),0.01,IF(OR(ISNUMBER(SEARCH("30",E19)),ISNUMBER(SEARCH("500",E19)),ISNUMBER(SEARCH("100",E19))),1,0.0001))),0)) | Q19: =IF(K19="","",SETTINGS!$B$6*O19) | R19: =IF(K19="","",IFERROR(Q19/(P19*IF(ISNUMBER(SEARCH("JPY",E19)),9.09,IF(ISNUMBER(SEARCH("XAU",E19)),1,IF(OR(ISNUMBER(SEARCH("30",E19)),ISNUMBER(SEARCH("500",E19)),ISNUMBER(SEARCH("100",E19))),1,10)))),0)) | U19: =IF(OR(S19="",T19=0),"",IFERROR((S19-K19)*IF(F19="Sell",-1,1)*R19*T19*IF(ISNUMBER(SEARCH("JPY",E19)),1000,IF(ISNUMBER(SEARCH("XAU",E19)),100,IF(OR(ISNUMBER(SEARCH("30",E19)),ISNUMBER(SEARCH("500",E19)),ISNUMBER(SEARCH("100",E19))),100,100000))),0)) | X19: =IF(OR(V19="",W19=0),"",IFERROR((V19-K19)*IF(F19="Sell",-1,1)*R19*W19*IF(ISNUMBER(SEARCH("JPY",E19)),1000,IF(ISNUMBER(SEARCH("XAU",E19)),100,IF(OR(ISNUMBER(SEARCH("30",E19)),ISNUMBER(SEARCH("500",E19)),ISNUMBER(SEARCH("100",E19))),100,100000))),0)) | AA19: =IF(OR(Y19="",Z19=0),"",IFERROR((Y19-K19)*IF(F19="Sell",-1,1)*R19*Z19*IF(ISNUMBER(SEARCH("JPY",E19)),1000,IF(ISNUMBER(SEARCH("XAU",E19)),100,IF(OR(ISNUMBER(SEARCH("30",E19)),ISNUMBER(SEARCH("500",E19)),ISNUMBER(SEARCH("100",E19))),100,100000))),0)) | AC19: =IF(K19="","",1-IFERROR(T19,0)-IFERROR(W19,0)-IFERROR(Z19,0)) | AD19: =IF(AB19="","",IFERROR((IFERROR(S19*T19,0)+IFERROR(V19*W19,0)+IFERROR(Y19*Z19,0)+AB19*AC19)/(IFERROR(T19,0)+IFERROR(W19,0)+IFERROR(Z19,0)+AC19),AB19)) | AE19: =IF(AB19="","",IF(U19="",0,U19)+IF(X19="",0,X19)+IF(AA19="",0,AA19)+IFERROR((AB19-K19)*IF(F19="Sell",-1,1)*R19*AC19*IF(ISNUMBER(SEARCH("JPY",E19)),1000,IF(ISNUMBER(SEARCH("XAU",E19)),100,IF(OR(ISNUMBER(SEARCH("30",E19)),ISNUMBER(SEARCH("500",E19)),ISNUMBER(SEARCH("100",E19))),100,100000))),0)) | AF19: =IF(OR(K19="",M19="",L19=""),"",IFERROR(ABS(M19-K19)/ABS(K19-L19),0)) | AG19: =IF(OR(AE19="",AE19=0,Q19=0,Q19=""),"",IFERROR(AE19/Q19,0)) | AH19: =IF(AB19="","Open",IF(AG19="","Open",IF(AG19>0.1,"Win",IF(AG19<-0.1,"Loss","Breakeven")))) -> Open | AI19: =IF(OR(B19="",D19=""),"",D19-B19) | AJ19: =IF(AD19="","",IFERROR((AD19-K19)*IF(F19="Sell",-1,1)/IF(ISNUMBER(SEARCH("JPY",E19)),0.01,IF(ISNUMBER(SEARCH("XAU",E19)),0.01,IF(OR(ISNUMBER(SEARCH("30",E19)),ISNUMBER(SEARCH("500",E19)),ISNUMBER(SEARCH("100",E19))),1,0.0001))),0)) | AO19: =IF(AE19="","",IFERROR(IF(AO18="",SETTINGS!$B$6,AO18),SETTINGS!$B$6)+IF(AE19="",0,AE19))
A20: =IF(B20="","",ROW()-3) | P20: =IF(K20="","",IFERROR(ABS(K20-L20)/IF(ISNUMBER(SEARCH("JPY",E20)),0.01,IF(ISNUMBER(SEARCH("XAU",E20)),0.01,IF(OR(ISNUMBER(SEARCH("30",E20)),ISNUMBER(SEARCH("500",E20)),ISNUMBER(SEARCH("100",E20))),1,0.0001))),0)) | Q20: =IF(K20="","",SETTINGS!$B$6*O20) | R20: =IF(K20="","",IFERROR(Q20/(P20*IF(ISNUMBER(SEARCH("JPY",E20)),9.09,IF(ISNUMBER(SEARCH("XAU",E20)),1,IF(OR(ISNUMBER(SEARCH("30",E20)),ISNUMBER(SEARCH("500",E20)),ISNUMBER(SEARCH("100",E20))),1,10)))),0)) | U20: =IF(OR(S20="",T20=0),"",IFERROR((S20-K20)*IF(F20="Sell",-1,1)*R20*T20*IF(ISNUMBER(SEARCH("JPY",E20)),1000,IF(ISNUMBER(SEARCH("XAU",E20)),100,IF(OR(ISNUMBER(SEARCH("30",E20)),ISNUMBER(SEARCH("500",E20)),ISNUMBER(SEARCH("100",E20))),100,100000))),0)) | X20: =IF(OR(V20="",W20=0),"",IFERROR((V20-K20)*IF(F20="Sell",-1,1)*R20*W20*IF(ISNUMBER(SEARCH("JPY",E20)),1000,IF(ISNUMBER(SEARCH("XAU",E20)),100,IF(OR(ISNUMBER(SEARCH("30",E20)),ISNUMBER(SEARCH("500",E20)),ISNUMBER(SEARCH("100",E20))),100,100000))),0)) | AA20: =IF(OR(Y20="",Z20=0),"",IFERROR((Y20-K20)*IF(F20="Sell",-1,1)*R20*Z20*IF(ISNUMBER(SEARCH("JPY",E20)),1000,IF(ISNUMBER(SEARCH("XAU",E20)),100,IF(OR(ISNUMBER(SEARCH("30",E20)),ISNUMBER(SEARCH("500",E20)),ISNUMBER(SEARCH("100",E20))),100,100000))),0)) | AC20: =IF(K20="","",1-IFERROR(T20,0)-IFERROR(W20,0)-IFERROR(Z20,0)) | AD20: =IF(AB20="","",IFERROR((IFERROR(S20*T20,0)+IFERROR(V20*W20,0)+IFERROR(Y20*Z20,0)+AB20*AC20)/(IFERROR(T20,0)+IFERROR(W20,0)+IFERROR(Z20,0)+AC20),AB20)) | AE20: =IF(AB20="","",IF(U20="",0,U20)+IF(X20="",0,X20)+IF(AA20="",0,AA20)+IFERROR((AB20-K20)*IF(F20="Sell",-1,1)*R20*AC20*IF(ISNUMBER(SEARCH("JPY",E20)),1000,IF(ISNUMBER(SEARCH("XAU",E20)),100,IF(OR(ISNUMBER(SEARCH("30",E20)),ISNUMBER(SEARCH("500",E20)),ISNUMBER(SEARCH("100",E20))),100,100000))),0)) | AF20: =IF(OR(K20="",M20="",L20=""),"",IFERROR(ABS(M20-K20)/ABS(K20-L20),0)) | AG20: =IF(OR(AE20="",AE20=0,Q20=0,Q20=""),"",IFERROR(AE20/Q20,0)) | AH20: =IF(AB20="","Open",IF(AG20="","Open",IF(AG20>0.1,"Win",IF(AG20<-0.1,"Loss","Breakeven")))) -> Open | AI20: =IF(OR(B20="",D20=""),"",D20-B20) | AJ20: =IF(AD20="","",IFERROR((AD20-K20)*IF(F20="Sell",-1,1)/IF(ISNUMBER(SEARCH("JPY",E20)),0.01,IF(ISNUMBER(SEARCH("XAU",E20)),0.01,IF(OR(ISNUMBER(SEARCH("30",E20)),ISNUMBER(SEARCH("500",E20)),ISNUMBER(SEARCH("100",E20))),1,0.0001))),0)) | AO20: =IF(AE20="","",IFERROR(IF(AO19="",SETTINGS!$B$6,AO19),SETTINGS!$B$6)+IF(AE20="",0,AE20))
... A503: =IF(B503="","",ROW()-3) | P503: =IF(K503="","",IFERROR(ABS(K503-L503)/IF(ISNUMBER(SEARCH("JPY",E503)),0.01,IF(ISNUMBER(SEARCH("XAU",E503)),0.01,IF(OR(ISNUMBER(SEARCH("30",E503)),ISNUMBER(SEARCH("500",E503)),ISNUMBER(SEARCH("100",E503))),1,0.0001))),0)) | Q503: =IF(K503="","",SETTINGS!$B$6*O503) | R503: =IF(K503="","",IFERROR(Q503/(P503*IF(ISNUMBER(SEARCH("JPY",E503)),9.09,IF(ISNUMBER(SEARCH("XAU",E503)),1,IF(OR(ISNUMBER(SEARCH("30",E503)),ISNUMBER(SEARCH("500",E503)),ISNUMBER(SEARCH("100",E503))),1,10)))),0)) | U503: =IF(OR(S503="",T503=0),"",IFERROR((S503-K503)*IF(F503="Sell",-1,1)*R503*T503*IF(ISNUMBER(SEARCH("JPY",E503)),1000,IF(ISNUMBER(SEARCH("XAU",E503)),100,IF(OR(ISNUMBER(SEARCH("30",E503)),ISNUMBER(SEARCH("500",E503)),ISNUMBER(SEARCH("100",E503))),100,100000))),0)) | X503: =IF(OR(V503="",W503=0),"",IFERROR((V503-K503)*IF(F503="Sell",-1,1)*R503*W503*IF(ISNUMBER(SEARCH("JPY",E503)),1000,IF(ISNUMBER(SEARCH("XAU",E503)),100,IF(OR(ISNUMBER(SEARCH("30",E503)),ISNUMBER(SEARCH("500",E503)),ISNUMBER(SEARCH("100",E503))),100,100000))),0)) | AA503: =IF(OR(Y503="",Z503=0),"",IFERROR((Y503-K503)*IF(F503="Sell",-1,1)*R503*Z503*IF(ISNUMBER(SEARCH("JPY",E503)),1000,IF(ISNUMBER(SEARCH("XAU",E503)),100,IF(OR(ISNUMBER(SEARCH("30",E503)),ISNUMBER(SEARCH("500",E503)),ISNUMBER(SEARCH("100",E503))),100,100000))),0)) | AC503: =IF(K503="","",1-IFERROR(T503,0)-IFERROR(W503,0)-IFERROR(Z503,0)) | AD503: =IF(AB503="","",IFERROR((IFERROR(S503*T503,0)+IFERROR(V503*W503,0)+IFERROR(Y503*Z503,0)+AB503*AC503)/(IFERROR(T503,0)+IFERROR(W503,0)+IFERROR(Z503,0)+AC503),AB503)) | AE503: =IF(AB503="","",IF(U503="",0,U503)+IF(X503="",0,X503)+IF(AA503="",0,AA503)+IFERROR((AB503-K503)*IF(F503="Sell",-1,1)*R503*AC503*IF(ISNUMBER(SEARCH("JPY",E503)),1000,IF(ISNUMBER(SEARCH("XAU",E503)),100,IF(OR(ISNUMBER(SEARCH("30",E503)),ISNUMBER(SEARCH("500",E503)),ISNUMBER(SEARCH("100",E503))),100,100000))),0)) | AF503: =IF(OR(K503="",M503="",L503=""),"",IFERROR(ABS(M503-K503)/ABS(K503-L503),0)) | AG503: =IF(OR(AE503="",AE503=0,Q503=0,Q503=""),"",IFERROR(AE503/Q503,0)) | AH503: =IF(AB503="","Open",IF(AG503="","Open",IF(AG503>0.1,"Win",IF(AG503<-0.1,"Loss","Breakeven")))) -> Open | AI503: =IF(OR(B503="",D503=""),"",D503-B503) | AJ503: =IF(AD503="","",IFERROR((AD503-K503)*IF(F503="Sell",-1,1)/IF(ISNUMBER(SEARCH("JPY",E503)),0.01,IF(ISNUMBER(SEARCH("XAU",E503)),0.01,IF(OR(ISNUMBER(SEARCH("30",E503)),ISNUMBER(SEARCH("500",E503)),ISNUMBER(SEARCH("100",E503))),1,0.0001))),0)) | AO503: =IF(AE503="","",IFERROR(IF(AO502="",SETTINGS!$B$6,AO502),SETTINGS!$B$6)+IF(AE503="",0,AE503))

Sheet POSITION_CALC
A1: 🔢 POSITION SIZE CALCULATOR — Forex, Gold & Indices
A2: BLUE cells = user input. Results update automatically. Account balance pulled from SETTINGS.
A4: INPUTS
A5: Account Balance ($) | C5: =SETTINGS!B6 -> 50000
A6: Risk per Trade (%) | C6: =SETTINGS!B8 -> 0.01
A7: Risk Amount ($) | C7: =C5*C6 -> 500
A8: Instrument Type | C8: Forex Non-JPY
A9: Instrument | C9: EUR/USD
A10: Entry Price | C10: 1.085
A11: Stop Loss Price | C11: 1.083
A12: Stop Distance (pips/pts) | C12: =IFERROR(ABS(C10-C11)/IF(C8="Forex JPY",0.01,IF(C8="Gold XAUUSD",0.01,IF(C8="Indices",1,0.0001))),0) -> 20
A13: Account Currency | C13: =SETTINGS!B5 -> USD
A16: CALCULATED POSITION SIZES
A17: Market Type | B17: Pip/Pt Value (std lot) | C17: Lot Size | D17: Mini Lots | E17: Units | F17: Risk Validation
A18: Forex Non-JPY | B18: =10 -> 10 | C18: =IFERROR(C7/(ABS(C10-C11)/0.0001*10),0) -> 2.5 | D18: =G18*10 -> 0 | E18: =G18*100000 -> 0 | F18: =IF(ABS(G18*ABS(C10-C11)/0.0001*10-C7)<0.01,"✓ OK","⚠ Check") -> ⚠ Check
A19: Forex JPY | B19: =9.09 -> 9.09 | C19: =IFERROR(C7/(ABS(C10-C11)/0.01*9.09),0) -> 275.0275 | D19: =G19*10 -> 0 | E19: =G19*100000 -> 0 | F19: =IF(ABS(G19*ABS(C10-C11)/0.01*9.09-C7)<0.01,"✓ OK","⚠ Check") -> ⚠ Check
A20: Gold XAUUSD | B20: =1 -> 1 | C20: =IFERROR(C7/(ABS(C10-C11)/0.01*1),0) -> 2500 | D20: =G20*10 -> 0 | E20: =G20*100 -> 0 | F20: =IF(ABS(G20*ABS(C10-C11)/0.01*1-C7)<0.01,"✓ OK","⚠ Check") -> ⚠ Check
A21: Indices | B21: =1 -> 1 | C21: =IFERROR(C7/(ABS(C10-C11)/1*1),0) -> 250000 | D21: =G21*10 -> 0 | E21: =G21*100 -> 0 | F21: =IF(ABS(G21*ABS(C10-C11)/1*1-C7)<0.01,"✓ OK","⚠ Check") -> ⚠ Check
A24: ► RECOMMENDED LOT SIZE (for selected instrument type above)
A25: Selected Lot Size: | C25: =IFERROR(IF(C8="Forex Non-JPY",G18,IF(C8="Forex JPY",G19,IF(C8="Gold XAUUSD",G20,IF(C8="Indices",G21,0)))),0) -> 0 | D25: Dollar Risk: | F25: =C7 -> 500
A28: 📐 POSITION SIZING LOGIC: Forex Non-JPY: Lots = Risk$ ÷ (SL_pips × $10) | Forex JPY: Lots = Risk$ ÷ (SL_pips × $9.09) | Gold: Lots = Risk$ ÷ (SL_pts × $1 × 100oz) | Indices: Lots = Risk$ ÷ (SL_pts × $1) NOTE: JPY pip value = 1000÷USD/JPY_rate — approximated at $9.09. Adjust the pip value reference in SETTINGS for precision.

Sheet STRATEGY_PERF
A1: 📈 STRATEGY PERFORMANCE ANALYTICS
A2: Auto-updates from TRADE_LOG. No manual input required. Formulas reference column H (Strategy) and AG (R-Multiple).
A4: Strategy | B4: Total Trades | C4: Wins | D4: Losses | E4: Breakeven | F4: Win Rate | G4: Avg R-Multiple | H4: Avg Win R | I4: Avg Loss R | J4: Best Trade R | K4: Worst Trade R | L4: Total P/L $ | M4: Avg P/L $ | N4: Expectancy | O4: Profit Factor | P4: Notes
A5: Breakout | B5: =COUNTIF(TRADE_LOG!$H$4:$H$5003,A5) -> 1 | C5: =COUNTIFS(TRADE_LOG!$H$4:$H$5003,A5,TRADE_LOG!$AH$4:$AH$5003,"Win") -> 1 | D5: =COUNTIFS(TRADE_LOG!$H$4:$H$5003,A5,TRADE_LOG!$AH$4:$AH$5003,"Loss") -> 0 | E5: =COUNTIFS(TRADE_LOG!$H$4:$H$5003,A5,TRADE_LOG!$AH$4:$AH$5003,"Breakeven") -> 0 | F5: =IFERROR(C5/B5,0) -> 1 | G5: =IFERROR(AVERAGEIF(TRADE_LOG!$H$4:$H$5003,A5,TRADE_LOG!$AG$4:$AG$5003),0) -> 2.3933333 | H5: =IFERROR(AVERAGEIFS(TRADE_LOG!$AG$4:$AG$5003,TRADE_LOG!$H$4:$H$5003,A5,TRADE_LOG!$AH$4:$AH$5003,"Win"),0) -> 2.3933333 | I5: =IFERROR(AVERAGEIFS(TRADE_LOG!$AG$4:$AG$5003,TRADE_LOG!$H$4:$H$5003,A5,TRADE_LOG!$AH$4:$AH$5003,"Loss"),0) -> 0 | J5: =IFERROR(maxifs(TRADE_LOG!$AG$4:$AG$5003,TRADE_LOG!$H$4:$H$5003,A5),0) -> 0 | K5: =IFERROR(minifs(TRADE_LOG!$AG$4:$AG$5003,TRADE_LOG!$H$4:$H$5003,A5),0) -> 0 | L5: =IFERROR(SUMIF(TRADE_LOG!$H$4:$H$5003,A5,TRADE_LOG!$AE$4:$AE$5003),0) -> 1795 | M5: =IFERROR(L5/B5,0) -> 1795 | N5: =IFERROR(F5*H5+(1-F5)*I5,0) -> 2.3933333 | O5: =IFERROR((C5*H5)/(D5*ABS(I5)),0) -> 0
A6: Trend Follow | B6: =COUNTIF(TRADE_LOG!$H$4:$H$5003,A6) -> 1 | C6: =COUNTIFS(TRADE_LOG!$H$4:$H$5003,A6,TRADE_LOG!$AH$4:$AH$5003,"Win") -> 1 | D6: =COUNTIFS(TRADE_LOG!$H$4:$H$5003,A6,TRADE_LOG!$AH$4:$AH$5003,"Loss") -> 0 | E6: =COUNTIFS(TRADE_LOG!$H$4:$H$5003,A6,TRADE_LOG!$AH$4:$AH$5003,"Breakeven") -> 0 | F6: =IFERROR(C6/B6,0) -> 1 | G6: =IFERROR(AVERAGEIF(TRADE_LOG!$H$4:$H$5003,A6,TRADE_LOG!$AG$4:$AG$5003),0) -> 2.275 | H6: =IFERROR(AVERAGEIFS(TRADE_LOG!$AG$4:$AG$5003,TRADE_LOG!$H$4:$H$5003,A6,TRADE_LOG!$AH$4:$AH$5003,"Win"),0) -> 2.275 | I6: =IFERROR(AVERAGEIFS(TRADE_LOG!$AG$4:$AG$5003,TRADE_LOG!$H$4:$H$5003,A6,TRADE_LOG!$AH$4:$AH$5003,"Loss"),0) -> 0 | J6: =IFERROR(maxifs(TRADE_LOG!$AG$4:$AG$5003,TRADE_LOG!$H$4:$H$5003,A6),0) -> 0 | K6: =IFERROR(minifs(TRADE_LOG!$AG$4:$AG$5003,TRADE_LOG!$H$4:$H$5003,A6),0) -> 0 | L6: =IFERROR(SUMIF(TRADE_LOG!$H$4:$H$5003,A6,TRADE_LOG!$AE$4:$AE$5003),0) -> 1137.5 | M6: =IFERROR(L6/B6,0) -> 1137.5 | N6: =IFERROR(F6*H6+(1-F6)*I6,0) -> 2.275 | O6: =IFERROR((C6*H6)/(D6*ABS(I6)),0) -> 0
A7: Mean Reversion | B7: =COUNTIF(TRADE_LOG!$H$4:$H$5003,A7) -> 1 | C7: =COUNTIFS(TRADE_LOG!$H$4:$H$5003,A7,TRADE_LOG!$AH$4:$AH$5003,"Win") -> 1 | D7: =COUNTIFS(TRADE_LOG!$H$4:$H$5003,A7,TRADE_LOG!$AH$4:$AH$5003,"Loss") -> 0 | E7: =COUNTIFS(TRADE_LOG!$H$4:$H$5003,A7,TRADE_LOG!$AH$4:$AH$5003,"Breakeven") -> 0 | F7: =IFERROR(C7/B7,0) -> 1 | G7: =IFERROR(AVERAGEIF(TRADE_LOG!$H$4:$H$5003,A7,TRADE_LOG!$AG$4:$AG$5003),0) -> 1.2376238 | H7: =IFERROR(AVERAGEIFS(TRADE_LOG!$AG$4:$AG$5003,TRADE_LOG!$H$4:$H$5003,A7,TRADE_LOG!$AH$4:$AH$5003,"Win"),0) -> 1.2376238 | I7: =IFERROR(AVERAGEIFS(TRADE_LOG!$AG$4:$AG$5003,TRADE_LOG!$H$4:$H$5003,A7,TRADE_LOG!$AH$4:$AH$5003,"Loss"),0) -> 0 | J7: =IFERROR(maxifs(TRADE_LOG!$AG$4:$AG$5003,TRADE_LOG!$H$4:$H$5003,A7),0) -> 0 | K7: =IFERROR(minifs(TRADE_LOG!$AG$4:$AG$5003,TRADE_LOG!$H$4:$H$5003,A7),0) -> 0 | L7: =IFERROR(SUMIF(TRADE_LOG!$H$4:$H$5003,A7,TRADE_LOG!$AE$4:$AE$5003),0) -> 618.81188 | M7: =IFERROR(L7/B7,0) -> 618.81188 | N7: =IFERROR(F7*H7+(1-F7)*I7,0) -> 1.2376238 | O7: =IFERROR((C7*H7)/(D7*ABS(I7)),0) -> 0
A8: Scalp | B8: =COUNTIF(TRADE_LOG!$H$4:$H$5003,A8) -> 0 | C8: =COUNTIFS(TRADE_LOG!$H$4:$H$5003,A8,TRADE_LOG!$AH$4:$AH$5003,"Win") -> 0 | D8: =COUNTIFS(TRADE_LOG!$H$4:$H$5003,A8,TRADE_LOG!$AH$4:$AH$5003,"Loss") -> 0 | E8: =COUNTIFS(TRADE_LOG!$H$4:$H$5003,A8,TRADE_LOG!$AH$4:$AH$5003,"Breakeven") -> 0 | F8: =IFERROR(C8/B8,0) -> 0 | G8: =IFERROR(AVERAGEIF(TRADE_LOG!$H$4:$H$5003,A8,TRADE_LOG!$AG$4:$AG$5003),0) -> 0 | H8: =IFERROR(AVERAGEIFS(TRADE_LOG!$AG$4:$AG$5003,TRADE_LOG!$H$4:$H$5003,A8,TRADE_LOG!$AH$4:$AH$5003,"Win"),0) -> 0 | I8: =IFERROR(AVERAGEIFS(TRADE_LOG!$AG$4:$AG$5003,TRADE_LOG!$H$4:$H$5003,A8,TRADE_LOG!$AH$4:$AH$5003,"Loss"),0) -> 0 | J8: =IFERROR(maxifs(TRADE_LOG!$AG$4:$AG$5003,TRADE_LOG!$H$4:$H$5003,A8),0) -> 0 | K8: =IFERROR(minifs(TRADE_LOG!$AG$4:$AG$5003,TRADE_LOG!$H$4:$H$5003,A8),0) -> 0 | L8: =IFERROR(SUMIF(TRADE_LOG!$H$4:$H$5003,A8,TRADE_LOG!$AE$4:$AE$5003),0) -> 0 | M8: =IFERROR(L8/B8,0) -> 0 | N8: =IFERROR(F8*H8+(1-F8)*I8,0) -> 0 | O8: =IFERROR((C8*H8)/(D8*ABS(I8)),0) -> 0
A9: News Trade | B9: =COUNTIF(TRADE_LOG!$H$4:$H$5003,A9) -> 0 | C9: =COUNTIFS(TRADE_LOG!$H$4:$H$5003,A9,TRADE_LOG!$AH$4:$AH$5003,"Win") -> 0 | D9: =COUNTIFS(TRADE_LOG!$H$4:$H$5003,A9,TRADE_LOG!$AH$4:$AH$5003,"Loss") -> 0 | E9: =COUNTIFS(TRADE_LOG!$H$4:$H$5003,A9,TRADE_LOG!$AH$4:$AH$5003,"Breakeven") -> 0 | F9: =IFERROR(C9/B9,0) -> 0 | G9: =IFERROR(AVERAGEIF(TRADE_LOG!$H$4:$H$5003,A9,TRADE_LOG!$AG$4:$AG$5003),0) -> 0 | H9: =IFERROR(AVERAGEIFS(TRADE_LOG!$AG$4:$AG$5003,TRADE_LOG!$H$4:$H$5003,A9,TRADE_LOG!$AH$4:$AH$5003,"Win"),0) -> 0 | I9: =IFERROR(AVERAGEIFS(TRADE_LOG!$AG$4:$AG$5003,TRADE_LOG!$H$4:$H$5003,A9,TRADE_LOG!$AH$4:$AH$5003,"Loss"),0) -> 0 | J9: =IFERROR(maxifs(TRADE_LOG!$AG$4:$AG$5003,TRADE_LOG!$H$4:$H$5003,A9),0) -> 0 | K9: =IFERROR(minifs(TRADE_LOG!$AG$4:$AG$5003,TRADE_LOG!$H$4:$H$5003,A9),0) -> 0 | L9: =IFERROR(SUMIF(TRADE_LOG!$H$4:$H$5003,A9,TRADE_LOG!$AE$4:$AE$5003),0) -> 0 | M9: =IFERROR(L9/B9,0) -> 0 | N9: =IFERROR(F9*H9+(1-F9)*I9,0) -> 0 | O9: =IFERROR((C9*H9)/(D9*ABS(I9)),0) -> 0
A10: Support/Resistance | B10: =COUNTIF(TRADE_LOG!$H$4:$H$5003,A10) -> 0 | C10: =COUNTIFS(TRADE_LOG!$H$4:$H$5003,A10,TRADE_LOG!$AH$4:$AH$5003,"Win") -> 0 | D10: =COUNTIFS(TRADE_LOG!$H$4:$H$5003,A10,TRADE_LOG!$AH$4:$AH$5003,"Loss") -> 0 | E10: =COUNTIFS(TRADE_LOG!$H$4:$H$5003,A10,TRADE_LOG!$AH$4:$AH$5003,"Breakeven") -> 0 | F10: =IFERROR(C10/B10,0) -> 0 | G10: =IFERROR(AVERAGEIF(TRADE_LOG!$H$4:$H$5003,A10,TRADE_LOG!$AG$4:$AG$5003),0) -> 0 | H10: =IFERROR(AVERAGEIFS(TRADE_LOG!$AG$4:$AG$5003,TRADE_LOG!$H$4:$H$5003,A10,TRADE_LOG!$AH$4:$AH$5003,"Win"),0) -> 0 | I10: =IFERROR(AVERAGEIFS(TRADE_LOG!$AG$4:$AG$5003,TRADE_LOG!$H$4:$H$5003,A10,TRADE_LOG!$AH$4:$AH$5003,"Loss"),0) -> 0 | J10: =IFERROR(maxifs(TRADE_LOG!$AG$4:$AG$5003,TRADE_LOG!$H$4:$H$5003,A10),0) -> 0 | K10: =IFERROR(minifs(TRADE_LOG!$AG$4:$AG$5003,TRADE_LOG!$H$4:$H$5003,A10),0) -> 0 | L10: =IFERROR(SUMIF(TRADE_LOG!$H$4:$H$5003,A10,TRADE_LOG!$AE$4:$AE$5003),0) -> 0 | M10: =IFERROR(L10/B10,0) -> 0 | N10: =IFERROR(F10*H10+(1-F10)*I10,0) -> 0 | O10: =IFERROR((C10*H10)/(D10*ABS(I10)),0) -> 0
A11: ICT/SMC | B11: =COUNTIF(TRADE_LOG!$H$4:$H$5003,A11) -> 1 | C11: =COUNTIFS(TRADE_LOG!$H$4:$H$5003,A11,TRADE_LOG!$AH$4:$AH$5003,"Win") -> 1 | D11: =COUNTIFS(TRADE_LOG!$H$4:$H$5003,A11,TRADE_LOG!$AH$4:$AH$5003,"Loss") -> 0 | E11: =COUNTIFS(TRADE_LOG!$H$4:$H$5003,A11,TRADE_LOG!$AH$4:$AH$5003,"Breakeven") -> 0 | F11: =IFERROR(C11/B11,0) -> 1 | G11: =IFERROR(AVERAGEIF(TRADE_LOG!$H$4:$H$5003,A11,TRADE_LOG!$AG$4:$AG$5003),0) -> 1.5 | H11: =IFERROR(AVERAGEIFS(TRADE_LOG!$AG$4:$AG$5003,TRADE_LOG!$H$4:$H$5003,A11,TRADE_LOG!$AH$4:$AH$5003,"Win"),0) -> 1.5 | I11: =IFERROR(AVERAGEIFS(TRADE_LOG!$AG$4:$AG$5003,TRADE_LOG!$H$4:$H$5003,A11,TRADE_LOG!$AH$4:$AH$5003,"Loss"),0) -> 0 | J11: =IFERROR(maxifs(TRADE_LOG!$AG$4:$AG$5003,TRADE_LOG!$H$4:$H$5003,A11),0) -> 0 | K11: =IFERROR(minifs(TRADE_LOG!$AG$4:$AG$5003,TRADE_LOG!$H$4:$H$5003,A11),0) -> 0 | L11: =IFERROR(SUMIF(TRADE_LOG!$H$4:$H$5003,A11,TRADE_LOG!$AE$4:$AE$5003),0) -> 750 | M11: =IFERROR(L11/B11,0) -> 750 | N11: =IFERROR(F11*H11+(1-F11)*I11,0) -> 1.5 | O11: =IFERROR((C11*H11)/(D11*ABS(I11)),0) -> 0
A12: Price Action | B12: =COUNTIF(TRADE_LOG!$H$4:$H$5003,A12) -> 1 | C12: =COUNTIFS(TRADE_LOG!$H$4:$H$5003,A12,TRADE_LOG!$AH$4:$AH$5003,"Win") -> 1 | D12: =COUNTIFS(TRADE_LOG!$H$4:$H$5003,A12,TRADE_LOG!$AH$4:$AH$5003,"Loss") -> 0 | E12: =COUNTIFS(TRADE_LOG!$H$4:$H$5003,A12,TRADE_LOG!$AH$4:$AH$5003,"Breakeven") -> 0 | F12: =IFERROR(C12/B12,0) -> 1 | G12: =IFERROR(AVERAGEIF(TRADE_LOG!$H$4:$H$5003,A12,TRADE_LOG!$AG$4:$AG$5003),0) -> 1.8333333 | H12: =IFERROR(AVERAGEIFS(TRADE_LOG!$AG$4:$AG$5003,TRADE_LOG!$H$4:$H$5003,A12,TRADE_LOG!$AH$4:$AH$5003,"Win"),0) -> 1.8333333 | I12: =IFERROR(AVERAGEIFS(TRADE_LOG!$AG$4:$AG$5003,TRADE_LOG!$H$4:$H$5003,A12,TRADE_LOG!$AH$4:$AH$5003,"Loss"),0) -> 0 | J12: =IFERROR(maxifs(TRADE_LOG!$AG$4:$AG$5003,TRADE_LOG!$H$4:$H$5003,A12),0) -> 0 | K12: =IFERROR(minifs(TRADE_LOG!$AG$4:$AG$5003,TRADE_LOG!$H$4:$H$5003,A12),0) -> 0 | L12: =IFERROR(SUMIF(TRADE_LOG!$H$4:$H$5003,A12,TRADE_LOG!$AE$4:$AE$5003),0) -> 916.66667 | M12: =IFERROR(L12/B12,0) -> 916.66667 | N12: =IFERROR(F12*H12+(1-F12)*I12,0) -> 1.8333333 | O12: =IFERROR((C12*H12)/(D12*ABS(I12)),0) -> 0
A13: Harmonic | B13: =COUNTIF(TRADE_LOG!$H$4:$H$5003,A13) -> 0 | C13: =COUNTIFS(TRADE_LOG!$H$4:$H$5003,A13,TRADE_LOG!$AH$4:$AH$5003,"Win") -> 0 | D13: =COUNTIFS(TRADE_LOG!$H$4:$H$5003,A13,TRADE_LOG!$AH$4:$AH$5003,"Loss") -> 0 | E13: =COUNTIFS(TRADE_LOG!$H$4:$H$5003,A13,TRADE_LOG!$AH$4:$AH$5003,"Breakeven") -> 0 | F13: =IFERROR(C13/B13,0) -> 0 | G13: =IFERROR(AVERAGEIF(TRADE_LOG!$H$4:$H$5003,A13,TRADE_LOG!$AG$4:$AG$5003),0) -> 0 | H13: =IFERROR(AVERAGEIFS(TRADE_LOG!$AG$4:$AG$5003,TRADE_LOG!$H$4:$H$5003,A13,TRADE_LOG!$AH$4:$AH$5003,"Win"),0) -> 0 | I13: =IFERROR(AVERAGEIFS(TRADE_LOG!$AG$4:$AG$5003,TRADE_LOG!$H$4:$H$5003,A13,TRADE_LOG!$AH$4:$AH$5003,"Loss"),0) -> 0 | J13: =IFERROR(maxifs(TRADE_LOG!$AG$4:$AG$5003,TRADE_LOG!$H$4:$H$5003,A13),0) -> 0 | K13: =IFERROR(minifs(TRADE_LOG!$AG$4:$AG$5003,TRADE_LOG!$H$4:$H$5003,A13),0) -> 0 | L13: =IFERROR(SUMIF(TRADE_LOG!$H$4:$H$5003,A13,TRADE_LOG!$AE$4:$AE$5003),0) -> 0 | M13: =IFERROR(L13/B13,0) -> 0 | N13: =IFERROR(F13*H13+(1-F13)*I13,0) -> 0 | O13: =IFERROR((C13*H13)/(D13*ABS(I13)),0) -> 0
A14: Other | B14: =COUNTIF(TRADE_LOG!$H$4:$H$5003,A14) -> 0 | C14: =COUNTIFS(TRADE_LOG!$H$4:$H$5003,A14,TRADE_LOG!$AH$4:$AH$5003,"Win") -> 0 | D14: =COUNTIFS(TRADE_LOG!$H$4:$H$5003,A14,TRADE_LOG!$AH$4:$AH$5003,"Loss") -> 0 | E14: =COUNTIFS(TRADE_LOG!$H$4:$H$5003,A14,TRADE_LOG!$AH$4:$AH$5003,"Breakeven") -> 0 | F14: =IFERROR(C14/B14,0) -> 0 | G14: =IFERROR(AVERAGEIF(TRADE_LOG!$H$4:$H$5003,A14,TRADE_LOG!$AG$4:$AG$5003),0) -> 0 | H14: =IFERROR(AVERAGEIFS(TRADE_LOG!$AG$4:$AG$5003,TRADE_LOG!$H$4:$H$5003,A14,TRADE_LOG!$AH$4:$AH$5003,"Win"),0) -> 0 | I14: =IFERROR(AVERAGEIFS(TRADE_LOG!$AG$4:$AG$5003,TRADE_LOG!$H$4:$H$5003,A14,TRADE_LOG!$AH$4:$AH$5003,"Loss"),0) -> 0 | J14: =IFERROR(maxifs(TRADE_LOG!$AG$4:$AG$5003,TRADE_LOG!$H$4:$H$5003,A14),0) -> 0 | K14: =IFERROR(minifs(TRADE_LOG!$AG$4:$AG$5003,TRADE_LOG!$H$4:$H$5003,A14),0) -> 0 | L14: =IFERROR(SUMIF(TRADE_LOG!$H$4:$H$5003,A14,TRADE_LOG!$AE$4:$AE$5003),0) -> 0 | M14: =IFERROR(L14/B14,0) -> 0 | N14: =IFERROR(F14*H14+(1-F14)*I14,0) -> 0 | O14: =IFERROR((C14*H14)/(D14*ABS(I14)),0) -> 0
A16: ALL STRATEGIES | B16: =COUNTA(TRADE_LOG!H4:H5003) -> 5 | C16: =COUNTIF(TRADE_LOG!AH4:AH5003,"Win") -> 5 | D16: =COUNTIF(TRADE_LOG!AH4:AH5003,"Loss") -> 0 | E16: =COUNTIF(TRADE_LOG!AH4:AH5003,"Breakeven") -> 0 | F16: =IFERROR(C16/B16,0) -> 1 | G16: =IFERROR(AVERAGE(TRADE_LOG!AG4:AG5003),0) -> 1.8478581 | L16: =IFERROR(SUM(TRADE_LOG!AE4:AE5003),0) -> 5217.9785

Sheet PAIR_PERF
A1: 🌍 PAIR / INSTRUMENT PERFORMANCE
A3: Pair | B3: Total Trades | C3: Wins | D3: Losses | E3: Win Rate | F3: Net P/L $ | G3: Avg R-Multiple | H3: Best Trade R | I3: Worst Trade R | J3: Avg Pips | K3: Total Pips | L3: Profitability Rank | M3: Long Trades | N3: Short Trades
A4: EUR/USD | B4: =COUNTIF(TRADE_LOG!$E$4:$E$5003,A4) -> 2 | C4: =COUNTIFS(TRADE_LOG!$E$4:$E$5003,A4,TRADE_LOG!$AH$4:$AH$5003,"Win") -> 2 | D4: =COUNTIFS(TRADE_LOG!$E$4:$E$5003,A4,TRADE_LOG!$AH$4:$AH$5003,"Loss") -> 0 | E4: =IFERROR(C4/B4,0) -> 1 | F4: =IFERROR(SUMIF(TRADE_LOG!$E$4:$E$5003,A4,TRADE_LOG!$AE$4:$AE$5003),0) -> 1887.5 | G4: =IFERROR(AVERAGEIF(TRADE_LOG!$E$4:$E$5003,A4,TRADE_LOG!$AG$4:$AG$5003),0) -> 1.8875 | H4: =IFERROR(maxifs(TRADE_LOG!$AG$4:$AG$5003,TRADE_LOG!$E$4:$E$5003,A4),0) -> 0 | I4: =IFERROR(minifs(TRADE_LOG!$AG$4:$AG$5003,TRADE_LOG!$E$4:$E$5003,A4),0) -> 0 | J4: =IFERROR(AVERAGEIF(TRADE_LOG!$E$4:$E$5003,A4,TRADE_LOG!$AJ$4:$AJ$5003),0) -> 37.75 | K4: =IFERROR(SUMIF(TRADE_LOG!$E$4:$E$5003,A4,TRADE_LOG!$AJ$4:$AJ$5003),0) -> 75.5 | L4: =IFERROR(RANK(F4,$F$4:$F$15,0),"-") -> 1 | M4: =COUNTIFS(TRADE_LOG!$E$4:$E$5003,A4,TRADE_LOG!$F$4:$F$5003,"Buy") -> 2 | N4: =COUNTIFS(TRADE_LOG!$E$4:$E$5003,A4,TRADE_LOG!$F$4:$F$5003,"Sell") -> 0
A5: GBP/USD | B5: =COUNTIF(TRADE_LOG!$E$4:$E$5003,A5) -> 1 | C5: =COUNTIFS(TRADE_LOG!$E$4:$E$5003,A5,TRADE_LOG!$AH$4:$AH$5003,"Win") -> 1 | D5: =COUNTIFS(TRADE_LOG!$E$4:$E$5003,A5,TRADE_LOG!$AH$4:$AH$5003,"Loss") -> 0 | E5: =IFERROR(C5/B5,0) -> 1 | F5: =IFERROR(SUMIF(TRADE_LOG!$E$4:$E$5003,A5,TRADE_LOG!$AE$4:$AE$5003),0) -> 916.66667 | G5: =IFERROR(AVERAGEIF(TRADE_LOG!$E$4:$E$5003,A5,TRADE_LOG!$AG$4:$AG$5003),0) -> 1.8333333 | H5: =IFERROR(maxifs(TRADE_LOG!$AG$4:$AG$5003,TRADE_LOG!$E$4:$E$5003,A5),0) -> 0 | I5: =IFERROR(minifs(TRADE_LOG!$AG$4:$AG$5003,TRADE_LOG!$E$4:$E$5003,A5),0) -> 0 | J5: =IFERROR(AVERAGEIF(TRADE_LOG!$E$4:$E$5003,A5,TRADE_LOG!$AJ$4:$AJ$5003),0) -> 55 | K5: =IFERROR(SUMIF(TRADE_LOG!$E$4:$E$5003,A5,TRADE_LOG!$AJ$4:$AJ$5003),0) -> 55 | L5: =IFERROR(RANK(F5,$F$4:$F$15,0),"-") -> 3 | M5: =COUNTIFS(TRADE_LOG!$E$4:$E$5003,A5,TRADE_LOG!$F$4:$F$5003,"Buy") -> 0 | N5: =COUNTIFS(TRADE_LOG!$E$4:$E$5003,A5,TRADE_LOG!$F$4:$F$5003,"Sell") -> 1
A6: USD/JPY | B6: =COUNTIF(TRADE_LOG!$E$4:$E$5003,A6) -> 1 | C6: =COUNTIFS(TRADE_LOG!$E$4:$E$5003,A6,TRADE_LOG!$AH$4:$AH$5003,"Win") -> 1 | D6: =COUNTIFS(TRADE_LOG!$E$4:$E$5003,A6,TRADE_LOG!$AH$4:$AH$5003,"Loss") -> 0 | E6: =IFERROR(C6/B6,0) -> 1 | F6: =IFERROR(SUMIF(TRADE_LOG!$E$4:$E$5003,A6,TRADE_LOG!$AE$4:$AE$5003),0) -> 618.81188 | G6: =IFERROR(AVERAGEIF(TRADE_LOG!$E$4:$E$5003,A6,TRADE_LOG!$AG$4:$AG$5003),0) -> 1.2376238 | H6: =IFERROR(maxifs(TRADE_LOG!$AG$4:$AG$5003,TRADE_LOG!$E$4:$E$5003,A6),0) -> 0 | I6: =IFERROR(minifs(TRADE_LOG!$AG$4:$AG$5003,TRADE_LOG!$E$4:$E$5003,A6),0) -> 0 | J6: =IFERROR(AVERAGEIF(TRADE_LOG!$E$4:$E$5003,A6,TRADE_LOG!$AJ$4:$AJ$5003),0) -> 45 | K6: =IFERROR(SUMIF(TRADE_LOG!$E$4:$E$5003,A6,TRADE_LOG!$AJ$4:$AJ$5003),0) -> 45 | L6: =IFERROR(RANK(F6,$F$4:$F$15,0),"-") -> 4 | M6: =COUNTIFS(TRADE_LOG!$E$4:$E$5003,A6,TRADE_LOG!$F$4:$F$5003,"Buy") -> 0 | N6: =COUNTIFS(TRADE_LOG!$E$4:$E$5003,A6,TRADE_LOG!$F$4:$F$5003,"Sell") -> 1
A7: GBP/JPY | B7: =COUNTIF(TRADE_LOG!$E$4:$E$5003,A7) -> 0 | C7: =COUNTIFS(TRADE_LOG!$E$4:$E$5003,A7,TRADE_LOG!$AH$4:$AH$5003,"Win") -> 0 | D7: =COUNTIFS(TRADE_LOG!$E$4:$E$5003,A7,TRADE_LOG!$AH$4:$AH$5003,"Loss") -> 0 | E7: =IFERROR(C7/B7,0) -> 0 | F7: =IFERROR(SUMIF(TRADE_LOG!$E$4:$E$5003,A7,TRADE_LOG!$AE$4:$AE$5003),0) -> 0 | G7: =IFERROR(AVERAGEIF(TRADE_LOG!$E$4:$E$5003,A7,TRADE_LOG!$AG$4:$AG$5003),0) -> 0 | H7: =IFERROR(maxifs(TRADE_LOG!$AG$4:$AG$5003,TRADE_LOG!$E$4:$E$5003,A7),0) -> 0 | I7: =IFERROR(minifs(TRADE_LOG!$AG$4:$AG$5003,TRADE_LOG!$E$4:$E$5003,A7),0) -> 0 | J7: =IFERROR(AVERAGEIF(TRADE_LOG!$E$4:$E$5003,A7,TRADE_LOG!$AJ$4:$AJ$5003),0) -> 0 | K7: =IFERROR(SUMIF(TRADE_LOG!$E$4:$E$5003,A7,TRADE_LOG!$AJ$4:$AJ$5003),0) -> 0 | L7: =IFERROR(RANK(F7,$F$4:$F$15,0),"-") -> 5 | M7: =COUNTIFS(TRADE_LOG!$E$4:$E$5003,A7,TRADE_LOG!$F$4:$F$5003,"Buy") -> 0 | N7: =COUNTIFS(TRADE_LOG!$E$4:$E$5003,A7,TRADE_LOG!$F$4:$F$5003,"Sell") -> 0
A8: AUD/USD | B8: =COUNTIF(TRADE_LOG!$E$4:$E$5003,A8) -> 0 | C8: =COUNTIFS(TRADE_LOG!$E$4:$E$5003,A8,TRADE_LOG!$AH$4:$AH$5003,"Win") -> 0 | D8: =COUNTIFS(TRADE_LOG!$E$4:$E$5003,A8,TRADE_LOG!$AH$4:$AH$5003,"Loss") -> 0 | E8: =IFERROR(C8/B8,0) -> 0 | F8: =IFERROR(SUMIF(TRADE_LOG!$E$4:$E$5003,A8,TRADE_LOG!$AE$4:$AE$5003),0) -> 0 | G8: =IFERROR(AVERAGEIF(TRADE_LOG!$E$4:$E$5003,A8,TRADE_LOG!$AG$4:$AG$5003),0) -> 0 | H8: =IFERROR(maxifs(TRADE_LOG!$AG$4:$AG$5003,TRADE_LOG!$E$4:$E$5003,A8),0) -> 0 | I8: =IFERROR(minifs(TRADE_LOG!$AG$4:$AG$5003,TRADE_LOG!$E$4:$E$5003,A8),0) -> 0 | J8: =IFERROR(AVERAGEIF(TRADE_LOG!$E$4:$E$5003,A8,TRADE_LOG!$AJ$4:$AJ$5003),0) -> 0 | K8: =IFERROR(SUMIF(TRADE_LOG!$E$4:$E$5003,A8,TRADE_LOG!$AJ$4:$AJ$5003),0) -> 0 | L8: =IFERROR(RANK(F8,$F$4:$F$15,0),"-") -> 5 | M8: =COUNTIFS(TRADE_LOG!$E$4:$E$5003,A8,TRADE_LOG!$F$4:$F$5003,"Buy") -> 0 | N8: =COUNTIFS(TRADE_LOG!$E$4:$E$5003,A8,TRADE_LOG!$F$4:$F$5003,"Sell") -> 0
A9: USD/CAD | B9: =COUNTIF(TRADE_LOG!$E$4:$E$5003,A9) -> 0 | C9: =COUNTIFS(TRADE_LOG!$E$4:$E$5003,A9,TRADE_LOG!$AH$4:$AH$5003,"Win") -> 0 | D9: =COUNTIFS(TRADE_LOG!$E$4:$E$5003,A9,TRADE_LOG!$AH$4:$AH$5003,"Loss") -> 0 | E9: =IFERROR(C9/B9,0) -> 0 | F9: =IFERROR(SUMIF(TRADE_LOG!$E$4:$E$5003,A9,TRADE_LOG!$AE$4:$AE$5003),0) -> 0 | G9: =IFERROR(AVERAGEIF(TRADE_LOG!$E$4:$E$5003,A9,TRADE_LOG!$AG$4:$AG$5003),0) -> 0 | H9: =IFERROR(maxifs(TRADE_LOG!$AG$4:$AG$5003,TRADE_LOG!$E$4:$E$5003,A9),0) -> 0 | I9: =IFERROR(minifs(TRADE_LOG!$AG$4:$AG$5003,TRADE_LOG!$E$4:$E$5003,A9),0) -> 0 | J9: =IFERROR(AVERAGEIF(TRADE_LOG!$E$4:$E$5003,A9,TRADE_LOG!$AJ$4:$AJ$5003),0) -> 0 | K9: =IFERROR(SUMIF(TRADE_LOG!$E$4:$E$5003,A9,TRADE_LOG!$AJ$4:$AJ$5003),0) -> 0 | L9: =IFERROR(RANK(F9,$F$4:$F$15,0),"-") -> 5 | M9: =COUNTIFS(TRADE_LOG!$E$4:$E$5003,A9,TRADE_LOG!$F$4:$F$5003,"Buy") -> 0 | N9: =COUNTIFS(TRADE_LOG!$E$4:$E$5003,A9,TRADE_LOG!$F$4:$F$5003,"Sell") -> 0
A10: EUR/JPY | B10: =COUNTIF(TRADE_LOG!$E$4:$E$5003,A10) -> 0 | C10: =COUNTIFS(TRADE_LOG!$E$4:$E$5003,A10,TRADE_LOG!$AH$4:$AH$5003,"Win") -> 0 | D10: =COUNTIFS(TRADE_LOG!$E$4:$E$5003,A10,TRADE_LOG!$AH$4:$AH$5003,"Loss") -> 0 | E10: =IFERROR(C10/B10,0) -> 0 | F10: =IFERROR(SUMIF(TRADE_LOG!$E$4:$E$5003,A10,TRADE_LOG!$AE$4:$AE$5003),0) -> 0 | G10: =IFERROR(AVERAGEIF(TRADE_LOG!$E$4:$E$5003,A10,TRADE_LOG!$AG$4:$AG$5003),0) -> 0 | H10: =IFERROR(maxifs(TRADE_LOG!$AG$4:$AG$5003,TRADE_LOG!$E$4:$E$5003,A10),0) -> 0 | I10: =IFERROR(minifs(TRADE_LOG!$AG$4:$AG$5003,TRADE_LOG!$E$4:$E$5003,A10),0) -> 0 | J10: =IFERROR(AVERAGEIF(TRADE_LOG!$E$4:$E$5003,A10,TRADE_LOG!$AJ$4:$AJ$5003),0) -> 0 | K10: =IFERROR(SUMIF(TRADE_LOG!$E$4:$E$5003,A10,TRADE_LOG!$AJ$4:$AJ$5003),0) -> 0 | L10: =IFERROR(RANK(F10,$F$4:$F$15,0),"-") -> 5 | M10: =COUNTIFS(TRADE_LOG!$E$4:$E$5003,A10,TRADE_LOG!$F$4:$F$5003,"Buy") -> 0 | N10: =COUNTIFS(TRADE_LOG!$E$4:$E$5003,A10,TRADE_LOG!$F$4:$F$5003,"Sell") -> 0
A11: XAU/USD | B11: =COUNTIF(TRADE_LOG!$E$4:$E$5003,A11) -> 1 | C11: =COUNTIFS(TRADE_LOG!$E$4:$E$5003,A11,TRADE_LOG!$AH$4:$AH$5003,"Win") -> 1 | D11: =COUNTIFS(TRADE_LOG!$E$4:$E$5003,A11,TRADE_LOG!$AH$4:$AH$5003,"Loss") -> 0 | E11: =IFERROR(C11/B11,0) -> 1 | F11: =IFERROR(SUMIF(TRADE_LOG!$E$4:$E$5003,A11,TRADE_LOG!$AE$4:$AE$5003),0) -> 1795 | G11: =IFERROR(AVERAGEIF(TRADE_LOG!$E$4:$E$5003,A11,TRADE_LOG!$AG$4:$AG$5003),0) -> 2.3933333 | H11: =IFERROR(maxifs(TRADE_LOG!$AG$4:$AG$5003,TRADE_LOG!$E$4:$E$5003,A11),0) -> 0 | I11: =IFERROR(minifs(TRADE_LOG!$AG$4:$AG$5003,TRADE_LOG!$E$4:$E$5003,A11),0) -> 0 | J11: =IFERROR(AVERAGEIF(TRADE_LOG!$E$4:$E$5003,A11,TRADE_LOG!$AJ$4:$AJ$5003),0) -> 1795 | K11: =IFERROR(SUMIF(TRADE_LOG!$E$4:$E$5003,A11,TRADE_LOG!$AJ$4:$AJ$5003),0) -> 1795 | L11: =IFERROR(RANK(F11,$F$4:$F$15,0),"-") -> 2 | M11: =COUNTIFS(TRADE_LOG!$E$4:$E$5003,A11,TRADE_LOG!$F$4:$F$5003,"Buy") -> 1 | N11: =COUNTIFS(TRADE_LOG!$E$4:$E$5003,A11,TRADE_LOG!$F$4:$F$5003,"Sell") -> 0
A12: US30 | B12: =COUNTIF(TRADE_LOG!$E$4:$E$5003,A12) -> 0 | C12: =COUNTIFS(TRADE_LOG!$E$4:$E$5003,A12,TRADE_LOG!$AH$4:$AH$5003,"Win") -> 0 | D12: =COUNTIFS(TRADE_LOG!$E$4:$E$5003,A12,TRADE_LOG!$AH$4:$AH$5003,"Loss") -> 0 | E12: =IFERROR(C12/B12,0) -> 0 | F12: =IFERROR(SUMIF(TRADE_LOG!$E$4:$E$5003,A12,TRADE_LOG!$AE$4:$AE$5003),0) -> 0 | G12: =IFERROR(AVERAGEIF(TRADE_LOG!$E$4:$E$5003,A12,TRADE_LOG!$AG$4:$AG$5003),0) -> 0 | H12: =IFERROR(maxifs(TRADE_LOG!$AG$4:$AG$5003,TRADE_LOG!$E$4:$E$5003,A12),0) -> 0 | I12: =IFERROR(minifs(TRADE_LOG!$AG$4:$AG$5003,TRADE_LOG!$E$4:$E$5003,A12),0) -> 0 | J12: =IFERROR(AVERAGEIF(TRADE_LOG!$E$4:$E$5003,A12,TRADE_LOG!$AJ$4:$AJ$5003),0) -> 0 | K12: =IFERROR(SUMIF(TRADE_LOG!$E$4:$E$5003,A12,TRADE_LOG!$AJ$4:$AJ$5003),0) -> 0 | L12: =IFERROR(RANK(F12,$F$4:$F$15,0),"-") -> 5 | M12: =COUNTIFS(TRADE_LOG!$E$4:$E$5003,A12,TRADE_LOG!$F$4:$F$5003,"Buy") -> 0 | N12: =COUNTIFS(TRADE_LOG!$E$4:$E$5003,A12,TRADE_LOG!$F$4:$F$5003,"Sell") -> 0
A13: SPX500 | B13: =COUNTIF(TRADE_LOG!$E$4:$E$5003,A13) -> 0 | C13: =COUNTIFS(TRADE_LOG!$E$4:$E$5003,A13,TRADE_LOG!$AH$4:$AH$5003,"Win") -> 0 | D13: =COUNTIFS(TRADE_LOG!$E$4:$E$5003,A13,TRADE_LOG!$AH$4:$AH$5003,"Loss") -> 0 | E13: =IFERROR(C13/B13,0) -> 0 | F13: =IFERROR(SUMIF(TRADE_LOG!$E$4:$E$5003,A13,TRADE_LOG!$AE$4:$AE$5003),0) -> 0 | G13: =IFERROR(AVERAGEIF(TRADE_LOG!$E$4:$E$5003,A13,TRADE_LOG!$AG$4:$AG$5003),0) -> 0 | H13: =IFERROR(maxifs(TRADE_LOG!$AG$4:$AG$5003,TRADE_LOG!$E$4:$E$5003,A13),0) -> 0 | I13: =IFERROR(minifs(TRADE_LOG!$AG$4:$AG$5003,TRADE_LOG!$E$4:$E$5003,A13),0) -> 0 | J13: =IFERROR(AVERAGEIF(TRADE_LOG!$E$4:$E$5003,A13,TRADE_LOG!$AJ$4:$AJ$5003),0) -> 0 | K13: =IFERROR(SUMIF(TRADE_LOG!$E$4:$E$5003,A13,TRADE_LOG!$AJ$4:$AJ$5003),0) -> 0 | L13: =IFERROR(RANK(F13,$F$4:$F$15,0),"-") -> 5 | M13: =COUNTIFS(TRADE_LOG!$E$4:$E$5003,A13,TRADE_LOG!$F$4:$F$5003,"Buy") -> 0 | N13: =COUNTIFS(TRADE_LOG!$E$4:$E$5003,A13,TRADE_LOG!$F$4:$F$5003,"Sell") -> 0
A14: NAS100 | B14: =COUNTIF(TRADE_LOG!$E$4:$E$5003,A14) -> 0 | C14: =COUNTIFS(TRADE_LOG!$E$4:$E$5003,A14,TRADE_LOG!$AH$4:$AH$5003,"Win") -> 0 | D14: =COUNTIFS(TRADE_LOG!$E$4:$E$5003,A14,TRADE_LOG!$AH$4:$AH$5003,"Loss") -> 0 | E14: =IFERROR(C14/B14,0) -> 0 | F14: =IFERROR(SUMIF(TRADE_LOG!$E$4:$E$5003,A14,TRADE_LOG!$AE$4:$AE$5003),0) -> 0 | G14: =IFERROR(AVERAGEIF(TRADE_LOG!$E$4:$E$5003,A14,TRADE_LOG!$AG$4:$AG$5003),0) -> 0 | H14: =IFERROR(maxifs(TRADE_LOG!$AG$4:$AG$5003,TRADE_LOG!$E$4:$E$5003,A14),0) -> 0 | I14: =IFERROR(minifs(TRADE_LOG!$AG$4:$AG$5003,TRADE_LOG!$E$4:$E$5003,A14),0) -> 0 | J14: =IFERROR(AVERAGEIF(TRADE_LOG!$E$4:$E$5003,A14,TRADE_LOG!$AJ$4:$AJ$5003),0) -> 0 | K14: =IFERROR(SUMIF(TRADE_LOG!$E$4:$E$5003,A14,TRADE_LOG!$AJ$4:$AJ$5003),0) -> 0 | L14: =IFERROR(RANK(F14,$F$4:$F$15,0),"-") -> 5 | M14: =COUNTIFS(TRADE_LOG!$E$4:$E$5003,A14,TRADE_LOG!$F$4:$F$5003,"Buy") -> 0 | N14: =COUNTIFS(TRADE_LOG!$E$4:$E$5003,A14,TRADE_LOG!$F$4:$F$5003,"Sell") -> 0
A15: UK100 | B15: =COUNTIF(TRADE_LOG!$E$4:$E$5003,A15) -> 0 | C15: =COUNTIFS(TRADE_LOG!$E$4:$E$5003,A15,TRADE_LOG!$AH$4:$AH$5003,"Win") -> 0 | D15: =COUNTIFS(TRADE_LOG!$E$4:$E$5003,A15,TRADE_LOG!$AH$4:$AH$5003,"Loss") -> 0 | E15: =IFERROR(C15/B15,0) -> 0 | F15: =IFERROR(SUMIF(TRADE_LOG!$E$4:$E$5003,A15,TRADE_LOG!$AE$4:$AE$5003),0) -> 0 | G15: =IFERROR(AVERAGEIF(TRADE_LOG!$E$4:$E$5003,A15,TRADE_LOG!$AG$4:$AG$5003),0) -> 0 | H15: =IFERROR(maxifs(TRADE_LOG!$AG$4:$AG$5003,TRADE_LOG!$E$4:$E$5003,A15),0) -> 0 | I15: =IFERROR(minifs(TRADE_LOG!$AG$4:$AG$5003,TRADE_LOG!$E$4:$E$5003,A15),0) -> 0 | J15: =IFERROR(AVERAGEIF(TRADE_LOG!$E$4:$E$5003,A15,TRADE_LOG!$AJ$4:$AJ$5003),0) -> 0 | K15: =IFERROR(SUMIF(TRADE_LOG!$E$4:$E$5003,A15,TRADE_LOG!$AJ$4:$AJ$5003),0) -> 0 | L15: =IFERROR(RANK(F15,$F$4:$F$15,0),"-") -> 5 | M15: =COUNTIFS(TRADE_LOG!$E$4:$E$5003,A15,TRADE_LOG!$F$4:$F$5003,"Buy") -> 0 | N15: =COUNTIFS(TRADE_LOG!$E$4:$E$5003,A15,TRADE_LOG!$F$4:$F$5003,"Sell") -> 0

Sheet CALENDAR
A1: 📅 CALENDAR VIEW — Daily P/L & R Summary
A2: DAILY SUMMARY — Each row = one trading day. Conditional formatting: Green=Net Win, Red=Net Loss, Amber=Breakeven.
A4: Select Year: | B4: 2024 | C4: Select Month: | D4: 1 | E4: Month Total R: | F4: =SUMPRODUCT((MONTH(TRADE_LOG!B4:B5003)=D4)*(YEAR(TRADE_LOG!B4:B5003)=B4)*N(TRADE_LOG!AG4:AG5003)) -> 9.2392904 | G4: Month P/L $: | H4: =SUMPRODUCT((MONTH(TRADE_LOG!B4:B5003)=D4)*(YEAR(TRADE_LOG!B4:B5003)=B4)*N(TRADE_LOG!AE4:AE5003)) -> 5217.9785 | I4: Month Trades: | J4: =SUMPRODUCT((MONTH(TRADE_LOG!B4:B5003)=D4)*(YEAR(TRADE_LOG!B4:B5003)=B4)*(TRADE_LOG!B4:B5003<>"")) -> 5 | K4: Win Days: | L4: =COUNTIF(F7:F37,">0.05") -> 5 | M4: Loss Days: | N4: =COUNTIF(F7:F37,"<-0.05") -> 0 | O4: Win Rate (Days): | P4: =IFERROR(L4/(L4+N4),0) -> 1
A6: Date | B6: Day | C6: Trades | D6: Wins | E6: Losses | F6: Net R | G6: Net P/L $ | H6: Best R | I6: Worst R | J6: Pips | K6: Running Balance | L6: Day Status
A7: =IFERROR(IF(DAY(DATE($B$4,$D$4,1))=1,DATE($B$4,$D$4,1),""),"") -> 45292 | B7: =IF(A7="","",TEXT(A7,"DDD")) -> Mon | C7: =IF(A7="","",COUNTIF(TRADE_LOG!$B$4:$B$5003,A7)) -> 0 | D7: =IF(A7="","",COUNTIFS(TRADE_LOG!$B$4:$B$5003,A7,TRADE_LOG!$AH$4:$AH$5003,"Win")) -> 0 | E7: =IF(A7="","",COUNTIFS(TRADE_LOG!$B$4:$B$5003,A7,TRADE_LOG!$AH$4:$AH$5003,"Loss")) -> 0 | F7: =IF(A7="","",SUMPRODUCT((TRADE_LOG!$B$4:$B$5003=A7)*N(TRADE_LOG!$AG$4:$AG$5003))) -> 0 | G7: =IF(A7="","",SUMPRODUCT((TRADE_LOG!$B$4:$B$5003=A7)*N(TRADE_LOG!$AE$4:$AE$5003))) -> 0 | H7: =IF(A7="","",IFERROR(maxifs(TRADE_LOG!$AG$4:$AG$5003,TRADE_LOG!$B$4:$B$5003,A7,TRADE_LOG!$AG$4:$AG$5003,"<>"),0)) -> 0 | I7: =IF(A7="","",IFERROR(minifs(TRADE_LOG!$AG$4:$AG$5003,TRADE_LOG!$B$4:$B$5003,A7,TRADE_LOG!$AG$4:$AG$5003,"<>"),0)) -> 0 | J7: =IF(A7="","",SUMPRODUCT((TRADE_LOG!$B$4:$B$5003=A7)*N(TRADE_LOG!$AJ$4:$AJ$5003))) -> 0 | K7: =IF(A7="","",SETTINGS!$B$6+SUMPRODUCT((TRADE_LOG!$B$4:$B$5003<>"")*N(TRADE_LOG!$B$4:$B$5003<=A7)*N(TRADE_LOG!$AE$4:$AE$5003))) -> 50000 | L7: =IF(A7="","",IF(C7=0,"—",IF(F7>0.05,"✅ WIN DAY",IF(F7<-0.05,"❌ LOSS DAY","🔶 BE DAY")))) -> —
A8: =IFERROR(IF(DAY(DATE($B$4,$D$4,2))=2,DATE($B$4,$D$4,2),""),"") -> 45293 | B8: =IF(A8="","",TEXT(A8,"DDD")) -> Tue | C8: =IF(A8="","",COUNTIF(TRADE_LOG!$B$4:$B$5003,A8)) -> 0 | D8: =IF(A8="","",COUNTIFS(TRADE_LOG!$B$4:$B$5003,A8,TRADE_LOG!$AH$4:$AH$5003,"Win")) -> 0 | E8: =IF(A8="","",COUNTIFS(TRADE_LOG!$B$4:$B$5003,A8,TRADE_LOG!$AH$4:$AH$5003,"Loss")) -> 0 | F8: =IF(A8="","",SUMPRODUCT((TRADE_LOG!$B$4:$B$5003=A8)*N(TRADE_LOG!$AG$4:$AG$5003))) -> 0 | G8: =IF(A8="","",SUMPRODUCT((TRADE_LOG!$B$4:$B$5003=A8)*N(TRADE_LOG!$AE$4:$AE$5003))) -> 0 | H8: =IF(A8="","",IFERROR(maxifs(TRADE_LOG!$AG$4:$AG$5003,TRADE_LOG!$B$4:$B$5003,A8,TRADE_LOG!$AG$4:$AG$5003,"<>"),0)) -> 0 | I8: =IF(A8="","",IFERROR(minifs(TRADE_LOG!$AG$4:$AG$5003,TRADE_LOG!$B$4:$B$5003,A8,TRADE_LOG!$AG$4:$AG$5003,"<>"),0)) -> 0 | J8: =IF(A8="","",SUMPRODUCT((TRADE_LOG!$B$4:$B$5003=A8)*N(TRADE_LOG!$AJ$4:$AJ$5003))) -> 0 | K8: =IF(A8="","",SETTINGS!$B$6+SUMPRODUCT((TRADE_LOG!$B$4:$B$5003<>"")*N(TRADE_LOG!$B$4:$B$5003<=A8)*N(TRADE_LOG!$AE$4:$AE$5003))) -> 50000 | L8: =IF(A8="","",IF(C8=0,"—",IF(F8>0.05,"✅ WIN DAY",IF(F8<-0.05,"❌ LOSS DAY","🔶 BE DAY")))) -> —
A9: =IFERROR(IF(DAY(DATE($B$4,$D$4,3))=3,DATE($B$4,$D$4,3),""),"") -> 45294 | B9: =IF(A9="","",TEXT(A9,"DDD")) -> Wed | C9: =IF(A9="","",COUNTIF(TRADE_LOG!$B$4:$B$5003,A9)) -> 0 | D9: =IF(A9="","",COUNTIFS(TRADE_LOG!$B$4:$B$5003,A9,TRADE_LOG!$AH$4:$AH$5003,"Win")) -> 0 | E9: =IF(A9="","",COUNTIFS(TRADE_LOG!$B$4:$B$5003,A9,TRADE_LOG!$AH$4:$AH$5003,"Loss")) -> 0 | F9: =IF(A9="","",SUMPRODUCT((TRADE_LOG!$B$4:$B$5003=A9)*N(TRADE_LOG!$AG$4:$AG$5003))) -> 0 | G9: =IF(A9="","",SUMPRODUCT((TRADE_LOG!$B$4:$B$5003=A9)*N(TRADE_LOG!$AE$4:$AE$5003))) -> 0 | H9: =IF(A9="","",IFERROR(maxifs(TRADE_LOG!$AG$4:$AG$5003,TRADE_LOG!$B$4:$B$5003,A9,TRADE_LOG!$AG$4:$AG$5003,"<>"),0)) -> 0 | I9: =IF(A9="","",IFERROR(minifs(TRADE_LOG!$AG$4:$AG$5003,TRADE_LOG!$B$4:$B$5003,A9,TRADE_LOG!$AG$4:$AG$5003,"<>"),0)) -> 0 | J9: =IF(A9="","",SUMPRODUCT((TRADE_LOG!$B$4:$B$5003=A9)*N(TRADE_LOG!$AJ$4:$AJ$5003))) -> 0 | K9: =IF(A9="","",SETTINGS!$B$6+SUMPRODUCT((TRADE_LOG!$B$4:$B$5003<>"")*N(TRADE_LOG!$B$4:$B$5003<=A9)*N(TRADE_LOG!$AE$4:$AE$5003))) -> 50000 | L9: =IF(A9="","",IF(C9=0,"—",IF(F9>0.05,"✅ WIN DAY",IF(F9<-0.05,"❌ LOSS DAY","🔶 BE DAY")))) -> —
A10: =IFERROR(IF(DAY(DATE($B$4,$D$4,4))=4,DATE($B$4,$D$4,4),""),"") -> 45295 | B10: =IF(A10="","",TEXT(A10,"DDD")) -> Thu | C10: =IF(A10="","",COUNTIF(TRADE_LOG!$B$4:$B$5003,A10)) -> 0 | D10: =IF(A10="","",COUNTIFS(TRADE_LOG!$B$4:$B$5003,A10,TRADE_LOG!$AH$4:$AH$5003,"Win")) -> 0 | E10: =IF(A10="","",COUNTIFS(TRADE_LOG!$B$4:$B$5003,A10,TRADE_LOG!$AH$4:$AH$5003,"Loss")) -> 0 | F10: =IF(A10="","",SUMPRODUCT((TRADE_LOG!$B$4:$B$5003=A10)*N(TRADE_LOG!$AG$4:$AG$5003))) -> 0 | G10: =IF(A10="","",SUMPRODUCT((TRADE_LOG!$B$4:$B$5003=A10)*N(TRADE_LOG!$AE$4:$AE$5003))) -> 0 | H10: =IF(A10="","",IFERROR(maxifs(TRADE_LOG!$AG$4:$AG$5003,TRADE_LOG!$B$4:$B$5003,A10,TRADE_LOG!$AG$4:$AG$5003,"<>"),0)) -> 0 | I10: =IF(A10="","",IFERROR(minifs(TRADE_LOG!$AG$4:$AG$5003,TRADE_LOG!$B$4:$B$5003,A10,TRADE_LOG!$AG$4:$AG$5003,"<>"),0)) -> 0 | J10: =IF(A10="","",SUMPRODUCT((TRADE_LOG!$B$4:$B$5003=A10)*N(TRADE_LOG!$AJ$4:$AJ$5003))) -> 0 | K10: =IF(A10="","",SETTINGS!$B$6+SUMPRODUCT((TRADE_LOG!$B$4:$B$5003<>"")*N(TRADE_LOG!$B$4:$B$5003<=A10)*N(TRADE_LOG!$AE$4:$AE$5003))) -> 50000 | L10: =IF(A10="","",IF(C10=0,"—",IF(F10>0.05,"✅ WIN DAY",IF(F10<-0.05,"❌ LOSS DAY","🔶 BE DAY")))) -> —
A11: =IFERROR(IF(DAY(DATE($B$4,$D$4,5))=5,DATE($B$4,$D$4,5),""),"") -> 45296 | B11: =IF(A11="","",TEXT(A11,"DDD")) -> Fri | C11: =IF(A11="","",COUNTIF(TRADE_LOG!$B$4:$B$5003,A11)) -> 0 | D11: =IF(A11="","",COUNTIFS(TRADE_LOG!$B$4:$B$5003,A11,TRADE_LOG!$AH$4:$AH$5003,"Win")) -> 0 | E11: =IF(A11="","",COUNTIFS(TRADE_LOG!$B$4:$B$5003,A11,TRADE_LOG!$AH$4:$AH$5003,"Loss")) -> 0 | F11: =IF(A11="","",SUMPRODUCT((TRADE_LOG!$B$4:$B$5003=A11)*N(TRADE_LOG!$AG$4:$AG$5003))) -> 0 | G11: =IF(A11="","",SUMPRODUCT((TRADE_LOG!$B$4:$B$5003=A11)*N(TRADE_LOG!$AE$4:$AE$5003))) -> 0 | H11: =IF(A11="","",IFERROR(maxifs(TRADE_LOG!$AG$4:$AG$5003,TRADE_LOG!$B$4:$B$5003,A11,TRADE_LOG!$AG$4:$AG$5003,"<>"),0)) -> 0 | I11: =IF(A11="","",IFERROR(minifs(TRADE_LOG!$AG$4:$AG$5003,TRADE_LOG!$B$4:$B$5003,A11,TRADE_LOG!$AG$4:$AG$5003,"<>"),0)) -> 0 | J11: =IF(A11="","",SUMPRODUCT((TRADE_LOG!$B$4:$B$5003=A11)*N(TRADE_LOG!$AJ$4:$AJ$5003))) -> 0 | K11: =IF(A11="","",SETTINGS!$B$6+SUMPRODUCT((TRADE_LOG!$B$4:$B$5003<>"")*N(TRADE_LOG!$B$4:$B$5003<=A11)*N(TRADE_LOG!$AE$4:$AE$5003))) -> 50000 | L11: =IF(A11="","",IF(C11=0,"—",IF(F11>0.05,"✅ WIN DAY",IF(F11<-0.05,"❌ LOSS DAY","🔶 BE DAY")))) -> —
A12: =IFERROR(IF(DAY(DATE($B$4,$D$4,6))=6,DATE($B$4,$D$4,6),""),"") -> 45297 | B12: =IF(A12="","",TEXT(A12,"DDD")) -> Sat | C12: =IF(A12="","",COUNTIF(TRADE_LOG!$B$4:$B$5003,A12)) -> 0 | D12: =IF(A12="","",COUNTIFS(TRADE_LOG!$B$4:$B$5003,A12,TRADE_LOG!$AH$4:$AH$5003,"Win")) -> 0 | E12: =IF(A12="","",COUNTIFS(TRADE_LOG!$B$4:$B$5003,A12,TRADE_LOG!$AH$4:$AH$5003,"Loss")) -> 0 | F12: =IF(A12="","",SUMPRODUCT((TRADE_LOG!$B$4:$B$5003=A12)*N(TRADE_LOG!$AG$4:$AG$5003))) -> 0 | G12: =IF(A12="","",SUMPRODUCT((TRADE_LOG!$B$4:$B$5003=A12)*N(TRADE_LOG!$AE$4:$AE$5003))) -> 0 | H12: =IF(A12="","",IFERROR(maxifs(TRADE_LOG!$AG$4:$AG$5003,TRADE_LOG!$B$4:$B$5003,A12,TRADE_LOG!$AG$4:$AG$5003,"<>"),0)) -> 0 | I12: =IF(A12="","",IFERROR(minifs(TRADE_LOG!$AG$4:$AG$5003,TRADE_LOG!$B$4:$B$5003,A12,TRADE_LOG!$AG$4:$AG$5003,"<>"),0)) -> 0 | J12: =IF(A12="","",SUMPRODUCT((TRADE_LOG!$B$4:$B$5003=A12)*N(TRADE_LOG!$AJ$4:$AJ$5003))) -> 0 | K12: =IF(A12="","",SETTINGS!$B$6+SUMPRODUCT((TRADE_LOG!$B$4:$B$5003<>"")*N(TRADE_LOG!$B$4:$B$5003<=A12)*N(TRADE_LOG!$AE$4:$AE$5003))) -> 50000 | L12: =IF(A12="","",IF(C12=0,"—",IF(F12>0.05,"✅ WIN DAY",IF(F12<-0.05,"❌ LOSS DAY","🔶 BE DAY")))) -> —
A13: =IFERROR(IF(DAY(DATE($B$4,$D$4,7))=7,DATE($B$4,$D$4,7),""),"") -> 45298 | B13: =IF(A13="","",TEXT(A13,"DDD")) -> Sun | C13: =IF(A13="","",COUNTIF(TRADE_LOG!$B$4:$B$5003,A13)) -> 0 | D13: =IF(A13="","",COUNTIFS(TRADE_LOG!$B$4:$B$5003,A13,TRADE_LOG!$AH$4:$AH$5003,"Win")) -> 0 | E13: =IF(A13="","",COUNTIFS(TRADE_LOG!$B$4:$B$5003,A13,TRADE_LOG!$AH$4:$AH$5003,"Loss")) -> 0 | F13: =IF(A13="","",SUMPRODUCT((TRADE_LOG!$B$4:$B$5003=A13)*N(TRADE_LOG!$AG$4:$AG$5003))) -> 0 | G13: =IF(A13="","",SUMPRODUCT((TRADE_LOG!$B$4:$B$5003=A13)*N(TRADE_LOG!$AE$4:$AE$5003))) -> 0 | H13: =IF(A13="","",IFERROR(maxifs(TRADE_LOG!$AG$4:$AG$5003,TRADE_LOG!$B$4:$B$5003,A13,TRADE_LOG!$AG$4:$AG$5003,"<>"),0)) -> 0 | I13: =IF(A13="","",IFERROR(minifs(TRADE_LOG!$AG$4:$AG$5003,TRADE_LOG!$B$4:$B$5003,A13,TRADE_LOG!$AG$4:$AG$5003,"<>"),0)) -> 0 | J13: =IF(A13="","",SUMPRODUCT((TRADE_LOG!$B$4:$B$5003=A13)*N(TRADE_LOG!$AJ$4:$AJ$5003))) -> 0 | K13: =IF(A13="","",SETTINGS!$B$6+SUMPRODUCT((TRADE_LOG!$B$4:$B$5003<>"")*N(TRADE_LOG!$B$4:$B$5003<=A13)*N(TRADE_LOG!$AE$4:$AE$5003))) -> 50000 | L13: =IF(A13="","",IF(C13=0,"—",IF(F13>0.05,"✅ WIN DAY",IF(F13<-0.05,"❌ LOSS DAY","🔶 BE DAY")))) -> —
A14: =IFERROR(IF(DAY(DATE($B$4,$D$4,8))=8,DATE($B$4,$D$4,8),""),"") -> 45299 | B14: =IF(A14="","",TEXT(A14,"DDD")) -> Mon | C14: =IF(A14="","",COUNTIF(TRADE_LOG!$B$4:$B$5003,A14)) -> 0 | D14: =IF(A14="","",COUNTIFS(TRADE_LOG!$B$4:$B$5003,A14,TRADE_LOG!$AH$4:$AH$5003,"Win")) -> 0 | E14: =IF(A14="","",COUNTIFS(TRADE_LOG!$B$4:$B$5003,A14,TRADE_LOG!$AH$4:$AH$5003,"Loss")) -> 0 | F14: =IF(A14="","",SUMPRODUCT((TRADE_LOG!$B$4:$B$5003=A14)*N(TRADE_LOG!$AG$4:$AG$5003))) -> 0 | G14: =IF(A14="","",SUMPRODUCT((TRADE_LOG!$B$4:$B$5003=A14)*N(TRADE_LOG!$AE$4:$AE$5003))) -> 0 | H14: =IF(A14="","",IFERROR(maxifs(TRADE_LOG!$AG$4:$AG$5003,TRADE_LOG!$B$4:$B$5003,A14,TRADE_LOG!$AG$4:$AG$5003,"<>"),0)) -> 0 | I14: =IF(A14="","",IFERROR(minifs(TRADE_LOG!$AG$4:$AG$5003,TRADE_LOG!$B$4:$B$5003,A14,TRADE_LOG!$AG$4:$AG$5003,"<>"),0)) -> 0 | J14: =IF(A14="","",SUMPRODUCT((TRADE_LOG!$B$4:$B$5003=A14)*N(TRADE_LOG!$AJ$4:$AJ$5003))) -> 0 | K14: =IF(A14="","",SETTINGS!$B$6+SUMPRODUCT((TRADE_LOG!$B$4:$B$5003<>"")*N(TRADE_LOG!$B$4:$B$5003<=A14)*N(TRADE_LOG!$AE$4:$AE$5003))) -> 50000 | L14: =IF(A14="","",IF(C14=0,"—",IF(F14>0.05,"✅ WIN DAY",IF(F14<-0.05,"❌ LOSS DAY","🔶 BE DAY")))) -> —
A15: =IFERROR(IF(DAY(DATE($B$4,$D$4,9))=9,DATE($B$4,$D$4,9),""),"") -> 45300 | B15: =IF(A15="","",TEXT(A15,"DDD")) -> Tue | C15: =IF(A15="","",COUNTIF(TRADE_LOG!$B$4:$B$5003,A15)) -> 0 | D15: =IF(A15="","",COUNTIFS(TRADE_LOG!$B$4:$B$5003,A15,TRADE_LOG!$AH$4:$AH$5003,"Win")) -> 0 | E15: =IF(A15="","",COUNTIFS(TRADE_LOG!$B$4:$B$5003,A15,TRADE_LOG!$AH$4:$AH$5003,"Loss")) -> 0 | F15: =IF(A15="","",SUMPRODUCT((TRADE_LOG!$B$4:$B$5003=A15)*N(TRADE_LOG!$AG$4:$AG$5003))) -> 0 | G15: =IF(A15="","",SUMPRODUCT((TRADE_LOG!$B$4:$B$5003=A15)*N(TRADE_LOG!$AE$4:$AE$5003))) -> 0 | H15: =IF(A15="","",IFERROR(maxifs(TRADE_LOG!$AG$4:$AG$5003,TRADE_LOG!$B$4:$B$5003,A15,TRADE_LOG!$AG$4:$AG$5003,"<>"),0)) -> 0 | I15: =IF(A15="","",IFERROR(minifs(TRADE_LOG!$AG$4:$AG$5003,TRADE_LOG!$B$4:$B$5003,A15,TRADE_LOG!$AG$4:$AG$5003,"<>"),0)) -> 0 | J15: =IF(A15="","",SUMPRODUCT((TRADE_LOG!$B$4:$B$5003=A15)*N(TRADE_LOG!$AJ$4:$AJ$5003))) -> 0 | K15: =IF(A15="","",SETTINGS!$B$6+SUMPRODUCT((TRADE_LOG!$B$4:$B$5003<>"")*N(TRADE_LOG!$B$4:$B$5003<=A15)*N(TRADE_LOG!$AE$4:$AE$5003))) -> 50000 | L15: =IF(A15="","",IF(C15=0,"—",IF(F15>0.05,"✅ WIN DAY",IF(F15<-0.05,"❌ LOSS DAY","🔶 BE DAY")))) -> —
A16: =IFERROR(IF(DAY(DATE($B$4,$D$4,10))=10,DATE($B$4,$D$4,10),""),"") -> 45301 | B16: =IF(A16="","",TEXT(A16,"DDD")) -> Wed | C16: =IF(A16="","",COUNTIF(TRADE_LOG!$B$4:$B$5003,A16)) -> 0 | D16: =IF(A16="","",COUNTIFS(TRADE_LOG!$B$4:$B$5003,A16,TRADE_LOG!$AH$4:$AH$5003,"Win")) -> 0 | E16: =IF(A16="","",COUNTIFS(TRADE_LOG!$B$4:$B$5003,A16,TRADE_LOG!$AH$4:$AH$5003,"Loss")) -> 0 | F16: =IF(A16="","",SUMPRODUCT((TRADE_LOG!$B$4:$B$5003=A16)*N(TRADE_LOG!$AG$4:$AG$5003))) -> 0 | G16: =IF(A16="","",SUMPRODUCT((TRADE_LOG!$B$4:$B$5003=A16)*N(TRADE_LOG!$AE$4:$AE$5003))) -> 0 | H16: =IF(A16="","",IFERROR(maxifs(TRADE_LOG!$AG$4:$AG$5003,TRADE_LOG!$B$4:$B$5003,A16,TRADE_LOG!$AG$4:$AG$5003,"<>"),0)) -> 0 | I16: =IF(A16="","",IFERROR(minifs(TRADE_LOG!$AG$4:$AG$5003,TRADE_LOG!$B$4:$B$5003,A16,TRADE_LOG!$AG$4:$AG$5003,"<>"),0)) -> 0 | J16: =IF(A16="","",SUMPRODUCT((TRADE_LOG!$B$4:$B$5003=A16)*N(TRADE_LOG!$AJ$4:$AJ$5003))) -> 0 | K16: =IF(A16="","",SETTINGS!$B$6+SUMPRODUCT((TRADE_LOG!$B$4:$B$5003<>"")*N(TRADE_LOG!$B$4:$B$5003<=A16)*N(TRADE_LOG!$AE$4:$AE$5003))) -> 50000 | L16: =IF(A16="","",IF(C16=0,"—",IF(F16>0.05,"✅ WIN DAY",IF(F16<-0.05,"❌ LOSS DAY","🔶 BE DAY")))) -> —
A17: =IFERROR(IF(DAY(DATE($B$4,$D$4,11))=11,DATE($B$4,$D$4,11),""),"") -> 45302 | B17: =IF(A17="","",TEXT(A17,"DDD")) -> Thu | C17: =IF(A17="","",COUNTIF(TRADE_LOG!$B$4:$B$5003,A17)) -> 0 | D17: =IF(A17="","",COUNTIFS(TRADE_LOG!$B$4:$B$5003,A17,TRADE_LOG!$AH$4:$AH$5003,"Win")) -> 0 | E17: =IF(A17="","",COUNTIFS(TRADE_LOG!$B$4:$B$5003,A17,TRADE_LOG!$AH$4:$AH$5003,"Loss")) -> 0 | F17: =IF(A17="","",SUMPRODUCT((TRADE_LOG!$B$4:$B$5003=A17)*N(TRADE_LOG!$AG$4:$AG$5003))) -> 0 | G17: =IF(A17="","",SUMPRODUCT((TRADE_LOG!$B$4:$B$5003=A17)*N(TRADE_LOG!$AE$4:$AE$5003))) -> 0 | H17: =IF(A17="","",IFERROR(maxifs(TRADE_LOG!$AG$4:$AG$5003,TRADE_LOG!$B$4:$B$5003,A17,TRADE_LOG!$AG$4:$AG$5003,"<>"),0)) -> 0 | I17: =IF(A17="","",IFERROR(minifs(TRADE_LOG!$AG$4:$AG$5003,TRADE_LOG!$B$4:$B$5003,A17,TRADE_LOG!$AG$4:$AG$5003,"<>"),0)) -> 0 | J17: =IF(A17="","",SUMPRODUCT((TRADE_LOG!$B$4:$B$5003=A17)*N(TRADE_LOG!$AJ$4:$AJ$5003))) -> 0 | K17: =IF(A17="","",SETTINGS!$B$6+SUMPRODUCT((TRADE_LOG!$B$4:$B$5003<>"")*N(TRADE_LOG!$B$4:$B$5003<=A17)*N(TRADE_LOG!$AE$4:$AE$5003))) -> 50000 | L17: =IF(A17="","",IF(C17=0,"—",IF(F17>0.05,"✅ WIN DAY",IF(F17<-0.05,"❌ LOSS DAY","🔶 BE DAY")))) -> —
A18: =IFERROR(IF(DAY(DATE($B$4,$D$4,12))=12,DATE($B$4,$D$4,12),""),"") -> 45303 | B18: =IF(A18="","",TEXT(A18,"DDD")) -> Fri | C18: =IF(A18="","",COUNTIF(TRADE_LOG!$B$4:$B$5003,A18)) -> 0 | D18: =IF(A18="","",COUNTIFS(TRADE_LOG!$B$4:$B$5003,A18,TRADE_LOG!$AH$4:$AH$5003,"Win")) -> 0 | E18: =IF(A18="","",COUNTIFS(TRADE_LOG!$B$4:$B$5003,A18,TRADE_LOG!$AH$4:$AH$5003,"Loss")) -> 0 | F18: =IF(A18="","",SUMPRODUCT((TRADE_LOG!$B$4:$B$5003=A18)*N(TRADE_LOG!$AG$4:$AG$5003))) -> 0 | G18: =IF(A18="","",SUMPRODUCT((TRADE_LOG!$B$4:$B$5003=A18)*N(TRADE_LOG!$AE$4:$AE$5003))) -> 0 | H18: =IF(A18="","",IFERROR(maxifs(TRADE_LOG!$AG$4:$AG$5003,TRADE_LOG!$B$4:$B$5003,A18,TRADE_LOG!$AG$4:$AG$5003,"<>"),0)) -> 0 | I18: =IF(A18="","",IFERROR(minifs(TRADE_LOG!$AG$4:$AG$5003,TRADE_LOG!$B$4:$B$5003,A18,TRADE_LOG!$AG$4:$AG$5003,"<>"),0)) -> 0 | J18: =IF(A18="","",SUMPRODUCT((TRADE_LOG!$B$4:$B$5003=A18)*N(TRADE_LOG!$AJ$4:$AJ$5003))) -> 0 | K18: =IF(A18="","",SETTINGS!$B$6+SUMPRODUCT((TRADE_LOG!$B$4:$B$5003<>"")*N(TRADE_LOG!$B$4:$B$5003<=A18)*N(TRADE_LOG!$AE$4:$AE$5003))) -> 50000 | L18: =IF(A18="","",IF(C18=0,"—",IF(F18>0.05,"✅ WIN DAY",IF(F18<-0.05,"❌ LOSS DAY","🔶 BE DAY")))) -> —
A19: =IFERROR(IF(DAY(DATE($B$4,$D$4,13))=13,DATE($B$4,$D$4,13),""),"") -> 45304 | B19: =IF(A19="","",TEXT(A19,"DDD")) -> Sat | C19: =IF(A19="","",COUNTIF(TRADE_LOG!$B$4:$B$5003,A19)) -> 0 | D19: =IF(A19="","",COUNTIFS(TRADE_LOG!$B$4:$B$5003,A19,TRADE_LOG!$AH$4:$AH$5003,"Win")) -> 0 | E19: =IF(A19="","",COUNTIFS(TRADE_LOG!$B$4:$B$5003,A19,TRADE_LOG!$AH$4:$AH$5003,"Loss")) -> 0 | F19: =IF(A19="","",SUMPRODUCT((TRADE_LOG!$B$4:$B$5003=A19)*N(TRADE_LOG!$AG$4:$AG$5003))) -> 0 | G19: =IF(A19="","",SUMPRODUCT((TRADE_LOG!$B$4:$B$5003=A19)*N(TRADE_LOG!$AE$4:$AE$5003))) -> 0 | H19: =IF(A19="","",IFERROR(maxifs(TRADE_LOG!$AG$4:$AG$5003,TRADE_LOG!$B$4:$B$5003,A19,TRADE_LOG!$AG$4:$AG$5003,"<>"),0)) -> 0 | I19: =IF(A19="","",IFERROR(minifs(TRADE_LOG!$AG$4:$AG$5003,TRADE_LOG!$B$4:$B$5003,A19,TRADE_LOG!$AG$4:$AG$5003,"<>"),0)) -> 0 | J19: =IF(A19="","",SUMPRODUCT((TRADE_LOG!$B$4:$B$5003=A19)*N(TRADE_LOG!$AJ$4:$AJ$5003))) -> 0 | K19: =IF(A19="","",SETTINGS!$B$6+SUMPRODUCT((TRADE_LOG!$B$4:$B$5003<>"")*N(TRADE_LOG!$B$4:$B$5003<=A19)*N(TRADE_LOG!$AE$4:$AE$5003))) -> 50000 | L19: =IF(A19="","",IF(C19=0,"—",IF(F19>0.05,"✅ WIN DAY",IF(F19<-0.05,"❌ LOSS DAY","🔶 BE DAY")))) -> —
A20: =IFERROR(IF(DAY(DATE($B$4,$D$4,14))=14,DATE($B$4,$D$4,14),""),"") -> 45305 | B20: =IF(A20="","",TEXT(A20,"DDD")) -> Sun | C20: =IF(A20="","",COUNTIF(TRADE_LOG!$B$4:$B$5003,A20)) -> 0 | D20: =IF(A20="","",COUNTIFS(TRADE_LOG!$B$4:$B$5003,A20,TRADE_LOG!$AH$4:$AH$5003,"Win")) -> 0 | E20: =IF(A20="","",COUNTIFS(TRADE_LOG!$B$4:$B$5003,A20,TRADE_LOG!$AH$4:$AH$5003,"Loss")) -> 0 | F20: =IF(A20="","",SUMPRODUCT((TRADE_LOG!$B$4:$B$5003=A20)*N(TRADE_LOG!$AG$4:$AG$5003))) -> 0 | G20: =IF(A20="","",SUMPRODUCT((TRADE_LOG!$B$4:$B$5003=A20)*N(TRADE_LOG!$AE$4:$AE$5003))) -> 0 | H20: =IF(A20="","",IFERROR(maxifs(TRADE_LOG!$AG$4:$AG$5003,TRADE_LOG!$B$4:$B$5003,A20,TRADE_LOG!$AG$4:$AG$5003,"<>"),0)) -> 0 | I20: =IF(A20="","",IFERROR(minifs(TRADE_LOG!$AG$4:$AG$5003,TRADE_LOG!$B$4:$B$5003,A20,TRADE_LOG!$AG$4:$AG$5003,"<>"),0)) -> 0 | J20: =IF(A20="","",SUMPRODUCT((TRADE_LOG!$B$4:$B$5003=A20)*N(TRADE_LOG!$AJ$4:$AJ$5003))) -> 0 | K20: =IF(A20="","",SETTINGS!$B$6+SUMPRODUCT((TRADE_LOG!$B$4:$B$5003<>"")*N(TRADE_LOG!$B$4:$B$5003<=A20)*N(TRADE_LOG!$AE$4:$AE$5003))) -> 50000 | L20: =IF(A20="","",IF(C20=0,"—",IF(F20>0.05,"✅ WIN DAY",IF(F20<-0.05,"❌ LOSS DAY","🔶 BE DAY")))) -> —
A21: =IFERROR(IF(DAY(DATE($B$4,$D$4,15))=15,DATE($B$4,$D$4,15),""),"") -> 45306 | B21: =IF(A21="","",TEXT(A21,"DDD")) -> Mon | C21: =IF(A21="","",COUNTIF(TRADE_LOG!$B$4:$B$5003,A21)) -> 1 | D21: =IF(A21="","",COUNTIFS(TRADE_LOG!$B$4:$B$5003,A21,TRADE_LOG!$AH$4:$AH$5003,"Win")) -> 1 | E21: =IF(A21="","",COUNTIFS(TRADE_LOG!$B$4:$B$5003,A21,TRADE_LOG!$AH$4:$AH$5003,"Loss")) -> 0 | F21: =IF(A21="","",SUMPRODUCT((TRADE_LOG!$B$4:$B$5003=A21)*N(TRADE_LOG!$AG$4:$AG$5003))) -> 2.275 | G21: =IF(A21="","",SUMPRODUCT((TRADE_LOG!$B$4:$B$5003=A21)*N(TRADE_LOG!$AE$4:$AE$5003))) -> 1137.5 | H21: =IF(A21="","",IFERROR(maxifs(TRADE_LOG!$AG$4:$AG$5003,TRADE_LOG!$B$4:$B$5003,A21,TRADE_LOG!$AG$4:$AG$5003,"<>"),0)) -> 0 | I21: =IF(A21="","",IFERROR(minifs(TRADE_LOG!$AG$4:$AG$5003,TRADE_LOG!$B$4:$B$5003,A21,TRADE_LOG!$AG$4:$AG$5003,"<>"),0)) -> 0 | J21: =IF(A21="","",SUMPRODUCT((TRADE_LOG!$B$4:$B$5003=A21)*N(TRADE_LOG!$AJ$4:$AJ$5003))) -> 45.5 | K21: =IF(A21="","",SETTINGS!$B$6+SUMPRODUCT((TRADE_LOG!$B$4:$B$5003<>"")*N(TRADE_LOG!$B$4:$B$5003<=A21)*N(TRADE_LOG!$AE$4:$AE$5003))) -> 51137.5 | L21: =IF(A21="","",IF(C21=0,"—",IF(F21>0.05,"✅ WIN DAY",IF(F21<-0.05,"❌ LOSS DAY","🔶 BE DAY")))) -> ✅ WIN DAY
A22: =IFERROR(IF(DAY(DATE($B$4,$D$4,16))=16,DATE($B$4,$D$4,16),""),"") -> 45307 | B22: =IF(A22="","",TEXT(A22,"DDD")) -> Tue | C22: =IF(A22="","",COUNTIF(TRADE_LOG!$B$4:$B$5003,A22)) -> 1 | D22: =IF(A22="","",COUNTIFS(TRADE_LOG!$B$4:$B$5003,A22,TRADE_LOG!$AH$4:$AH$5003,"Win")) -> 1 | E22: =IF(A22="","",COUNTIFS(TRADE_LOG!$B$4:$B$5003,A22,TRADE_LOG!$AH$4:$AH$5003,"Loss")) -> 0 | F22: =IF(A22="","",SUMPRODUCT((TRADE_LOG!$B$4:$B$5003=A22)*N(TRADE_LOG!$AG$4:$AG$5003))) -> 1.8333333 | G22: =IF(A22="","",SUMPRODUCT((TRADE_LOG!$B$4:$B$5003=A22)*N(TRADE_LOG!$AE$4:$AE$5003))) -> 916.66667 | H22: =IF(A22="","",IFERROR(maxifs(TRADE_LOG!$AG$4:$AG$5003,TRADE_LOG!$B$4:$B$5003,A22,TRADE_LOG!$AG$4:$AG$5003,"<>"),0)) -> 0 | I22: =IF(A22="","",IFERROR(minifs(TRADE_LOG!$AG$4:$AG$5003,TRADE_LOG!$B$4:$B$5003,A22,TRADE_LOG!$AG$4:$AG$5003,"<>"),0)) -> 0 | J22: =IF(A22="","",SUMPRODUCT((TRADE_LOG!$B$4:$B$5003=A22)*N(TRADE_LOG!$AJ$4:$AJ$5003))) -> 55 | K22: =IF(A22="","",SETTINGS!$B$6+SUMPRODUCT((TRADE_LOG!$B$4:$B$5003<>"")*N(TRADE_LOG!$B$4:$B$5003<=A22)*N(TRADE_LOG!$AE$4:$AE$5003))) -> 52054.167 | L22: =IF(A22="","",IF(C22=0,"—",IF(F22>0.05,"✅ WIN DAY",IF(F22<-0.05,"❌ LOSS DAY","🔶 BE DAY")))) -> ✅ WIN DAY
A23: =IFERROR(IF(DAY(DATE($B$4,$D$4,17))=17,DATE($B$4,$D$4,17),""),"") -> 45308 | B23: =IF(A23="","",TEXT(A23,"DDD")) -> Wed | C23: =IF(A23="","",COUNTIF(TRADE_LOG!$B$4:$B$5003,A23)) -> 1 | D23: =IF(A23="","",COUNTIFS(TRADE_LOG!$B$4:$B$5003,A23,TRADE_LOG!$AH$4:$AH$5003,"Win")) -> 1 | E23: =IF(A23="","",COUNTIFS(TRADE_LOG!$B$4:$B$5003,A23,TRADE_LOG!$AH$4:$AH$5003,"Loss")) -> 0 | F23: =IF(A23="","",SUMPRODUCT((TRADE_LOG!$B$4:$B$5003=A23)*N(TRADE_LOG!$AG$4:$AG$5003))) -> 2.3933333 | G23: =IF(A23="","",SUMPRODUCT((TRADE_LOG!$B$4:$B$5003=A23)*N(TRADE_LOG!$AE$4:$AE$5003))) -> 1795 | H23: =IF(A23="","",IFERROR(maxifs(TRADE_LOG!$AG$4:$AG$5003,TRADE_LOG!$B$4:$B$5003,A23,TRADE_LOG!$AG$4:$AG$5003,"<>"),0)) -> 0 | I23: =IF(A23="","",IFERROR(minifs(TRADE_LOG!$AG$4:$AG$5003,TRADE_LOG!$B$4:$B$5003,A23,TRADE_LOG!$AG$4:$AG$5003,"<>"),0)) -> 0 | J23: =IF(A23="","",SUMPRODUCT((TRADE_LOG!$B$4:$B$5003=A23)*N(TRADE_LOG!$AJ$4:$AJ$5003))) -> 1795 | K23: =IF(A23="","",SETTINGS!$B$6+SUMPRODUCT((TRADE_LOG!$B$4:$B$5003<>"")*N(TRADE_LOG!$B$4:$B$5003<=A23)*N(TRADE_LOG!$AE$4:$AE$5003))) -> 53849.167 | L23: =IF(A23="","",IF(C23=0,"—",IF(F23>0.05,"✅ WIN DAY",IF(F23<-0.05,"❌ LOSS DAY","🔶 BE DAY")))) -> ✅ WIN DAY
A24: =IFERROR(IF(DAY(DATE($B$4,$D$4,18))=18,DATE($B$4,$D$4,18),""),"") -> 45309 | B24: =IF(A24="","",TEXT(A24,"DDD")) -> Thu | C24: =IF(A24="","",COUNTIF(TRADE_LOG!$B$4:$B$5003,A24)) -> 1 | D24: =IF(A24="","",COUNTIFS(TRADE_LOG!$B$4:$B$5003,A24,TRADE_LOG!$AH$4:$AH$5003,"Win")) -> 1 | E24: =IF(A24="","",COUNTIFS(TRADE_LOG!$B$4:$B$5003,A24,TRADE_LOG!$AH$4:$AH$5003,"Loss")) -> 0 | F24: =IF(A24="","",SUMPRODUCT((TRADE_LOG!$B$4:$B$5003=A24)*N(TRADE_LOG!$AG$4:$AG$5003))) -> 1.2376238 | G24: =IF(A24="","",SUMPRODUCT((TRADE_LOG!$B$4:$B$5003=A24)*N(TRADE_LOG!$AE$4:$AE$5003))) -> 618.81188 | H24: =IF(A24="","",IFERROR(maxifs(TRADE_LOG!$AG$4:$AG$5003,TRADE_LOG!$B$4:$B$5003,A24,TRADE_LOG!$AG$4:$AG$5003,"<>"),0)) -> 0 | I24: =IF(A24="","",IFERROR(minifs(TRADE_LOG!$AG$4:$AG$5003,TRADE_LOG!$B$4:$B$5003,A24,TRADE_LOG!$AG$4:$AG$5003,"<>"),0)) -> 0 | J24: =IF(A24="","",SUMPRODUCT((TRADE_LOG!$B$4:$B$5003=A24)*N(TRADE_LOG!$AJ$4:$AJ$5003))) -> 45 | K24: =IF(A24="","",SETTINGS!$B$6+SUMPRODUCT((TRADE_LOG!$B$4:$B$5003<>"")*N(TRADE_LOG!$B$4:$B$5003<=A24)*N(TRADE_LOG!$AE$4:$AE$5003))) -> 54467.979 | L24: =IF(A24="","",IF(C24=0,"—",IF(F24>0.05,"✅ WIN DAY",IF(F24<-0.05,"❌ LOSS DAY","🔶 BE DAY")))) -> ✅ WIN DAY
A25: =IFERROR(IF(DAY(DATE($B$4,$D$4,19))=19,DATE($B$4,$D$4,19),""),"") -> 45310 | B25: =IF(A25="","",TEXT(A25,"DDD")) -> Fri | C25: =IF(A25="","",COUNTIF(TRADE_LOG!$B$4:$B$5003,A25)) -> 0 | D25: =IF(A25="","",COUNTIFS(TRADE_LOG!$B$4:$B$5003,A25,TRADE_LOG!$AH$4:$AH$5003,"Win")) -> 0 | E25: =IF(A25="","",COUNTIFS(TRADE_LOG!$B$4:$B$5003,A25,TRADE_LOG!$AH$4:$AH$5003,"Loss")) -> 0 | F25: =IF(A25="","",SUMPRODUCT((TRADE_LOG!$B$4:$B$5003=A25)*N(TRADE_LOG!$AG$4:$AG$5003))) -> 0 | G25: =IF(A25="","",SUMPRODUCT((TRADE_LOG!$B$4:$B$5003=A25)*N(TRADE_LOG!$AE$4:$AE$5003))) -> 0 | H25: =IF(A25="","",IFERROR(maxifs(TRADE_LOG!$AG$4:$AG$5003,TRADE_LOG!$B$4:$B$5003,A25,TRADE_LOG!$AG$4:$AG$5003,"<>"),0)) -> 0 | I25: =IF(A25="","",IFERROR(minifs(TRADE_LOG!$AG$4:$AG$5003,TRADE_LOG!$B$4:$B$5003,A25,TRADE_LOG!$AG$4:$AG$5003,"<>"),0)) -> 0 | J25: =IF(A25="","",SUMPRODUCT((TRADE_LOG!$B$4:$B$5003=A25)*N(TRADE_LOG!$AJ$4:$AJ$5003))) -> 0 | K25: =IF(A25="","",SETTINGS!$B$6+SUMPRODUCT((TRADE_LOG!$B$4:$B$5003<>"")*N(TRADE_LOG!$B$4:$B$5003<=A25)*N(TRADE_LOG!$AE$4:$AE$5003))) -> 54467.979 | L25: =IF(A25="","",IF(C25=0,"—",IF(F25>0.05,"✅ WIN DAY",IF(F25<-0.05,"❌ LOSS DAY","🔶 BE DAY")))) -> —
A26: =IFERROR(IF(DAY(DATE($B$4,$D$4,20))=20,DATE($B$4,$D$4,20),""),"") -> 45311 | B26: =IF(A26="","",TEXT(A26,"DDD")) -> Sat | C26: =IF(A26="","",COUNTIF(TRADE_LOG!$B$4:$B$5003,A26)) -> 0 | D26: =IF(A26="","",COUNTIFS(TRADE_LOG!$B$4:$B$5003,A26,TRADE_LOG!$AH$4:$AH$5003,"Win")) -> 0 | E26: =IF(A26="","",COUNTIFS(TRADE_LOG!$B$4:$B$5003,A26,TRADE_LOG!$AH$4:$AH$5003,"Loss")) -> 0 | F26: =IF(A26="","",SUMPRODUCT((TRADE_LOG!$B$4:$B$5003=A26)*N(TRADE_LOG!$AG$4:$AG$5003))) -> 0 | G26: =IF(A26="","",SUMPRODUCT((TRADE_LOG!$B$4:$B$5003=A26)*N(TRADE_LOG!$AE$4:$AE$5003))) -> 0 | H26: =IF(A26="","",IFERROR(maxifs(TRADE_LOG!$AG$4:$AG$5003,TRADE_LOG!$B$4:$B$5003,A26,TRADE_LOG!$AG$4:$AG$5003,"<>"),0)) -> 0 | I26: =IF(A26="","",IFERROR(minifs(TRADE_LOG!$AG$4:$AG$5003,TRADE_LOG!$B$4:$B$5003,A26,TRADE_LOG!$AG$4:$AG$5003,"<>"),0)) -> 0 | J26: =IF(A26="","",SUMPRODUCT((TRADE_LOG!$B$4:$B$5003=A26)*N(TRADE_LOG!$AJ$4:$AJ$5003))) -> 0 | K26: =IF(A26="","",SETTINGS!$B$6+SUMPRODUCT((TRADE_LOG!$B$4:$B$5003<>"")*N(TRADE_LOG!$B$4:$B$5003<=A26)*N(TRADE_LOG!$AE$4:$AE$5003))) -> 54467.979 | L26: =IF(A26="","",IF(C26=0,"—",IF(F26>0.05,"✅ WIN DAY",IF(F26<-0.05,"❌ LOSS DAY","🔶 BE DAY")))) -> —
A27: =IFERROR(IF(DAY(DATE($B$4,$D$4,21))=21,DATE($B$4,$D$4,21),""),"") -> 45312 | B27: =IF(A27="","",TEXT(A27,"DDD")) -> Sun | C27: =IF(A27="","",COUNTIF(TRADE_LOG!$B$4:$B$5003,A27)) -> 0 | D27: =IF(A27="","",COUNTIFS(TRADE_LOG!$B$4:$B$5003,A27,TRADE_LOG!$AH$4:$AH$5003,"Win")) -> 0 | E27: =IF(A27="","",COUNTIFS(TRADE_LOG!$B$4:$B$5003,A27,TRADE_LOG!$AH$4:$AH$5003,"Loss")) -> 0 | F27: =IF(A27="","",SUMPRODUCT((TRADE_LOG!$B$4:$B$5003=A27)*N(TRADE_LOG!$AG$4:$AG$5003))) -> 0 | G27: =IF(A27="","",SUMPRODUCT((TRADE_LOG!$B$4:$B$5003=A27)*N(TRADE_LOG!$AE$4:$AE$5003))) -> 0 | H27: =IF(A27="","",IFERROR(maxifs(TRADE_LOG!$AG$4:$AG$5003,TRADE_LOG!$B$4:$B$5003,A27,TRADE_LOG!$AG$4:$AG$5003,"<>"),0)) -> 0 | I27: =IF(A27="","",IFERROR(minifs(TRADE_LOG!$AG$4:$AG$5003,TRADE_LOG!$B$4:$B$5003,A27,TRADE_LOG!$AG$4:$AG$5003,"<>"),0)) -> 0 | J27: =IF(A27="","",SUMPRODUCT((TRADE_LOG!$B$4:$B$5003=A27)*N(TRADE_LOG!$AJ$4:$AJ$5003))) -> 0 | K27: =IF(A27="","",SETTINGS!$B$6+SUMPRODUCT((TRADE_LOG!$B$4:$B$5003<>"")*N(TRADE_LOG!$B$4:$B$5003<=A27)*N(TRADE_LOG!$AE$4:$AE$5003))) -> 54467.979 | L27: =IF(A27="","",IF(C27=0,"—",IF(F27>0.05,"✅ WIN DAY",IF(F27<-0.05,"❌ LOSS DAY","🔶 BE DAY")))) -> —
A28: =IFERROR(IF(DAY(DATE($B$4,$D$4,22))=22,DATE($B$4,$D$4,22),""),"") -> 45313 | B28: =IF(A28="","",TEXT(A28,"DDD")) -> Mon | C28: =IF(A28="","",COUNTIF(TRADE_LOG!$B$4:$B$5003,A28)) -> 1 | D28: =IF(A28="","",COUNTIFS(TRADE_LOG!$B$4:$B$5003,A28,TRADE_LOG!$AH$4:$AH$5003,"Win")) -> 1 | E28: =IF(A28="","",COUNTIFS(TRADE_LOG!$B$4:$B$5003,A28,TRADE_LOG!$AH$4:$AH$5003,"Loss")) -> 0 | F28: =IF(A28="","",SUMPRODUCT((TRADE_LOG!$B$4:$B$5003=A28)*N(TRADE_LOG!$AG$4:$AG$5003))) -> 1.5 | G28: =IF(A28="","",SUMPRODUCT((TRADE_LOG!$B$4:$B$5003=A28)*N(TRADE_LOG!$AE$4:$AE$5003))) -> 750 | H28: =IF(A28="","",IFERROR(maxifs(TRADE_LOG!$AG$4:$AG$5003,TRADE_LOG!$B$4:$B$5003,A28,TRADE_LOG!$AG$4:$AG$5003,"<>"),0)) -> 0 | I28: =IF(A28="","",IFERROR(minifs(TRADE_LOG!$AG$4:$AG$5003,TRADE_LOG!$B$4:$B$5003,A28,TRADE_LOG!$AG$4:$AG$5003,"<>"),0)) -> 0 | J28: =IF(A28="","",SUMPRODUCT((TRADE_LOG!$B$4:$B$5003=A28)*N(TRADE_LOG!$AJ$4:$AJ$5003))) -> 30 | K28: =IF(A28="","",SETTINGS!$B$6+SUMPRODUCT((TRADE_LOG!$B$4:$B$5003<>"")*N(TRADE_LOG!$B$4:$B$5003<=A28)*N(TRADE_LOG!$AE$4:$AE$5003))) -> 55217.979 | L28: =IF(A28="","",IF(C28=0,"—",IF(F28>0.05,"✅ WIN DAY",IF(F28<-0.05,"❌ LOSS DAY","🔶 BE DAY")))) -> ✅ WIN DAY
A29: =IFERROR(IF(DAY(DATE($B$4,$D$4,23))=23,DATE($B$4,$D$4,23),""),"") -> 45314 | B29: =IF(A29="","",TEXT(A29,"DDD")) -> Tue | C29: =IF(A29="","",COUNTIF(TRADE_LOG!$B$4:$B$5003,A29)) -> 0 | D29: =IF(A29="","",COUNTIFS(TRADE_LOG!$B$4:$B$5003,A29,TRADE_LOG!$AH$4:$AH$5003,"Win")) -> 0 | E29: =IF(A29="","",COUNTIFS(TRADE_LOG!$B$4:$B$5003,A29,TRADE_LOG!$AH$4:$AH$5003,"Loss")) -> 0 | F29: =IF(A29="","",SUMPRODUCT((TRADE_LOG!$B$4:$B$5003=A29)*N(TRADE_LOG!$AG$4:$AG$5003))) -> 0 | G29: =IF(A29="","",SUMPRODUCT((TRADE_LOG!$B$4:$B$5003=A29)*N(TRADE_LOG!$AE$4:$AE$5003))) -> 0 | H29: =IF(A29="","",IFERROR(maxifs(TRADE_LOG!$AG$4:$AG$5003,TRADE_LOG!$B$4:$B$5003,A29,TRADE_LOG!$AG$4:$AG$5003,"<>"),0)) -> 0 | I29: =IF(A29="","",IFERROR(minifs(TRADE_LOG!$AG$4:$AG$5003,TRADE_LOG!$B$4:$B$5003,A29,TRADE_LOG!$AG$4:$AG$5003,"<>"),0)) -> 0 | J29: =IF(A29="","",SUMPRODUCT((TRADE_LOG!$B$4:$B$5003=A29)*N(TRADE_LOG!$AJ$4:$AJ$5003))) -> 0 | K29: =IF(A29="","",SETTINGS!$B$6+SUMPRODUCT((TRADE_LOG!$B$4:$B$5003<>"")*N(TRADE_LOG!$B$4:$B$5003<=A29)*N(TRADE_LOG!$AE$4:$AE$5003))) -> 55217.979 | L29: =IF(A29="","",IF(C29=0,"—",IF(F29>0.05,"✅ WIN DAY",IF(F29<-0.05,"❌ LOSS DAY","🔶 BE DAY")))) -> —
A30: =IFERROR(IF(DAY(DATE($B$4,$D$4,24))=24,DATE($B$4,$D$4,24),""),"") -> 45315 | B30: =IF(A30="","",TEXT(A30,"DDD")) -> Wed | C30: =IF(A30="","",COUNTIF(TRADE_LOG!$B$4:$B$5003,A30)) -> 0 | D30: =IF(A30="","",COUNTIFS(TRADE_LOG!$B$4:$B$5003,A30,TRADE_LOG!$AH$4:$AH$5003,"Win")) -> 0 | E30: =IF(A30="","",COUNTIFS(TRADE_LOG!$B$4:$B$5003,A30,TRADE_LOG!$AH$4:$AH$5003,"Loss")) -> 0 | F30: =IF(A30="","",SUMPRODUCT((TRADE_LOG!$B$4:$B$5003=A30)*N(TRADE_LOG!$AG$4:$AG$5003))) -> 0 | G30: =IF(A30="","",SUMPRODUCT((TRADE_LOG!$B$4:$B$5003=A30)*N(TRADE_LOG!$AE$4:$AE$5003))) -> 0 | H30: =IF(A30="","",IFERROR(maxifs(TRADE_LOG!$AG$4:$AG$5003,TRADE_LOG!$B$4:$B$5003,A30,TRADE_LOG!$AG$4:$AG$5003,"<>"),0)) -> 0 | I30: =IF(A30="","",IFERROR(minifs(TRADE_LOG!$AG$4:$AG$5003,TRADE_LOG!$B$4:$B$5003,A30,TRADE_LOG!$AG$4:$AG$5003,"<>"),0)) -> 0 | J30: =IF(A30="","",SUMPRODUCT((TRADE_LOG!$B$4:$B$5003=A30)*N(TRADE_LOG!$AJ$4:$AJ$5003))) -> 0 | K30: =IF(A30="","",SETTINGS!$B$6+SUMPRODUCT((TRADE_LOG!$B$4:$B$5003<>"")*N(TRADE_LOG!$B$4:$B$5003<=A30)*N(TRADE_LOG!$AE$4:$AE$5003))) -> 55217.979 | L30: =IF(A30="","",IF(C30=0,"—",IF(F30>0.05,"✅ WIN DAY",IF(F30<-0.05,"❌ LOSS DAY","🔶 BE DAY")))) -> —
A31: =IFERROR(IF(DAY(DATE($B$4,$D$4,25))=25,DATE($B$4,$D$4,25),""),"") -> 45316 | B31: =IF(A31="","",TEXT(A31,"DDD")) -> Thu | C31: =IF(A31="","",COUNTIF(TRADE_LOG!$B$4:$B$5003,A31)) -> 0 | D31: =IF(A31="","",COUNTIFS(TRADE_LOG!$B$4:$B$5003,A31,TRADE_LOG!$AH$4:$AH$5003,"Win")) -> 0 | E31: =IF(A31="","",COUNTIFS(TRADE_LOG!$B$4:$B$5003,A31,TRADE_LOG!$AH$4:$AH$5003,"Loss")) -> 0 | F31: =IF(A31="","",SUMPRODUCT((TRADE_LOG!$B$4:$B$5003=A31)*N(TRADE_LOG!$AG$4:$AG$5003))) -> 0 | G31: =IF(A31="","",SUMPRODUCT((TRADE_LOG!$B$4:$B$5003=A31)*N(TRADE_LOG!$AE$4:$AE$5003))) -> 0 | H31: =IF(A31="","",IFERROR(maxifs(TRADE_LOG!$AG$4:$AG$5003,TRADE_LOG!$B$4:$B$5003,A31,TRADE_LOG!$AG$4:$AG$5003,"<>"),0)) -> 0 | I31: =IF(A31="","",IFERROR(minifs(TRADE_LOG!$AG$4:$AG$5003,TRADE_LOG!$B$4:$B$5003,A31,TRADE_LOG!$AG$4:$AG$5003,"<>"),0)) -> 0 | J31: =IF(A31="","",SUMPRODUCT((TRADE_LOG!$B$4:$B$5003=A31)*N(TRADE_LOG!$AJ$4:$AJ$5003))) -> 0 | K31: =IF(A31="","",SETTINGS!$B$6+SUMPRODUCT((TRADE_LOG!$B$4:$B$5003<>"")*N(TRADE_LOG!$B$4:$B$5003<=A31)*N(TRADE_LOG!$AE$4:$AE$5003))) -> 55217.979 | L31: =IF(A31="","",IF(C31=0,"—",IF(F31>0.05,"✅ WIN DAY",IF(F31<-0.05,"❌ LOSS DAY","🔶 BE DAY")))) -> —
A32: =IFERROR(IF(DAY(DATE($B$4,$D$4,26))=26,DATE($B$4,$D$4,26),""),"") -> 45317 | B32: =IF(A32="","",TEXT(A32,"DDD")) -> Fri | C32: =IF(A32="","",COUNTIF(TRADE_LOG!$B$4:$B$5003,A32)) -> 0 | D32: =IF(A32="","",COUNTIFS(TRADE_LOG!$B$4:$B$5003,A32,TRADE_LOG!$AH$4:$AH$5003,"Win")) -> 0 | E32: =IF(A32="","",COUNTIFS(TRADE_LOG!$B$4:$B$5003,A32,TRADE_LOG!$AH$4:$AH$5003,"Loss")) -> 0 | F32: =IF(A32="","",SUMPRODUCT((TRADE_LOG!$B$4:$B$5003=A32)*N(TRADE_LOG!$AG$4:$AG$5003))) -> 0 | G32: =IF(A32="","",SUMPRODUCT((TRADE_LOG!$B$4:$B$5003=A32)*N(TRADE_LOG!$AE$4:$AE$5003))) -> 0 | H32: =IF(A32="","",IFERROR(maxifs(TRADE_LOG!$AG$4:$AG$5003,TRADE_LOG!$B$4:$B$5003,A32,TRADE_LOG!$AG$4:$AG$5003,"<>"),0)) -> 0 | I32: =IF(A32="","",IFERROR(minifs(TRADE_LOG!$AG$4:$AG$5003,TRADE_LOG!$B$4:$B$5003,A32,TRADE_LOG!$AG$4:$AG$5003,"<>"),0)) -> 0 | J32: =IF(A32="","",SUMPRODUCT((TRADE_LOG!$B$4:$B$5003=A32)*N(TRADE_LOG!$AJ$4:$AJ$5003))) -> 0 | K32: =IF(A32="","",SETTINGS!$B$6+SUMPRODUCT((TRADE_LOG!$B$4:$B$5003<>"")*N(TRADE_LOG!$B$4:$B$5003<=A32)*N(TRADE_LOG!$AE$4:$AE$5003))) -> 55217.979 | L32: =IF(A32="","",IF(C32=0,"—",IF(F32>0.05,"✅ WIN DAY",IF(F32<-0.05,"❌ LOSS DAY","🔶 BE DAY")))) -> —
A33: =IFERROR(IF(DAY(DATE($B$4,$D$4,27))=27,DATE($B$4,$D$4,27),""),"") -> 45318 | B33: =IF(A33="","",TEXT(A33,"DDD")) -> Sat | C33: =IF(A33="","",COUNTIF(TRADE_LOG!$B$4:$B$5003,A33)) -> 0 | D33: =IF(A33="","",COUNTIFS(TRADE_LOG!$B$4:$B$5003,A33,TRADE_LOG!$AH$4:$AH$5003,"Win")) -> 0 | E33: =IF(A33="","",COUNTIFS(TRADE_LOG!$B$4:$B$5003,A33,TRADE_LOG!$AH$4:$AH$5003,"Loss")) -> 0 | F33: =IF(A33="","",SUMPRODUCT((TRADE_LOG!$B$4:$B$5003=A33)*N(TRADE_LOG!$AG$4:$AG$5003))) -> 0 | G33: =IF(A33="","",SUMPRODUCT((TRADE_LOG!$B$4:$B$5003=A33)*N(TRADE_LOG!$AE$4:$AE$5003))) -> 0 | H33: =IF(A33="","",IFERROR(maxifs(TRADE_LOG!$AG$4:$AG$5003,TRADE_LOG!$B$4:$B$5003,A33,TRADE_LOG!$AG$4:$AG$5003,"<>"),0)) -> 0 | I33: =IF(A33="","",IFERROR(minifs(TRADE_LOG!$AG$4:$AG$5003,TRADE_LOG!$B$4:$B$5003,A33,TRADE_LOG!$AG$4:$AG$5003,"<>"),0)) -> 0 | J33: =IF(A33="","",SUMPRODUCT((TRADE_LOG!$B$4:$B$5003=A33)*N(TRADE_LOG!$AJ$4:$AJ$5003))) -> 0 | K33: =IF(A33="","",SETTINGS!$B$6+SUMPRODUCT((TRADE_LOG!$B$4:$B$5003<>"")*N(TRADE_LOG!$B$4:$B$5003<=A33)*N(TRADE_LOG!$AE$4:$AE$5003))) -> 55217.979 | L33: =IF(A33="","",IF(C33=0,"—",IF(F33>0.05,"✅ WIN DAY",IF(F33<-0.05,"❌ LOSS DAY","🔶 BE DAY")))) -> —
A34: =IFERROR(IF(DAY(DATE($B$4,$D$4,28))=28,DATE($B$4,$D$4,28),""),"") -> 45319 | B34: =IF(A34="","",TEXT(A34,"DDD")) -> Sun | C34: =IF(A34="","",COUNTIF(TRADE_LOG!$B$4:$B$5003,A34)) -> 0 | D34: =IF(A34="","",COUNTIFS(TRADE_LOG!$B$4:$B$5003,A34,TRADE_LOG!$AH$4:$AH$5003,"Win")) -> 0 | E34: =IF(A34="","",COUNTIFS(TRADE_LOG!$B$4:$B$5003,A34,TRADE_LOG!$AH$4:$AH$5003,"Loss")) -> 0 | F34: =IF(A34="","",SUMPRODUCT((TRADE_LOG!$B$4:$B$5003=A34)*N(TRADE_LOG!$AG$4:$AG$5003))) -> 0 | G34: =IF(A34="","",SUMPRODUCT((TRADE_LOG!$B$4:$B$5003=A34)*N(TRADE_LOG!$AE$4:$AE$5003))) -> 0 | H34: =IF(A34="","",IFERROR(maxifs(TRADE_LOG!$AG$4:$AG$5003,TRADE_LOG!$B$4:$B$5003,A34,TRADE_LOG!$AG$4:$AG$5003,"<>"),0)) -> 0 | I34: =IF(A34="","",IFERROR(minifs(TRADE_LOG!$AG$4:$AG$5003,TRADE_LOG!$B$4:$B$5003,A34,TRADE_LOG!$AG$4:$AG$5003,"<>"),0)) -> 0 | J34: =IF(A34="","",SUMPRODUCT((TRADE_LOG!$B$4:$B$5003=A34)*N(TRADE_LOG!$AJ$4:$AJ$5003))) -> 0 | K34: =IF(A34="","",SETTINGS!$B$6+SUMPRODUCT((TRADE_LOG!$B$4:$B$5003<>"")*N(TRADE_LOG!$B$4:$B$5003<=A34)*N(TRADE_LOG!$AE$4:$AE$5003))) -> 55217.979 | L34: =IF(A34="","",IF(C34=0,"—",IF(F34>0.05,"✅ WIN DAY",IF(F34<-0.05,"❌ LOSS DAY","🔶 BE DAY")))) -> —
A35: =IFERROR(IF(DAY(DATE($B$4,$D$4,29))=29,DATE($B$4,$D$4,29),""),"") -> 45320 | B35: =IF(A35="","",TEXT(A35,"DDD")) -> Mon | C35: =IF(A35="","",COUNTIF(TRADE_LOG!$B$4:$B$5003,A35)) -> 0 | D35: =IF(A35="","",COUNTIFS(TRADE_LOG!$B$4:$B$5003,A35,TRADE_LOG!$AH$4:$AH$5003,"Win")) -> 0 | E35: =IF(A35="","",COUNTIFS(TRADE_LOG!$B$4:$B$5003,A35,TRADE_LOG!$AH$4:$AH$5003,"Loss")) -> 0 | F35: =IF(A35="","",SUMPRODUCT((TRADE_LOG!$B$4:$B$5003=A35)*N(TRADE_LOG!$AG$4:$AG$5003))) -> 0 | G35: =IF(A35="","",SUMPRODUCT((TRADE_LOG!$B$4:$B$5003=A35)*N(TRADE_LOG!$AE$4:$AE$5003))) -> 0 | H35: =IF(A35="","",IFERROR(maxifs(TRADE_LOG!$AG$4:$AG$5003,TRADE_LOG!$B$4:$B$5003,A35,TRADE_LOG!$AG$4:$AG$5003,"<>"),0)) -> 0 | I35: =IF(A35="","",IFERROR(minifs(TRADE_LOG!$AG$4:$AG$5003,TRADE_LOG!$B$4:$B$5003,A35,TRADE_LOG!$AG$4:$AG$5003,"<>"),0)) -> 0 | J35: =IF(A35="","",SUMPRODUCT((TRADE_LOG!$B$4:$B$5003=A35)*N(TRADE_LOG!$AJ$4:$AJ$5003))) -> 0 | K35: =IF(A35="","",SETTINGS!$B$6+SUMPRODUCT((TRADE_LOG!$B$4:$B$5003<>"")*N(TRADE_LOG!$B$4:$B$5003<=A35)*N(TRADE_LOG!$AE$4:$AE$5003))) -> 55217.979 | L35: =IF(A35="","",IF(C35=0,"—",IF(F35>0.05,"✅ WIN DAY",IF(F35<-0.05,"❌ LOSS DAY","🔶 BE DAY")))) -> —
A36: =IFERROR(IF(DAY(DATE($B$4,$D$4,30))=30,DATE($B$4,$D$4,30),""),"") -> 45321 | B36: =IF(A36="","",TEXT(A36,"DDD")) -> Tue | C36: =IF(A36="","",COUNTIF(TRADE_LOG!$B$4:$B$5003,A36)) -> 0 | D36: =IF(A36="","",COUNTIFS(TRADE_LOG!$B$4:$B$5003,A36,TRADE_LOG!$AH$4:$AH$5003,"Win")) -> 0 | E36: =IF(A36="","",COUNTIFS(TRADE_LOG!$B$4:$B$5003,A36,TRADE_LOG!$AH$4:$AH$5003,"Loss")) -> 0 | F36: =IF(A36="","",SUMPRODUCT((TRADE_LOG!$B$4:$B$5003=A36)*N(TRADE_LOG!$AG$4:$AG$5003))) -> 0 | G36: =IF(A36="","",SUMPRODUCT((TRADE_LOG!$B$4:$B$5003=A36)*N(TRADE_LOG!$AE$4:$AE$5003))) -> 0 | H36: =IF(A36="","",IFERROR(maxifs(TRADE_LOG!$AG$4:$AG$5003,TRADE_LOG!$B$4:$B$5003,A36,TRADE_LOG!$AG$4:$AG$5003,"<>"),0)) -> 0 | I36: =IF(A36="","",IFERROR(minifs(TRADE_LOG!$AG$4:$AG$5003,TRADE_LOG!$B$4:$B$5003,A36,TRADE_LOG!$AG$4:$AG$5003,"<>"),0)) -> 0 | J36: =IF(A36="","",SUMPRODUCT((TRADE_LOG!$B$4:$B$5003=A36)*N(TRADE_LOG!$AJ$4:$AJ$5003))) -> 0 | K36: =IF(A36="","",SETTINGS!$B$6+SUMPRODUCT((TRADE_LOG!$B$4:$B$5003<>"")*N(TRADE_LOG!$B$4:$B$5003<=A36)*N(TRADE_LOG!$AE$4:$AE$5003))) -> 55217.979 | L36: =IF(A36="","",IF(C36=0,"—",IF(F36>0.05,"✅ WIN DAY",IF(F36<-0.05,"❌ LOSS DAY","🔶 BE DAY")))) -> —
A37: =IFERROR(IF(DAY(DATE($B$4,$D$4,31))=31,DATE($B$4,$D$4,31),""),"") -> 45322 | B37: =IF(A37="","",TEXT(A37,"DDD")) -> Wed | C37: =IF(A37="","",COUNTIF(TRADE_LOG!$B$4:$B$5003,A37)) -> 0 | D37: =IF(A37="","",COUNTIFS(TRADE_LOG!$B$4:$B$5003,A37,TRADE_LOG!$AH$4:$AH$5003,"Win")) -> 0 | E37: =IF(A37="","",COUNTIFS(TRADE_LOG!$B$4:$B$5003,A37,TRADE_LOG!$AH$4:$AH$5003,"Loss")) -> 0 | F37: =IF(A37="","",SUMPRODUCT((TRADE_LOG!$B$4:$B$5003=A37)*N(TRADE_LOG!$AG$4:$AG$5003))) -> 0 | G37: =IF(A37="","",SUMPRODUCT((TRADE_LOG!$B$4:$B$5003=A37)*N(TRADE_LOG!$AE$4:$AE$5003))) -> 0 | H37: =IF(A37="","",IFERROR(maxifs(TRADE_LOG!$AG$4:$AG$5003,TRADE_LOG!$B$4:$B$5003,A37,TRADE_LOG!$AG$4:$AG$5003,"<>"),0)) -> 0 | I37: =IF(A37="","",IFERROR(minifs(TRADE_LOG!$AG$4:$AG$5003,TRADE_LOG!$B$4:$B$5003,A37,TRADE_LOG!$AG$4:$AG$5003,"<>"),0)) -> 0 | J37: =IF(A37="","",SUMPRODUCT((TRADE_LOG!$B$4:$B$5003=A37)*N(TRADE_LOG!$AJ$4:$AJ$5003))) -> 0 | K37: =IF(A37="","",SETTINGS!$B$6+SUMPRODUCT((TRADE_LOG!$B$4:$B$5003<>"")*N(TRADE_LOG!$B$4:$B$5003<=A37)*N(TRADE_LOG!$AE$4:$AE$5003))) -> 55217.979 | L37: =IF(A37="","",IF(C37=0,"—",IF(F37>0.05,"✅ WIN DAY",IF(F37<-0.05,"❌ LOSS DAY","🔶 BE DAY")))) -> —

Sheet DASHBOARD
A1: ⚡ TRADING DASHBOARD — Live Performance Overview
B2: Total Trades | D2: Total P/L | F2: Win Rate | H2: Avg R-Multiple | J2: Best Trade R | L2: Worst Trade R | N2: Current Balance | P2: Profit Factor
B3: =COUNTA(TRADE_LOG!H4:H5003) -> 5 | D3: =SUM(TRADE_LOG!AE4:AE5003) -> 5217.9785 | F3: =IFERROR(COUNTIF(TRADE_LOG!AH4:AH5003,"Win")/COUNTA(TRADE_LOG!AH4:AH5003),0) -> 0.01 | H3: =IFERROR(AVERAGE(TRADE_LOG!AG4:AG5003),0) -> 1.8478581 | J3: =IFERROR(MAX(TRADE_LOG!AG4:AG5003),0) -> 2.3933333 | L3: =IFERROR(MIN(TRADE_LOG!AG4:AG5003),0) -> 1.2376238 | N3: =SETTINGS!B6+SUM(TRADE_LOG!AE4:AE5003) -> 55217.979 | P3: =IFERROR(SUMIF(TRADE_LOG!AE4:AE5003,">"&0)/ABS(SUMIF(TRADE_LOG!AE4:AE5003,"<"&0)),0) -> 0
B4: Open Trades | D4: Expectancy | F4: Max Consec Wins | H4: Total Risk Used | J4: Avg Trade Duration | L4: Return on Acct | N4: Loss Rate | P4: Total Lots Traded
B5: =COUNTIF(TRADE_LOG!AH4:AH5003,"Open") -> 495 | D5: =IFERROR((COUNTIF(TRADE_LOG!AH4:AH5003,"Win")/COUNTA(TRADE_LOG!AH4:AH5003))*AVERAGEIFS(TRADE_LOG!AG4:AG5003,TRADE_LOG!AH4:AH5003,"Win")+(COUNTIF(TRADE_LOG!AH4:AH5003,"Loss")/COUNTA(TRADE_LOG!AH4:AH5003))*AVERAGEIFS(TRADE_LOG!AG4:AG5003,TRADE_LOG!AH4:AH5003,"Loss"),0) -> 0 | F5: =IFERROR(MAX(FREQUENCY(IF(TRADE_LOG!AH4:AH103="Win",ROW(TRADE_LOG!AH4:AH103)),IF(TRADE_LOG!AH4:AH103<>"Win",ROW(TRADE_LOG!AH4:AH103)))),0) -> 5 | H5: =IFERROR(SUMPRODUCT(IFERROR(TRADE_LOG!Q4:Q5003,0)),0) -> 2750 | J5: =IFERROR(AVERAGE(TRADE_LOG!AI4:AI5003),"N/A") -> 0.2 | L5: =IFERROR((D3-SETTINGS!B6)/SETTINGS!B6,0) -> -0.89564043 | N5: =IFERROR(COUNTIF(TRADE_LOG!AH4:AH5003,"Loss")/COUNTA(TRADE_LOG!AH4:AH5003),0) -> 0 | P5: =IFERROR(SUM(TRADE_LOG!R4:R5003),0) -> 9.0418042
A7: MONTHLY RETURNS
A8: Year | B8: Jan | C8: Feb | D8: Mar | E8: Apr | F8: May | G8: Jun | H8: Jul | I8: Aug | J8: Sep | K8: Oct | L8: Nov | M8: Dec | N8: Annual Total
A9: 2024 | B9: =IFERROR(SUMPRODUCT((YEAR(TRADE_LOG!$B$4:$B$5003)=2024)*(MONTH(TRADE_LOG!$B$4:$B$5003)=1)*IFERROR(TRADE_LOG!$AE$4:$AE$5003,0)),0) -> 0 | C9: =IFERROR(SUMPRODUCT((YEAR(TRADE_LOG!$B$4:$B$5003)=2024)*(MONTH(TRADE_LOG!$B$4:$B$5003)=2)*IFERROR(TRADE_LOG!$AE$4:$AE$5003,0)),0) -> 0 | D9: =IFERROR(SUMPRODUCT((YEAR(TRADE_LOG!$B$4:$B$5003)=2024)*(MONTH(TRADE_LOG!$B$4:$B$5003)=3)*IFERROR(TRADE_LOG!$AE$4:$AE$5003,0)),0) -> 0 | E9: =IFERROR(SUMPRODUCT((YEAR(TRADE_LOG!$B$4:$B$5003)=2024)*(MONTH(TRADE_LOG!$B$4:$B$5003)=4)*IFERROR(TRADE_LOG!$AE$4:$AE$5003,0)),0) -> 0 | F9: =IFERROR(SUMPRODUCT((YEAR(TRADE_LOG!$B$4:$B$5003)=2024)*(MONTH(TRADE_LOG!$B$4:$B$5003)=5)*IFERROR(TRADE_LOG!$AE$4:$AE$5003,0)),0) -> 0 | G9: =IFERROR(SUMPRODUCT((YEAR(TRADE_LOG!$B$4:$B$5003)=2024)*(MONTH(TRADE_LOG!$B$4:$B$5003)=6)*IFERROR(TRADE_LOG!$AE$4:$AE$5003,0)),0) -> 0 | H9: =IFERROR(SUMPRODUCT((YEAR(TRADE_LOG!$B$4:$B$5003)=2024)*(MONTH(TRADE_LOG!$B$4:$B$5003)=7)*IFERROR(TRADE_LOG!$AE$4:$AE$5003,0)),0) -> 0 | I9: =IFERROR(SUMPRODUCT((YEAR(TRADE_LOG!$B$4:$B$5003)=2024)*(MONTH(TRADE_LOG!$B$4:$B$5003)=8)*IFERROR(TRADE_LOG!$AE$4:$AE$5003,0)),0) -> 0 | J9: =IFERROR(SUMPRODUCT((YEAR(TRADE_LOG!$B$4:$B$5003)=2024)*(MONTH(TRADE_LOG!$B$4:$B$5003)=9)*IFERROR(TRADE_LOG!$AE$4:$AE$5003,0)),0) -> 0 | K9: =IFERROR(SUMPRODUCT((YEAR(TRADE_LOG!$B$4:$B$5003)=2024)*(MONTH(TRADE_LOG!$B$4:$B$5003)=10)*IFERROR(TRADE_LOG!$AE$4:$AE$5003,0)),0) -> 0 | L9: =IFERROR(SUMPRODUCT((YEAR(TRADE_LOG!$B$4:$B$5003)=2024)*(MONTH(TRADE_LOG!$B$4:$B$5003)=11)*IFERROR(TRADE_LOG!$AE$4:$AE$5003,0)),0) -> 0 | M9: =IFERROR(SUMPRODUCT((YEAR(TRADE_LOG!$B$4:$B$5003)=2024)*(MONTH(TRADE_LOG!$B$4:$B$5003)=12)*IFERROR(TRADE_LOG!$AE$4:$AE$5003,0)),0) -> 0 | N9: =SUM(B9:M9) -> 0
A10: 2025 | B10: =IFERROR(SUMPRODUCT((YEAR(TRADE_LOG!$B$4:$B$5003)=2025)*(MONTH(TRADE_LOG!$B$4:$B$5003)=1)*IFERROR(TRADE_LOG!$AE$4:$AE$5003,0)),0) -> 0 | C10: =IFERROR(SUMPRODUCT((YEAR(TRADE_LOG!$B$4:$B$5003)=2025)*(MONTH(TRADE_LOG!$B$4:$B$5003)=2)*IFERROR(TRADE_LOG!$AE$4:$AE$5003,0)),0) -> 0 | D10: =IFERROR(SUMPRODUCT((YEAR(TRADE_LOG!$B$4:$B$5003)=2025)*(MONTH(TRADE_LOG!$B$4:$B$5003)=3)*IFERROR(TRADE_LOG!$AE$4:$AE$5003,0)),0) -> 0 | E10: =IFERROR(SUMPRODUCT((YEAR(TRADE_LOG!$B$4:$B$5003)=2025)*(MONTH(TRADE_LOG!$B$4:$B$5003)=4)*IFERROR(TRADE_LOG!$AE$4:$AE$5003,0)),0) -> 0 | F10: =IFERROR(SUMPRODUCT((YEAR(TRADE_LOG!$B$4:$B$5003)=2025)*(MONTH(TRADE_LOG!$B$4:$B$5003)=5)*IFERROR(TRADE_LOG!$AE$4:$AE$5003,0)),0) -> 0 | G10: =IFERROR(SUMPRODUCT((YEAR(TRADE_LOG!$B$4:$B$5003)=2025)*(MONTH(TRADE_LOG!$B$4:$B$5003)=6)*IFERROR(TRADE_LOG!$AE$4:$AE$5003,0)),0) -> 0 | H10: =IFERROR(SUMPRODUCT((YEAR(TRADE_LOG!$B$4:$B$5003)=2025)*(MONTH(TRADE_LOG!$B$4:$B$5003)=7)*IFERROR(TRADE_LOG!$AE$4:$AE$5003,0)),0) -> 0 | I10: =IFERROR(SUMPRODUCT((YEAR(TRADE_LOG!$B$4:$B$5003)=2025)*(MONTH(TRADE_LOG!$B$4:$B$5003)=8)*IFERROR(TRADE_LOG!$AE$4:$AE$5003,0)),0) -> 0 | J10: =IFERROR(SUMPRODUCT((YEAR(TRADE_LOG!$B$4:$B$5003)=2025)*(MONTH(TRADE_LOG!$B$4:$B$5003)=9)*IFERROR(TRADE_LOG!$AE$4:$AE$5003,0)),0) -> 0 | K10: =IFERROR(SUMPRODUCT((YEAR(TRADE_LOG!$B$4:$B$5003)=2025)*(MONTH(TRADE_LOG!$B$4:$B$5003)=10)*IFERROR(TRADE_LOG!$AE$4:$AE$5003,0)),0) -> 0 | L10: =IFERROR(SUMPRODUCT((YEAR(TRADE_LOG!$B$4:$B$5003)=2025)*(MONTH(TRADE_LOG!$B$4:$B$5003)=11)*IFERROR(TRADE_LOG!$AE$4:$AE$5003,0)),0) -> 0 | M10: =IFERROR(SUMPRODUCT((YEAR(TRADE_LOG!$B$4:$B$5003)=2025)*(MONTH(TRADE_LOG!$B$4:$B$5003)=12)*IFERROR(TRADE_LOG!$AE$4:$AE$5003,0)),0) -> 0 | N10: =SUM(B10:M10) -> 0
A11: 2026 | B11: =IFERROR(SUMPRODUCT((YEAR(TRADE_LOG!$B$4:$B$5003)=2026)*(MONTH(TRADE_LOG!$B$4:$B$5003)=1)*IFERROR(TRADE_LOG!$AE$4:$AE$5003,0)),0) -> 0 | C11: =IFERROR(SUMPRODUCT((YEAR(TRADE_LOG!$B$4:$B$5003)=2026)*(MONTH(TRADE_LOG!$B$4:$B$5003)=2)*IFERROR(TRADE_LOG!$AE$4:$AE$5003,0)),0) -> 0 | D11: =IFERROR(SUMPRODUCT((YEAR(TRADE_LOG!$B$4:$B$5003)=2026)*(MONTH(TRADE_LOG!$B$4:$B$5003)=3)*IFERROR(TRADE_LOG!$AE$4:$AE$5003,0)),0) -> 0 | E11: =IFERROR(SUMPRODUCT((YEAR(TRADE_LOG!$B$4:$B$5003)=2026)*(MONTH(TRADE_LOG!$B$4:$B$5003)=4)*IFERROR(TRADE_LOG!$AE$4:$AE$5003,0)),0) -> 0 | F11: =IFERROR(SUMPRODUCT((YEAR(TRADE_LOG!$B$4:$B$5003)=2026)*(MONTH(TRADE_LOG!$B$4:$B$5003)=5)*IFERROR(TRADE_LOG!$AE$4:$AE$5003,0)),0) -> 0 | G11: =IFERROR(SUMPRODUCT((YEAR(TRADE_LOG!$B$4:$B$5003)=2026)*(MONTH(TRADE_LOG!$B$4:$B$5003)=6)*IFERROR(TRADE_LOG!$AE$4:$AE$5003,0)),0) -> 0 | H11: =IFERROR(SUMPRODUCT((YEAR(TRADE_LOG!$B$4:$B$5003)=2026)*(MONTH(TRADE_LOG!$B$4:$B$5003)=7)*IFERROR(TRADE_LOG!$AE$4:$AE$5003,0)),0) -> 0 | I11: =IFERROR(SUMPRODUCT((YEAR(TRADE_LOG!$B$4:$B$5003)=2026)*(MONTH(TRADE_LOG!$B$4:$B$5003)=8)*IFERROR(TRADE_LOG!$AE$4:$AE$5003,0)),0) -> 0 | J11: =IFERROR(SUMPRODUCT((YEAR(TRADE_LOG!$B$4:$B$5003)=2026)*(MONTH(TRADE_LOG!$B$4:$B$5003)=9)*IFERROR(TRADE_LOG!$AE$4:$AE$5003,0)),0) -> 0 | K11: =IFERROR(SUMPRODUCT((YEAR(TRADE_LOG!$B$4:$B$5003)=2026)*(MONTH(TRADE_LOG!$B$4:$B$5003)=10)*IFERROR(TRADE_LOG!$AE$4:$AE$5003,0)),0) -> 0 | L11: =IFERROR(SUMPRODUCT((YEAR(TRADE_LOG!$B$4:$B$5003)=2026)*(MONTH(TRADE_LOG!$B$4:$B$5003)=11)*IFERROR(TRADE_LOG!$AE$4:$AE$5003,0)),0) -> 0 | M11: =IFERROR(SUMPRODUCT((YEAR(TRADE_LOG!$B$4:$B$5003)=2026)*(MONTH(TRADE_LOG!$B$4:$B$5003)=12)*IFERROR(TRADE_LOG!$AE$4:$AE$5003,0)),0) -> 0 | N11: =SUM(B11:M11) -> 0
A12: 2027 | B12: =IFERROR(SUMPRODUCT((YEAR(TRADE_LOG!$B$4:$B$5003)=2027)*(MONTH(TRADE_LOG!$B$4:$B$5003)=1)*IFERROR(TRADE_LOG!$AE$4:$AE$5003,0)),0) -> 0 | C12: =IFERROR(SUMPRODUCT((YEAR(TRADE_LOG!$B$4:$B$5003)=2027)*(MONTH(TRADE_LOG!$B$4:$B$5003)=2)*IFERROR(TRADE_LOG!$AE$4:$AE$5003,0)),0) -> 0 | D12: =IFERROR(SUMPRODUCT((YEAR(TRADE_LOG!$B$4:$B$5003)=2027)*(MONTH(TRADE_LOG!$B$4:$B$5003)=3)*IFERROR(TRADE_LOG!$AE$4:$AE$5003,0)),0) -> 0 | E12: =IFERROR(SUMPRODUCT((YEAR(TRADE_LOG!$B$4:$B$5003)=2027)*(MONTH(TRADE_LOG!$B$4:$B$5003)=4)*IFERROR(TRADE_LOG!$AE$4:$AE$5003,0)),0) -> 0 | F12: =IFERROR(SUMPRODUCT((YEAR(TRADE_LOG!$B$4:$B$5003)=2027)*(MONTH(TRADE_LOG!$B$4:$B$5003)=5)*IFERROR(TRADE_LOG!$AE$4:$AE$5003,0)),0) -> 0 | G12: =IFERROR(SUMPRODUCT((YEAR(TRADE_LOG!$B$4:$B$5003)=2027)*(MONTH(TRADE_LOG!$B$4:$B$5003)=6)*IFERROR(TRADE_LOG!$AE$4:$AE$5003,0)),0) -> 0 | H12: =IFERROR(SUMPRODUCT((YEAR(TRADE_LOG!$B$4:$B$5003)=2027)*(MONTH(TRADE_LOG!$B$4:$B$5003)=7)*IFERROR(TRADE_LOG!$AE$4:$AE$5003,0)),0) -> 0 | I12: =IFERROR(SUMPRODUCT((YEAR(TRADE_LOG!$B$4:$B$5003)=2027)*(MONTH(TRADE_LOG!$B$4:$B$5003)=8)*IFERROR(TRADE_LOG!$AE$4:$AE$5003,0)),0) -> 0 | J12: =IFERROR(SUMPRODUCT((YEAR(TRADE_LOG!$B$4:$B$5003)=2027)*(MONTH(TRADE_LOG!$B$4:$B$5003)=9)*IFERROR(TRADE_LOG!$AE$4:$AE$5003,0)),0) -> 0 | K12: =IFERROR(SUMPRODUCT((YEAR(TRADE_LOG!$B$4:$B$5003)=2027)*(MONTH(TRADE_LOG!$B$4:$B$5003)=10)*IFERROR(TRADE_LOG!$AE$4:$AE$5003,0)),0) -> 0 | L12: =IFERROR(SUMPRODUCT((YEAR(TRADE_LOG!$B$4:$B$5003)=2027)*(MONTH(TRADE_LOG!$B$4:$B$5003)=11)*IFERROR(TRADE_LOG!$AE$4:$AE$5003,0)),0) -> 0 | M12: =IFERROR(SUMPRODUCT((YEAR(TRADE_LOG!$B$4:$B$5003)=2027)*(MONTH(TRADE_LOG!$B$4:$B$5003)=12)*IFERROR(TRADE_LOG!$AE$4:$AE$5003,0)),0) -> 0 | N12: =SUM(B12:M12) -> 0
A14: R-MULTIPLE DISTRIBUTION
A15: <-3R | B15: -3R to -2R | C15: -2R to -1R | D15: -1R to 0R | E15: 0R to 1R | F15: 1R to 2R | G15: 2R to 3R | H15: >3R
A16: =COUNTIF(TRADE_LOG!$AG$4:$AG$5003,"<-3") -> 0 | B16: =COUNTIFS(TRADE_LOG!$AG$4:$AG$5003,">=-3",TRADE_LOG!$AG$4:$AG$5003,"<-2") -> 0 | C16: =COUNTIFS(TRADE_LOG!$AG$4:$AG$5003,">=-2",TRADE_LOG!$AG$4:$AG$5003,"<-1") -> 0 | D16: =COUNTIFS(TRADE_LOG!$AG$4:$AG$5003,">=-1",TRADE_LOG!$AG$4:$AG$5003,"<0") -> 0 | E16: =COUNTIFS(TRADE_LOG!$AG$4:$AG$5003,">=0",TRADE_LOG!$AG$4:$AG$5003,"<1") -> 0 | F16: =COUNTIFS(TRADE_LOG!$AG$4:$AG$5003,">=1",TRADE_LOG!$AG$4:$AG$5003,"<2") -> 3 | G16: =COUNTIFS(TRADE_LOG!$AG$4:$AG$5003,">=2",TRADE_LOG!$AG$4:$AG$5003,"<3") -> 2 | H16: =COUNTIF(TRADE_LOG!$AG$4:$AG$5003,">=3") -> 0
A18: STREAK & STREAK ANALYSIS
A19: Current Streak: | B19: =IF(TRADE_LOG!AH503="","N/A",COUNTIFS(TRADE_LOG!AH4:AH5003,TRADE_LOG!AH5003)) -> 0 | C19: Last Result: | D19: =IFERROR(LOOKUP(2,1/(TRADE_LOG!AH4:AH5003<>""),TRADE_LOG!AH4:AH5003),"N/A") -> Open | E19: Total Winning Trades: | F19: =COUNTIF(TRADE_LOG!AH4:AH5003,"Win") -> 5 | G19: Total Losing Trades: | H19: =COUNTIF(TRADE_LOG!AH4:AH5003,"Loss") -> 0
A22: EQUITY CURVE DATA (auto-populated from TRADE_LOG)
A23: Trade # | B23: Date | C23: P/L $ | D23: Running Balance
A24: =IF(TRADE_LOG!A4="","",TRADE_LOG!A4) -> 1 | B24: =IF(TRADE_LOG!B4="","",TRADE_LOG!B4) -> 45306 | C24: =IF(TRADE_LOG!AE4="","",TRADE_LOG!AE4) -> 1137.5 | D24: =IF(TRADE_LOG!AO4="","",TRADE_LOG!AO4) -> 51137.5
A25: =IF(TRADE_LOG!A5="","",TRADE_LOG!A5) -> 2 | B25: =IF(TRADE_LOG!B5="","",TRADE_LOG!B5) -> 45307 | C25: =IF(TRADE_LOG!AE5="","",TRADE_LOG!AE5) -> 916.66667 | D25: =IF(TRADE_LOG!AO5="","",TRADE_LOG!AO5) -> 52054.167
A26: =IF(TRADE_LOG!A6="","",TRADE_LOG!A6) -> 3 | B26: =IF(TRADE_LOG!B6="","",TRADE_LOG!B6) -> 45308 | C26: =IF(TRADE_LOG!AE6="","",TRADE_LOG!AE6) -> 1795 | D26: =IF(TRADE_LOG!AO6="","",TRADE_LOG!AO6) -> 53849.167
A27: =IF(TRADE_LOG!A7="","",TRADE_LOG!A7) -> 4 | B27: =IF(TRADE_LOG!B7="","",TRADE_LOG!B7) -> 45309 | C27: =IF(TRADE_LOG!AE7="","",TRADE_LOG!AE7) -> 618.81188 | D27: =IF(TRADE_LOG!AO7="","",TRADE_LOG!AO7) -> 54467.979
A28: =IF(TRADE_LOG!A8="","",TRADE_LOG!A8) -> 5 | B28: =IF(TRADE_LOG!B8="","",TRADE_LOG!B8) -> 45313 | C28: =IF(TRADE_LOG!AE8="","",TRADE_LOG!AE8) -> 750 | D28: =IF(TRADE_LOG!AO8="","",TRADE_LOG!AO8) -> 55217.979
A29: =IF(TRADE_LOG!A9="","",TRADE_LOG!A9) | B29: =IF(TRADE_LOG!B9="","",TRADE_LOG!B9) | C29: =IF(TRADE_LOG!AE9="","",TRADE_LOG!AE9) | D29: =IF(TRADE_LOG!AO9="","",TRADE_LOG!AO9)
A30: =IF(TRADE_LOG!A10="","",TRADE_LOG!A10) | B30: =IF(TRADE_LOG!B10="","",TRADE_LOG!B10) | C30: =IF(TRADE_LOG!AE10="","",TRADE_LOG!AE10) | D30: =IF(TRADE_LOG!AO10="","",TRADE_LOG!AO10)
A31: =IF(TRADE_LOG!A11="","",TRADE_LOG!A11) | B31: =IF(TRADE_LOG!B11="","",TRADE_LOG!B11) | C31: =IF(TRADE_LOG!AE11="","",TRADE_LOG!AE11) | D31: =IF(TRADE_LOG!AO11="","",TRADE_LOG!AO11)
A32: =IF(TRADE_LOG!A12="","",TRADE_LOG!A12) | B32: =IF(TRADE_LOG!B12="","",TRADE_LOG!B12) | C32: =IF(TRADE_LOG!AE12="","",TRADE_LOG!AE12) | D32: =IF(TRADE_LOG!AO12="","",TRADE_LOG!AO12)
A33: =IF(TRADE_LOG!A13="","",TRADE_LOG!A13) | B33: =IF(TRADE_LOG!B13="","",TRADE_LOG!B13) | C33: =IF(TRADE_LOG!AE13="","",TRADE_LOG!AE13) | D33: =IF(TRADE_LOG!AO13="","",TRADE_LOG!AO13)
A34: =IF(TRADE_LOG!A14="","",TRADE_LOG!A14) | B34: =IF(TRADE_LOG!B14="","",TRADE_LOG!B14) | C34: =IF(TRADE_LOG!AE14="","",TRADE_LOG!AE14) | D34: =IF(TRADE_LOG!AO14="","",TRADE_LOG!AO14)
A35: =IF(TRADE_LOG!A15="","",TRADE_LOG!A15) | B35: =IF(TRADE_LOG!B15="","",TRADE_LOG!B15) | C35: =IF(TRADE_LOG!AE15="","",TRADE_LOG!AE15) | D35: =IF(TRADE_LOG!AO15="","",TRADE_LOG!AO15)
... A123: =IF(TRADE_LOG!A103="","",TRADE_LOG!A103) | B123: =IF(TRADE_LOG!B103="","",TRADE_LOG!B103) | C123: =IF(TRADE_LOG!AE103="","",TRADE_LOG!AE103) | D123: =IF(TRADE_LOG!AO103="","",TRADE_LOG!AO103)

Sheet TRADE_REVIEW
A1: 🔍 TRADE REVIEW — Lookup & Analyse Individual Trades
A3: Enter Trade ID to Review: | D3: 1
A5: Trade ID | D5: =IFERROR(INDEX(TRADE_LOG!A4:A5003,MATCH($D$3,TRADE_LOG!A4:A5003,0)),"Not Found") -> 1
A6: Date Opened | D6: =IFERROR(INDEX(TRADE_LOG!B4:B5003,MATCH($D$3,TRADE_LOG!A4:A5003,0)),"") -> 45306
A7: Pair | D7: =IFERROR(INDEX(TRADE_LOG!E4:E5003,MATCH($D$3,TRADE_LOG!A4:A5003,0)),"") -> EUR/USD
A8: Direction | D8: =IFERROR(INDEX(TRADE_LOG!F4:F5003,MATCH($D$3,TRADE_LOG!A4:A5003,0)),"") -> Buy
A9: Strategy | D9: =IFERROR(INDEX(TRADE_LOG!H4:H5003,MATCH($D$3,TRADE_LOG!A4:A5003,0)),"") -> Trend Follow
A10: Entry Price | D10: =IFERROR(INDEX(TRADE_LOG!K4:K5003,MATCH($D$3,TRADE_LOG!A4:A5003,0)),"") -> 1.0852
A11: Stop Loss | D11: =IFERROR(INDEX(TRADE_LOG!L4:L5003,MATCH($D$3,TRADE_LOG!A4:A5003,0)),"") -> 1.0832
A12: Lot Size | D12: =IFERROR(INDEX(TRADE_LOG!R4:R5003,MATCH($D$3,TRADE_LOG!A4:A5003,0)),"") -> 2.5
A13: Wt Avg Exit | D13: =IFERROR(INDEX(TRADE_LOG!AD4:AD5003,MATCH($D$3,TRADE_LOG!A4:A5003,0)),"") -> 1.08975
A14: Total P/L $ | D14: =IFERROR(INDEX(TRADE_LOG!AE4:AE5003,MATCH($D$3,TRADE_LOG!A4:A5003,0)),"") -> 1137.5
A15: R-Multiple | D15: =IFERROR(INDEX(TRADE_LOG!AG4:AG5003,MATCH($D$3,TRADE_LOG!A4:A5003,0)),"") -> 2.275
A16: Result | D16: =IFERROR(INDEX(TRADE_LOG!AH4:AH5003,MATCH($D$3,TRADE_LOG!A4:A5003,0)),"") -> Win
A17: Trade Duration | D17: =IFERROR(INDEX(TRADE_LOG!AI4:AI5003,MATCH($D$3,TRADE_LOG!A4:A5003,0)),"") -> 0
A18: Pips P/L | D18: =IFERROR(INDEX(TRADE_LOG!AJ4:AJ5003,MATCH($D$3,TRADE_LOG!A4:A5003,0)),"") -> 45.5
A19: Notes | D19: =IFERROR(INDEX(TRADE_LOG!AK4:AK5003,MATCH($D$3,TRADE_LOG!A4:A5003,0)),"") -> Clean breakout setup
A20: Mistakes | D20: =IFERROR(INDEX(TRADE_LOG!AM4:AM5003,MATCH($D$3,TRADE_LOG!A4:A5003,0)),"") -> 0
A21: Emotion Score | D21: =IFERROR(INDEX(TRADE_LOG!AN4:AN5003,MATCH($D$3,TRADE_LOG!A4:A5003,0)),"") -> 7
